Workbook

Sheet Modelo financiero
K1: Decisiones financieras estratégicas
K2: Especialización en Ingeniería Financiera
K3: Proyecto final - Valor de las acciones de Chedraui
K4: Fajardo Aguilar Daniel
K5: Mayo de 2023
B7: Modelo financiero Chedraui
B8: Periodo | C8: =D8-1 -> -7 | D8: =E8-1 -> -6 | E8: =F8-1 -> -5 | F8: =G8-1 -> -4 | G8: =H8-1 -> -3 | H8: =I8-1 -> -2 | I8: =J8-1 -> -1 | J8: =K8-1 -> 0 | K8: 1 | L8: =K8+1 -> 2 | M8: =L8+1 -> 3 | N8: =M8+1 -> 4 | O8: =N8+1 -> 5 | P8: =O8+1 -> 6 | Q8: =P8+1 -> 7 | R8: =Q8+1 -> 8 | S8: =R8+1 -> 9 | ... Y8: =X8+1 -> 15 | Z8: n
B9: Concepto | C9: ='Estado de resultados'!C31 -> 2015 | D9: ='Estado de resultados'!D31 -> 2016 | E9: ='Estado de resultados'!E31 -> 2017 | F9: ='Estado de resultados'!F31 -> 2018 | G9: ='Estado de resultados'!G31 -> 2019 | H9: ='Estado de resultados'!H31 -> 2020 | I9: ='Estado de resultados'!I31 -> 2021 | J9: ='Estado de resultados'!J31 -> 2022 | K9: 2023 | L9: =K9+1 -> 2024 | M9: =L9+1 -> 2025 | N9: =M9+1 -> 2026 | O9: =N9+1 -> 2027 | P9: =O9+1 -> 2028 | Q9: =P9+1 -> 2029 | R9: =Q9+1 -> 2030 | S9: =R9+1 -> 2031 | ... Y9: =X9+1 -> 2037
B10: Ingresos | C10: ='Estado de resultados'!C32 -> 117861.89 | D10: ='Estado de resultados'!D32 -> 128579.52 | E10: ='Estado de resultados'!E32 -> 129124.71 | F10: ='Estado de resultados'!F32 -> 151524.88 | G10: ='Estado de resultados'!G32 -> 164664.44 | H10: =Información!C9 -> 180766.85 | I10: =Información!D9 -> 203226.68 | J10: =Información!E9 -> 259326 | K10: =Información!F9 -> 275920.33 | L10: =Información!G9 -> 293612.1 | M10: =Información!H9 -> 312476.74 | N10: =Información!I9 -> 332595.14 | O10: =Información!J9 -> 354054.05 | ... Y10: =Información!T9 -> 644061.05 | Z10: 644061.05
B11: Costos | C11: ='Estado de resultados'!C33+'Estado de resultados'!C35 -> 112348.54 | D11: ='Estado de resultados'!D33+'Estado de resultados'!D35 -> 122399.56 | E11: ='Estado de resultados'!E33+'Estado de resultados'!E35 -> 123091.89 | F11: ='Estado de resultados'!F33+'Estado de resultados'!F35 -> 144783.83 | G11: ='Estado de resultados'!G33+'Estado de resultados'!G35 -> 157571.21 | H11: =Información!C17 -> 172199.74 | I11: =Información!D17 -> 193794.59 | J11: =Información!E17 -> 245580 | K11: =Información!F17 -> 262954.19 | L11: =Información!G17 -> 279814.58 | M11: =Información!H17 -> 297792.73 | N11: =Información!I17 -> 316965.72 | O11: =Información!J17 -> 337416.22 | ... Y11: =Información!T17 -> 613795.12 | Z11: 613795.12
B12: Utilidad Bruta | C12: =C10-C11 -> 5513.3494 | D12: =D10-D11 -> 6179.962 | E12: =E10-E11 -> 6032.8188 | F12: =F10-F11 -> 6741.0558 | G12: =G10-G11 -> 7093.2296 | H12: =H10-H11 -> 8567.1081 | I12: =I10-I11 -> 9432.0936 | J12: =J10-J11 -> 13746 | ... Y12: =Y10-Y11 -> 30265.936 | Z12: 30265.936
C13: =C12/C10 -> 0.046778049 | D13: =D12/D10 -> 0.048063346 | E13: =E12/E10 -> 0.04672087 | F13: =F12/F10 -> 0.044488111 | G13: =G12/G10 -> 0.043076876 | H13: =H12/H10 -> 0.047393138 | I13: =I12/I10 -> 0.046411689 | J13: =J12/J10 -> 0.05300664
B14: Depreciación | C14: ='Flujo de efectivo'!C10 -> 1982.3915 | D14: ='Flujo de efectivo'!D10 -> 2218.6165 | E14: ='Flujo de efectivo'!E10 -> 2234.3218 | F14: ='Flujo de efectivo'!F10 -> 3986.5314 | G14: ='Flujo de efectivo'!G10 -> 4516.0326 | H14: ='Flujo de efectivo'!H10 -> 4694.2439 | I14: ='Flujo de efectivo'!I10 -> 5822.5366 | J14: ='Flujo de efectivo'!J10 -> 7680.74 | K14: =AVERAGE($C$14:$J$14) -> 4141.9268 | L14: =AVERAGE($C$14:$J$14) -> 4141.9268 | M14: =AVERAGE($C$14:$J$14) -> 4141.9268 | N14: =AVERAGE($C$14:$J$14) -> 4141.9268 | O14: =AVERAGE($C$14:$J$14) -> 4141.9268 | P14: =AVERAGE($C$14:$J$14) -> 4141.9268 | Q14: =AVERAGE($C$14:$J$14) -> 4141.9268 | R14: =AVERAGE($C$14:$J$14) -> 4141.9268 | ... Y14: =AVERAGE($C$14:$J$14) -> 4141.9268 | Z14: 4141.9268
B15: Utilidad antes de impuestos | C15: ='Flujo de efectivo'!C8 -> 3955.0931 | D15: ='Flujo de efectivo'!D8 -> 4462.9202 | E15: ='Flujo de efectivo'!E8 -> 4419.8978 | F15: ='Flujo de efectivo'!F8 -> 3179.527 | G15: ='Flujo de efectivo'!G8 -> 3135.8792 | H15: ='Flujo de efectivo'!H8 -> 4630.8475 | I15: ='Flujo de efectivo'!I8 -> 5336.5779 | J15: ='Flujo de efectivo'!J8 -> 8722.151 | K15: =K12-K14 -> 8824.2153 | L15: =L12-L14 -> 9655.5927 | M15: =M12-M14 -> 10542.086 | N15: =N12-N14 -> 11487.497 | O15: =O12-O14 -> 12495.902 | P15: =P12-P14 -> 13496.494 | Q15: =Q12-Q14 -> 14563.326 | R15: =R12-R14 -> 15701.08 | ... Y15: =Y12-Y14 -> 26124.009 | Z15: 26124.009
B16: Impuestos | C16: ='Estado de resultados'!C44 -> 1273.81 | D16: ='Estado de resultados'!D44 -> 1543.9012 | E16: ='Estado de resultados'!E44 -> 1529.024 | F16: ='Estado de resultados'!F44 -> 1107.4032 | G16: ='Estado de resultados'!G44 -> 1180.5088 | H16: ='Estado de resultados'!H44 -> 1325.9061 | I16: ='Estado de resultados'!I44 -> 1583.8758 | J16: ='Estado de resultados'!J44 -> 2546 | K16: =Información!D53 -> 3268.0261 | L16: =Información!E53 -> 3597.5106 | M16: =Información!F53 -> 3927.1667 | N16: =Información!G53 -> 4278.7362 | O16: =Información!H53 -> 4653.7357 | P16: =Información!I53 -> 5023.7206 | Q16: =Información!J53 -> 5420.4355 | R16: =Información!K53 -> 5843.5324 | ... Y16: =Información!R53 -> 9719.8189 | Z16: 9719.8189
B17: Utilidad después de impuestos (Utilidad Neta) | C17: ='Estado de resultados'!C45 -> 2682.494 | D17: ='Estado de resultados'!D45 -> 2919.324 | E17: ='Estado de resultados'!E45 -> 2890.1284 | F17: ='Estado de resultados'!F45 -> 2071.1574 | G17: ='Estado de resultados'!G45 -> 1955.2177 | H17: ='Estado de resultados'!H45 -> 3304.2618 | I17: ='Estado de resultados'!I45 -> 3752.136 | J17: ='Estado de resultados'!J45 -> 6176 | K17: =K15-K16 -> 5556.1892 | L17: =L15-L16 -> 6058.0821 | M17: =M15-M16 -> 6614.9195 | N17: =N15-N16 -> 7208.7608 | O17: =O15-O16 -> 7842.1659 | P17: =P15-P16 -> 8472.7735 | Q17: =Q15-Q16 -> 9142.8903 | R17: =R15-R16 -> 9857.548 | ... Y17: =Y15-Y16 -> 16404.19 | Z17: 16404.19
B18: Inversiones | C18: ='Flujo de efectivo'!C40 -> -4098.3338 | D18: ='Flujo de efectivo'!D40 -> -4877.1519 | E18: ='Flujo de efectivo'!E40 -> -4223.2175 | F18: ='Flujo de efectivo'!F40 -> -11544.304 | G18: ='Flujo de efectivo'!G40 -> -3618.9006 | H18: ='Flujo de efectivo'!H40 -> -3133.7772 | I18: ='Flujo de efectivo'!I40 -> -16843.257 | J18: ='Flujo de efectivo'!J40 -> -6480.844 | K18: =K10*1% -> 2759.2033 | L18: =L10*1% -> 2936.121 | M18: =M10*1% -> 3124.7674 | N18: =N10*1% -> 3325.9514 | O18: =O10*1% -> 3540.5405 | P18: =P10*1% -> 3753.4673 | Q18: =Q10*1% -> 3980.4897 | R18: =R10*1% -> 4222.6046 | ... Y18: =Y10*1% -> 6440.6105 | Z18: 6440.6105
B19: Depreciación | C19: =C14 -> 1982.3915 | D19: =D14 -> 2218.6165 | E19: =E14 -> 2234.3218 | F19: =F14 -> 3986.5314 | G19: =G14 -> 4516.0326 | H19: =H14 -> 4694.2439 | I19: =I14 -> 5822.5366 | J19: =J14 -> 7680.74 | ... Y19: =Y14 -> 4141.9268 | Z19: 4141.9268
B20: Capital de trabajo | C20: ='Balance general'!C68-'Balance general'!C90 -> -9354.2612 | D20: ='Balance general'!D68-'Balance general'!D90 -> -8466.0396 | E20: ='Balance general'!E68-'Balance general'!E90 -> -6406.8836 | F20: ='Balance general'!F68-'Balance general'!F90 -> -7433.1828 | G20: ='Balance general'!G68-'Balance general'!G90 -> -8103.277 | H20: ='Balance general'!H68-'Balance general'!H90 -> -7994.979 | I20: ='Balance general'!I68-'Balance general'!I90 -> -6800.2074 | J20: ='Balance general'!J68-'Balance general'!J90 -> -5446 | K20: =Información!D62 -> -1351.694 | L20: =Información!E62 -> -1441.0856 | M20: =Información!F62 -> -1536.6223 | N20: =Información!G62 -> -1638.7477 | O20: =Información!H62 -> -1747.9392 | P20: =Información!I62 -> -1734.3981 | Q20: =Información!J62 -> -1849.2152 | R20: =Información!K62 -> -1972.1508 | ... Y20: =Información!R62 -> -3116.3455 | Z20: -3116.3455
B21: Flujo disponible para el servicio de la deuda | C21: =C17-C18+C19+C20 -> -591.04185 | D21: =D17-D18+D19+D20 -> 1549.0529 | E21: =E17-E18+E19+E20 -> 2940.7841 | F21: =F17-F18+F19+F20 -> 10168.81 | G21: =G17-G18+G19+G20 -> 1986.8739 | H21: =H17-H18+H19+H20 -> 3137.3039 | I21: =I17-I18+I19+I20 -> 19617.722 | J21: =J17-J18+J19+J20 -> 14891.584 | ... Y21: =Y17-Y18+Y19+Y20 -> 10989.161 | Z21: 10989.161
B22: Servicio de la deuda | J22: =Información!C44 -> 12652.687 | K22: =Información!D44 -> 9467.3283 | L22: =Información!E44 -> 6060.2048 | M22: =Información!F44 -> 2415.8719 | N22: =AVERAGE($J$22:$M$22) -> 7649.0231 | O22: =AVERAGE($J$22:$M$22) -> 7649.0231 | P22: =AVERAGE($J$22:$M$22) -> 7649.0231 | Q22: =AVERAGE($J$22:$M$22) -> 7649.0231 | R22: =AVERAGE($J$22:$M$22) -> 7649.0231 | S22: =AVERAGE($J$22:$M$22) -> 7649.0231 | T22: =AVERAGE($J$22:$M$22) -> 7649.0231 | U22: =AVERAGE($J$22:$M$22) -> 7649.0231 | ... Y22: =AVERAGE($J$22:$M$22) -> 7649.0231 | Z22: 7649.0231
B23: Valor de rescate | Y23: =Z21/L35 -> 111193.76
B26: Flujo de Efectivo Libre | C26: =C17-C18+C19+C20 -> -591.04185 | D26: =D17-D18+D19+D20 -> 1549.0529 | E26: =E17-E18+E19+E20 -> 2940.7841 | F26: =F17-F18+F19+F20 -> 10168.81 | G26: =G17-G18+G19+G20 -> 1986.8739 | H26: =H17-H18+H19+H20 -> 3137.3039 | I26: =I17-I18+I19+I20 -> 19617.722 | J26: =J17-J18+J19+J20 -> 14891.584 | K26: =K17-K18+K19+K20 -> 5587.2186 | L26: =L21-L22 -> -237.40251 | M26: =M21-M22 -> 3679.5848 | N26: =N21-N22 -> -1263.0346 | O26: =O21-O22 -> -953.4101 | P26: =P21-P22 -> -522.18811 | Q26: =Q21-Q22 -> -193.91087 | R26: =R21-R22 -> 155.69631 | S26: =S21-S22 -> 528.12334 | ... X26: =X21-X22 -> 2792.7992 | Y26: =Y21-Y22+Y23 -> 114533.9 | Z26: =Z21-Z22 -> 3340.1378
B28: Flujo de Efectivo Libre Descontado | K28: =K26/((1+$L$35)^K8) -> 5084.7028 | L28: =L26/((1+$L$35)^L8) -> -196.61884 | M28: =M26/((1+$L$35)^M8) -> 2773.3747 | N28: =N26/((1+$L$35)^N8) -> -866.35301 | O28: =O26/((1+$L$35)^O8) -> -595.15394 | P28: =P26/((1+$L$35)^P8) -> -296.65144 | Q28: =Q26/((1+$L$35)^Q8) -> -100.25165 | R28: =R26/((1+$L$35)^R8) -> 73.255058 | ... Y28: =Y26/((1+$L$35)^Y8) -> 27860.105
B29: Flujo de Efectivo Libre Descontado Acumulado | K29: =K28 -> 5084.7028 | L29: =K29+L28 -> 4888.084 | M29: =L29+M28 -> 7661.4587 | N29: =M29+N28 -> 6795.1057 | O29: =N29+O28 -> 6199.9518 | P29: =O29+P28 -> 5903.3003 | Q29: =P29+Q28 -> 5803.0487 | R29: =Q29+R28 -> 5876.3037 | S29: =R29+S28 -> 6102.4371 | ... Y29: =X29+Y28 -> 36797.622
K32: RESULTADOS | O32: WACC | P32: =(P33*P34)+(P35*P36)*(1-P37) -> 0.098828934
K33: Valor del Negocio (VPN) | L33: =SUM(K28:Y28) -> 36797.622 | O33: Porcentaje de Capital | P33: 0.70123791
O34: Costo de capital | P34: 0.11200251
K35: Tasa de descuento | L35: =P32 -> 0.098828934 | O35: Porcentaje de Deuda | P35: =1-P33 -> 0.29876209
N36: 8.5 | O36: Costo de la Deuda | P36: 0.097012361
K37: Pasivos financieros (-) | L37: ='Balance general'!J101 -> 104071 | M37: Cost of equity Damodaran | O37: Tasa tributaria | P37: 0.3
K38: Pasivos Laborales (-)
K39: Pasivos contingentes (-)
K40: Tesoreria (+) | L40: ='Balance general'!J68 -> 37695 | M40: activo circulante
K41: Valor de la empresa | L41: =L33-L37-L38-L39+L40 -> -29578.378
K42: No. de acciones en circulación | L42: 963917211
K43: Precio de la acción | L43: =(L41*10^6)/L42 -> -30.6856
O57: Escenario | P57: Valor del negocio | Q57: Precio acción
O58: Base | P58: 36797.622 | Q58: -30.6856
O59: Tasa de descuento = 7.5% | P59: 60617.44 | Q59: -5.9741231
O60: Incremento anual en ingresos constante durante los 15 años | P60: 37254.984 | Q60: -30.211117
O61: Ingresos totales incrementan en 10% al año durante los primeros 5 años | P61: 46530.576 | Q61: -20.588308

Sheet Chedraui
B3: Tiendas en México | E3: Tiendas en Estados Unidos | L3: FORTALEZAS | Q3: OPORTUNIDADES
B4: 205 | C4: Chedraui | E4: 64 | F4: El Super
B5: 75 | C5: Súper Chedraui | E5: 59 | F5: Fiesta | L5: Estrategia de precios bajos. Productos de fabricantes líderes. Empresa líder mexicana de tiendas de autoservicio. Experiencia de compra. | Q5: Expandir la red de tiendas de autoservicio. Estructura organizacional sólida. Nuevos productos de marca propia. Campañas de descuentos/promociones.
B6: 8 | C6: Súper Che | E6: 253 | F6: Smart & Final
B7: 80 | C7: Supercito | E7: =SUM(E4:E6) -> 376
B8: 36 | C8: Arteli
B9: =SUM(B4:B8) -> 404
L13: AMENAZAS | Q13: DEBILIDADES
L15: Mercado altamente competitivo. Negocio altamente dependiente de las economías de México y de Estados Unidos. Ataques cibernéticos. Vencimiento anticipado de créditos. | Q15: Dificultades para obtener mercancía de suficiente calidad a bajo costo. Incapacidad de reaccionar a cambios en la demanda del consumidor. Imposibilidad de mantener relaciones con los sindicatos.

Sheet Información
D1: Incremento anual en ingresos de EUA: | E1: 0.055 | G1: Incremento anual en semento inmobiliario: | H1: =E8/D8-1 -> 0.14388178
D2: Incremento anual en ingresos de México: | E2: =E6/D6-1 -> 0.076285616 | G2: Relación Utilidad/Ingresos | H2: =AVERAGE('Modelo financiero'!$C$13:$J$13) -> 0.04699234 | I2: ='Estado de resultados'!$T$34 -> 0.21416988
B3: Ingresos
B4: ='Modelo financiero'!B8 -> Periodo | C4: ='Modelo financiero'!H8 -> -2 | D4: ='Modelo financiero'!I8 -> -1 | E4: ='Modelo financiero'!J8 -> 0 | F4: ='Modelo financiero'!K8 -> 1 | G4: ='Modelo financiero'!L8 -> 2 | H4: ='Modelo financiero'!M8 -> 3 | I4: ='Modelo financiero'!N8 -> 4 | J4: ='Modelo financiero'!O8 -> 5 | ... T4: ='Modelo financiero'!Y8 -> 15
B5: Ingresos por segmento | C5: ='Modelo financiero'!H9 -> 2020 | D5: ='Modelo financiero'!I9 -> 2021 | E5: ='Modelo financiero'!J9 -> 2022 | F5: ='Modelo financiero'!K9 -> 2023 | G5: ='Modelo financiero'!L9 -> 2024 | H5: ='Modelo financiero'!M9 -> 2025 | I5: ='Modelo financiero'!N9 -> 2026 | J5: ='Modelo financiero'!O9 -> 2027 | ... T5: ='Modelo financiero'!Y9 -> 2037
B6: Operaciones en México | C6: ='Estado de resultados'!H87 -> 101989.74 | D6: ='Estado de resultados'!I87 -> 97316.176 | E6: ='Estado de resultados'!J87 -> 104740 | F6: =E6*(1+$E$2) -> 112730.16 | G6: =F6*(1+$E$2) -> 121329.84 | H6: =G6*(1+$E$2) -> 130585.57 | I6: =H6*(1+$E$2) -> 140547.37 | J6: =I6*(1+$E$2) -> 151269.11 | K6: =J6*(1+$E$2/2) -> 157038.94 | L6: =K6*(1+$E$2/2) -> 163028.84 | M6: =L6*(1+$E$2/2) -> 169247.22 | N6: =M6*(1+$E$2/2) -> 175702.79 | O6: =N6*(1+$E$2/2) -> 182404.58 | P6: =O6*(1+$E$2/2) -> 189362.01 | Q6: =P6*(1+$E$2/2) -> 196584.81 | R6: =Q6*(1+$E$2/2) -> 204083.1 | ... T6: =S6*(1+$E$2/2) -> 219948.62
B7: Operaciones en Estados Unidos | C7: ='Estado de resultados'!H88 -> 77724.294 | D7: ='Estado de resultados'!I88 -> 104907.78 | E7: ='Estado de resultados'!J88 -> 153439 | F7: =E7*(1+$E$1) -> 161878.14 | G7: =F7*(1+$E$1) -> 170781.44 | H7: =G7*(1+$E$1) -> 180174.42 | I7: =H7*(1+$E$1) -> 190084.02 | J7: =I7*(1+$E$1) -> 200538.64 | K7: =J7*(1+$E$2) -> 215836.85 | L7: =K7*(1+$E$2) -> 232302.1 | M7: =L7*(1+$E$2) -> 250023.41 | N7: =M7*(1+$E$2) -> 269096.59 | O7: =N7*(1+$E$2) -> 289624.79 | P7: =O7*(1+$E$2) -> 311719 | Q7: =P7*(1+$E$2) -> 335498.68 | R7: =Q7*(1+$E$2) -> 361092.4 | ... T7: =S7*(1+$E$2) -> 418286.09
B8: Segmento inmobiliario | C8: ='Estado de resultados'!H89 -> 1052.8164 | D8: ='Estado de resultados'!I89 -> 1002.726 | E8: ='Estado de resultados'!J89 -> 1147 | F8: =E8*(1+$H$1) -> 1312.0324 | G8: =F8*(1+$H$1) -> 1500.81 | H8: =G8*(1+$H$1) -> 1716.7492 | I8: =H8*(1+$H$1) -> 1963.7581 | J8: =I8*(1+$H$1) -> 2246.3071 | K8: =J8*(1+10%) -> 2470.9378 | L8: =K8*(1+10%) -> 2718.0316 | M8: =L8*(1+10%) -> 2989.8347 | N8: =M8*(1+10%) -> 3288.8182 | O8: =N8*(1+10%) -> 3617.7 | P8: =O8*(1+10%) -> 3979.47 | Q8: =P8*(1+10%) -> 4377.417 | R8: =Q8*(1+10%) -> 4815.1587 | ... T8: =S8*(1+10%) -> 5826.3421
B9: Total de ingresos | C9: =SUM(C6:C8) -> 180766.85 | D9: =SUM(D6:D8) -> 203226.68 | E9: =SUM(E6:E8) -> 259326 | F9: =SUM(F6:F8) -> 275920.33 | G9: =SUM(G6:G8) -> 293612.1 | H9: =SUM(H6:H8) -> 312476.74 | I9: =SUM(I6:I8) -> 332595.14 | J9: =SUM(J6:J8) -> 354054.05 | ... T9: =SUM(T6:T8) -> 644061.05
B12: Costos
B13: =B4 -> Periodo | C13: =C4 -> -2 | D13: =D4 -> -1 | E13: =E4 -> 0 | F13: =F4 -> 1 | G13: =G4 -> 2 | H13: =H4 -> 3 | I13: =I4 -> 4 | ... T13: =T4 -> 15
C14: =C5 -> 2020 | D14: =D5 -> 2021 | E14: =E5 -> 2022 | F14: =F5 -> 2023 | G14: =G5 -> 2024 | H14: =H5 -> 2025 | I14: =I5 -> 2026 | J14: =J5 -> 2027 | ... T14: =T5 -> 2037
B15: Gastos de operación | C15: ='Estado de resultados'!H35 -> 31443.622 | D15: ='Estado de resultados'!I35 -> 35800.553 | E15: ='Estado de resultados'!J35 -> 45554 | F15: =F17-F16 -> 52590.838 | G15: =G17-G16 -> 55962.916 | H15: =H17-H16 -> 59558.545 | I15: =I17-I16 -> 63393.143 | J15: =J17-J16 -> 67483.245 | K15: =K17-K16 -> 71541.661 | L15: =L17-L16 -> 75868.744 | M15: =M17-M16 -> 80483.491 | ... T15: =T17-T16 -> 122759.02
B16: Costo de ventas | C16: ='Estado de resultados'!H33 -> 140756.12 | D16: ='Estado de resultados'!I33 -> 157994.04 | E16: ='Estado de resultados'!J33 -> 200026 | F16: =F17*0.8 -> 210363.35 | G16: =G17*0.8 -> 223851.66 | H16: =H17*0.8 -> 238234.18 | I16: =I17*0.8 -> 253572.57 | J16: =J17*0.8 -> 269932.98 | K16: =K17*0.8 -> 286166.64 | L16: =L17*0.8 -> 303474.98 | M16: =M17*0.8 -> 321933.96 | ... T16: =T17*0.8 -> 491036.09
B17: Total de costos | C17: =SUM(C15:C16) -> 172199.74 | D17: =SUM(D15:D16) -> 193794.59 | E17: =SUM(E15:E16) -> 245580 | F17: =F9*(1-$H$2) -> 262954.19 | G17: =G9*(1-$H$2) -> 279814.58 | H17: =H9*(1-$H$2) -> 297792.73 | I17: =I9*(1-$H$2) -> 316965.72 | J17: =J9*(1-$H$2) -> 337416.22 | K17: =K9*(1-$H$2) -> 357708.3 | L17: =L9*(1-$H$2) -> 379343.72 | M17: =M9*(1-$H$2) -> 402417.46 | ... T17: =T9*(1-$H$2) -> 613795.12
C21: Crédito 1 | D21: =620*10^6 -> 620000000 | F21: Crédito 2 | G21: =200*10^6 -> 200000000
C22: n | D22: 5 | F22: n | G22: 4
C23: i | D23: 0.0155 | F23: i | G23: 0.0125
C24: Tasa deuda | D24: =D23+D27 -> 0.0705 | F24: Tasa deuda | G24: =G23+D27 -> 0.0675
C25: R | D25: =PMT(D24,D22,-D21) -> 1.5141472e+08 | F25: R | G25: =PMT(G24,G22,-G21) -> 58712734
C27: LIBOR | D27: 0.055 | F27: Tipo de cambio USD | G27: 19.3615
B29: Deuda largo plazo
B30: Periodo | C30: =E4 -> 0 | D30: =F4 -> 1 | E30: =G4 -> 2 | F30: =H4 -> 3 | G30: =I4 -> 4
B31: Amortización 1 | C31: =E5 -> 2022 | D31: =F5 -> 2023 | E31: =G5 -> 2024 | F31: =H5 -> 2025 | G31: =I5 -> 2026
B32: Saldo inicial | C32: =D21 -> 620000000 | D32: =C36 -> 498710000 | E32: =D36 -> 3.8245433e+08 | F32: =E36 -> 2.5800264e+08 | G32: =F36 -> 1.247771e+08
B33: Pago total | C33: =165*10^6 -> 165000000 | D33: =$D$25 -> 1.5141472e+08 | E33: =$D$25 -> 1.5141472e+08 | F33: =$D$25 -> 1.5141472e+08 | G33: =G32+G34 -> 1.3357389e+08
B34: Intereses | C34: =C32*$D$24 -> 43710000 | D34: =D32*$D$24 -> 35159055 | E34: =E32*$D$24 -> 26963030 | F34: =F32*$D$24 -> 18189186 | G34: =G32*$D$24 -> 8796785.7
B35: Capital | C35: =C33-C34 -> 121290000 | D35: =D33-D34 -> 1.1625567e+08 | E35: =E33-E34 -> 1.2445169e+08 | F35: =F33-F34 -> 1.3322554e+08 | G35: =G33-G34 -> 1.247771e+08
B36: Saldo final | C36: =C32-C35 -> 498710000 | D36: =D32-D35 -> 3.8245433e+08 | E36: =E32-E35 -> 2.5800264e+08 | F36: =F32-F35 -> 1.247771e+08 | G36: =G32-G35 -> 0
B37: Amortización 2 | C37: =C31 -> 2022 | D37: =D31 -> 2023 | E37: =E31 -> 2024 | F37: =F31 -> 2025 | G37: =G31 -> 2026
B38: Saldo inicial | C38: =G21 -> 200000000 | D38: =C42 -> 1.5478727e+08 | E38: =D42 -> 1.0652267e+08 | F38: =E42 -> 55000219 | G38: 0
B39: Pago total | C39: =$G$25 -> 58712734 | D39: =$G$25 -> 58712734 | E39: =$G$25 -> 58712734 | F39: =$G$25 -> 58712734 | G39: 0
B40: Intereses | C40: =C38*$G$24 -> 13500000 | D40: =D38*$G$24 -> 10448140 | E40: =E38*$G$24 -> 7190280.4 | F40: =F38*$G$24 -> 3712514.8 | G40: 0
B41: Capital | C41: =C39-C40 -> 45212734 | D41: =D39-D40 -> 48264593 | E41: =E39-E40 -> 51522454 | F41: =F39-F40 -> 55000219 | G41: 0
B42: Saldo final | C42: =C38-C41 -> 1.5478727e+08 | D42: =D38-D41 -> 1.0652267e+08 | E42: =E38-E41 -> 55000219 | F42: =F38-F41 -> 0 | G42: 0
B43: Millones Deuda total, USD | C43: =(C36+C42)/(10^6) -> 653.49727 | D43: =(D36+D42)/(10^6) -> 488.977 | E43: =(E36+E42)/(10^6) -> 313.00286 | F43: =(F36+F42)/(10^6) -> 124.7771 | G43: =(G36+G42)/(10^6) -> 0
B44: Millones Deuda total, MXN | C44: =C43*$G$27 -> 12652.687 | D44: =D43*$G$27 -> 9467.3283 | E44: =E43*$G$27 -> 6060.2048 | F44: =F43*$G$27 -> 2415.8719 | G44: =G43*$G$27 -> 0
B46: Impuestos
C47: =E4 -> 0 | D47: =F4 -> 1 | E47: =G4 -> 2 | F47: =H4 -> 3 | G47: =I4 -> 4 | H47: =J4 -> 5 | I47: =K4 -> 6 | J47: =L4 -> 7 | ... R47: =T4 -> 15
B48: Periodo | C48: =E5 -> 2022 | D48: =F5 -> 2023 | E48: =G5 -> 2024 | F48: =H5 -> 2025 | G48: =I5 -> 2026 | H48: =J5 -> 2027 | I48: =K5 -> 2028 | J48: =L5 -> 2029 | ... R48: =T5 -> 2037
B49: Utilidad antes de impuestos | C49: ='Estado de resultados'!J43 -> 8722 | D49: ='Modelo financiero'!K15 -> 8824.2153 | E49: ='Modelo financiero'!L15 -> 9655.5927 | F49: ='Modelo financiero'!M15 -> 10542.086 | G49: ='Modelo financiero'!N15 -> 11487.497 | H49: ='Modelo financiero'!O15 -> 12495.902 | I49: ='Modelo financiero'!P15 -> 13496.494 | J49: ='Modelo financiero'!Q15 -> 14563.326 | K49: ='Modelo financiero'!R15 -> 15701.08 | ... R49: ='Modelo financiero'!Y15 -> 26124.009
B50: Participación de los Trabajadores en las Utilidades (PTU, 10%) | C50: =IF(C49>0,C49*10%,0) -> 872.2 | D50: =IF(D49>0,D49*10%,0) -> 882.42153 | E50: =IF(E49>0,E49*10%,0) -> 965.55927 | F50: =IF(F49>0,F49*10%,0) -> 1054.2086 | G50: =IF(G49>0,G49*10%,0) -> 1148.7497 | H50: =IF(H49>0,H49*10%,0) -> 1249.5902 | I50: =IF(I49>0,I49*10%,0) -> 1349.6494 | J50: =IF(J49>0,J49*10%,0) -> 1456.3326 | ... R50: =IF(R49>0,R49*10%,0) -> 2612.4009
B51: Base gravable | D51: =D49-C50 -> 7952.0153 | E51: =E49-D50 -> 8773.1712 | F51: =F49-E50 -> 9576.527 | G51: =G49-F50 -> 10433.288 | H51: =H49-G50 -> 11347.152 | I51: =I49-H50 -> 12246.904 | J51: =J49-I50 -> 13213.676 | K51: =K49-J50 -> 14244.748 | ... R51: =R49-Q50 -> 23691.393
B52: Impuestos | D52: =IF(D51>0,D51*30%,0) -> 2385.6046 | E52: =IF(E51>0,E51*30%,0) -> 2631.9513 | F52: =IF(F51>0,F51*30%,0) -> 2872.9581 | G52: =IF(G51>0,G51*30%,0) -> 3129.9865 | H52: =IF(H51>0,H51*30%,0) -> 3404.1456 | I52: =IF(I51>0,I51*30%,0) -> 3674.0712 | J52: =IF(J51>0,J51*30%,0) -> 3964.1029 | K52: =IF(K51>0,K51*30%,0) -> 4273.4243 | ... R52: =IF(R51>0,R51*30%,0) -> 7107.418
B53: Total de impuestos | D53: =D50+D52 -> 3268.0261 | E53: =E50+E52 -> 3597.5106 | F53: =F50+F52 -> 3927.1667 | G53: =G50+G52 -> 4278.7362 | H53: =H50+H52 -> 4653.7357 | I53: =I50+I52 -> 5023.7206 | J53: =J50+J52 -> 5420.4355 | K53: =K50+K52 -> 5843.5324 | ... R53: =R50+R52 -> 9719.8189
B58: Capital de trabajo | C58: =C47 -> 0 | D58: =D47 -> 1 | E58: =E47 -> 2 | F58: =F47 -> 3 | G58: =G47 -> 4 | H58: =H47 -> 5 | I58: =I47 -> 6 | J58: =J47 -> 7 | ... R58: =R47 -> 15
B59: Periodo | C59: =C48 -> 2022 | D59: =D48 -> 2023 | E59: =E48 -> 2024 | F59: =F48 -> 2025 | G59: =G48 -> 2026 | H59: =H48 -> 2027 | I59: =I48 -> 2028 | J59: =J48 -> 2029 | ... R59: =R48 -> 2037
B60: Ingresos | C60: =E9 -> 259326 | D60: =F9 -> 275920.33 | E60: =G9 -> 293612.1 | F60: =H9 -> 312476.74 | G60: =I9 -> 332595.14 | H60: =J9 -> 354054.05 | I60: =K9 -> 375346.73 | J60: =L9 -> 398048.97 | ... R60: =T9 -> 644061.05
A61: 0.081455161 | B61: Capital de trabajo | C61: =C60*$A$61 -> 21123.441 | D61: =D60*$A$61 -> 22475.135 | E61: =E60*$A$61 -> 23916.221 | F61: =F60*$A$61 -> 25452.843 | G61: =G60*$A$61 -> 27091.591 | H61: =H60*$A$61 -> 28839.53 | I61: =I60*$A$61 -> 30573.928 | J61: =J60*$A$61 -> 32423.143 | ... R61: =R60*$A$61 -> 52462.096
B62: Cambio en el capital de trabajo | D62: =C61-D61 -> -1351.694 | E62: =D61-E61 -> -1441.0856 | F62: =E61-F61 -> -1536.6223 | G62: =F61-G61 -> -1638.7477 | H62: =G61-H61 -> -1747.9392 | I62: =H61-I61 -> -1734.3981 | J62: =I61-J61 -> -1849.2152 | K62: =J61-K61 -> -1972.1508 | ... R62: =Q61-R61 -> -3116.3455

Sheet Razones financieras
B3: Liquidez | C3: 2015 | D3: 2016 | E3: 2017 | F3: 2018 | G3: 2019 | H3: 2020 | I3: 2021 | J3: 2022
B4: Solvencia circulante | C4: =C5/C6 -> 0.65308731 | D4: =D5/D6 -> 0.68355049 | E4: =E5/E6 -> 0.74802685 | F4: =F5/F6 -> 0.7631984 | G4: =G5/G6 -> 0.74488366 | H4: =H5/H6 -> 0.76683004 | I4: =I5/I6 -> 0.83636883 | J4: =J5/J6 -> 0.87376278 | K4: La empresa no es capaz de pagar lo que debe en el corto plazo. Ha mejorado su solvencia en los últimos años.
B5: Activo ciruclante | C5: ='Balance general'!C68 -> 17610.049 | D5: ='Balance general'!D68 -> 18287.168 | E5: ='Balance general'!E68 -> 19019.966 | F5: ='Balance general'!F68 -> 23956.735 | G5: ='Balance general'!G68 -> 23659.788 | H5: ='Balance general'!H68 -> 26293.225 | I5: ='Balance general'!I68 -> 34757.933 | J5: ='Balance general'!J68 -> 37695
B6: Pasivo circulante | C6: ='Balance general'!C90 -> 26964.31 | D6: ='Balance general'!D90 -> 26753.208 | E6: ='Balance general'!E90 -> 25426.85 | F6: ='Balance general'!F90 -> 31389.918 | G6: ='Balance general'!G90 -> 31763.065 | H6: ='Balance general'!H90 -> 34288.204 | I6: ='Balance general'!I90 -> 41558.141 | J6: ='Balance general'!J90 -> 43141
B7: Prueba de ácido | C7: =C8/C9 -> 0.23653643 | D7: =D8/D9 -> 0.19809989 | E7: =E8/E9 -> 0.22969128 | F7: =F8/F9 -> 0.22773225 | G7: =G8/G9 -> 0.20537466 | H7: =H8/H9 -> 0.33487098 | I7: =I8/I9 -> 0.37175695 | J7: =J8/J9 -> 0.38608284 | K7: Debido al gran peso de los inventarios, sin su venta, la empresa posee muy baja solvencia para cubrir las obligaciones
B8: Activo circulante - Inventario | C8: =('Balance general'!C68-'Balance general'!C65) -> 6378.0416 | D8: =('Balance general'!D68-'Balance general'!D65) -> 5299.8076 | E8: =('Balance general'!E68-'Balance general'!E65) -> 5840.3256 | F8: =('Balance general'!F68-'Balance general'!F65) -> 7148.4966 | G8: =('Balance general'!G68-'Balance general'!G65) -> 6523.3288 | H8: =('Balance general'!H68-'Balance general'!H65) -> 11482.124 | I8: =('Balance general'!I68-'Balance general'!I65) -> 15449.528 | J8: =('Balance general'!J68-'Balance general'!J65) -> 16656
B9: Pasivo circulante | C9: ='Balance general'!C90 -> 26964.31 | D9: ='Balance general'!D90 -> 26753.208 | E9: ='Balance general'!E90 -> 25426.85 | F9: ='Balance general'!F90 -> 31389.918 | G9: ='Balance general'!G90 -> 31763.065 | H9: ='Balance general'!H90 -> 34288.204 | I9: ='Balance general'!I90 -> 41558.141 | J9: ='Balance general'!J90 -> 43141
B10: Razón pago inmediato | C10: =('Balance general'!C68-'Balance general'!C65-'Balance general'!C61)/'Balance general'!C90 -> 0.19235258 | D10: =('Balance general'!D68-'Balance general'!D65-'Balance general'!D61)/'Balance general'!D90 -> 0.14641694 | E10: =('Balance general'!E68-'Balance general'!E65-'Balance general'!E61)/'Balance general'!E90 -> 0.1753557 | F10: =('Balance general'!F68-'Balance general'!F65-'Balance general'!F61)/'Balance general'!F90 -> 0.16574448 | G10: =('Balance general'!G68-'Balance general'!G65-'Balance general'!G61)/'Balance general'!G90 -> 0.15118747 | H10: =('Balance general'!H68-'Balance general'!H65-'Balance general'!H61)/'Balance general'!H90 -> 0.28661525 | I10: =('Balance general'!I68-'Balance general'!I65-'Balance general'!I61)/'Balance general'!I90 -> 0.31475716 | J10: =('Balance general'!J68-'Balance general'!J65-'Balance general'!J61)/'Balance general'!J90 -> 0.33995503 | K10: En los últimos años Chedraui a incrementado su efectivo pero continua sin la posibilidad de cubrir sus deudas de inmediato (deficiencia de efectivo).
B13: Estabilidad o solvencia | C13: 2015 | D13: 2016 | E13: 2017 | F13: 2018 | G13: 2019 | H13: 2020 | I13: 2021 | J13: 2022
B14: Apalancamiento | C14: =C16/C17 -> 1.0210841 | D14: =D16/D17 -> 0.97791224 | E14: =E16/E17 -> 0.93461593 | F14: =F16/F17 -> 2.2603444 | G14: =G16/G17 -> 2.1883254 | H14: =H16/H17 -> 2.0889625 | I14: =I16/I17 -> 3.3184017 | J14: =J16/J17 -> 2.643543 | K14: Se están utilizando de manera eficiente los recursos de terceros para hacer frente a los compromisos.
B15: Razón pasivo capital | C15: ='Balance general'!C100/'Balance general'!C102 -> 0.3039458 | D15: ='Balance general'!D100/'Balance general'!D102 -> 0.29411983 | E15: ='Balance general'!E100/'Balance general'!E102 -> 0.27954418 | F15: ='Balance general'!F100/'Balance general'!F102 -> 1.3643107 | G15: ='Balance general'!G100/'Balance general'!G102 -> 1.2773805 | H15: ='Balance general'!H100/'Balance general'!H102 -> 1.1413496 | I15: ='Balance general'!I100/'Balance general'!I102 -> 2.1382425 | J15: ='Balance general'!J100/'Balance general'!J102 -> 1.5477037 | K15: La mayor parte del endeudamiento corresponde a largo plazo.
B16: Pasivo total | C16: ='Balance general'!C101 -> 38392.633 | D16: ='Balance general'!D101 -> 38260.573 | E16: ='Balance general'!E101 -> 36277.46 | F16: ='Balance general'!F101 -> 79184.552 | G16: ='Balance general'!G101 -> 76303.102 | H16: ='Balance general'!H101 -> 75586.533 | I16: ='Balance general'!I101 -> 116854.24 | J16: ='Balance general'!J101 -> 104071
B17: Capital contable | C17: ='Balance general'!C102 -> 37599.874 | D17: ='Balance general'!D102 -> 39124.751 | E17: ='Balance general'!E102 -> 38815.366 | F17: ='Balance general'!F102 -> 35032.073 | G17: ='Balance general'!G102 -> 34868.261 | H17: ='Balance general'!H102 -> 36183.767 | I17: ='Balance general'!I102 -> 35214.012 | J17: ='Balance general'!J102 -> 39368
B18: Razón de endeudamiento | C18: =C19/C20 -> 0.505226 | D18: =D19/D20 -> 0.49442568 | E18: =E19/E20 -> 0.48308397 | F18: =F19/F20 -> 0.69326809 | G18: =G19/G20 -> 0.68636358 | H18: =H19/H20 -> 0.67628166 | I18: =I19/I20 -> 0.7684274 | J18: =J19/J20 -> 0.72554187 | K18: Los activos han sido financiados pacticamente por los dueños del negocio.
B19: Pasivo total | C19: ='Balance general'!C101 -> 38392.633 | D19: ='Balance general'!D101 -> 38260.573 | E19: ='Balance general'!E101 -> 36277.46 | F19: ='Balance general'!F101 -> 79184.552 | G19: ='Balance general'!G101 -> 76303.102 | H19: ='Balance general'!H101 -> 75586.533 | I19: ='Balance general'!I101 -> 116854.24 | J19: ='Balance general'!J101 -> 104071
B20: Activo total | C20: ='Balance general'!C79 -> 75991.009 | D20: ='Balance general'!D79 -> 77383.872 | E20: ='Balance general'!E79 -> 75095.556 | F20: ='Balance general'!F79 -> 114219.24 | G20: ='Balance general'!G79 -> 111170.09 | H20: ='Balance general'!H79 -> 111767.83 | I20: ='Balance general'!I79 -> 152069.33 | J20: ='Balance general'!J79 -> 143439
B21: Inversión del capital | C21: ='Balance general'!C78/'Balance general'!C102 -> 1.5526903 | D21: ='Balance general'!D78/'Balance general'!D102 -> 1.5104685 | E21: ='Balance general'!E78/'Balance general'!E102 -> 1.444675 | F21: ='Balance general'!F78/'Balance general'!F102 -> 2.5765675 | G21: ='Balance general'!G78/'Balance general'!G102 -> 2.509741 | H21: ='Balance general'!H78/'Balance general'!H102 -> 2.3622362 | I21: ='Balance general'!I78/'Balance general'!I102 -> 3.331384 | J21: ='Balance general'!J78/'Balance general'!J102 -> 2.6860394
B22: Valor del capital | C22: ='Balance general'!C102/'Balance general'!C103 -> 99.563492 | D22: ='Balance general'!D102/'Balance general'!D103 -> 106.89683 | E22: ='Balance general'!E102/'Balance general'!E103 -> 112.8254 | F22: ='Balance general'!F102/'Balance general'!F103 -> 106.45238 | G22: ='Balance general'!G102/'Balance general'!G103 -> 108.76984 | H22: ='Balance general'!H102/'Balance general'!H103 -> 116.19841 | I22: ='Balance general'!I102/'Balance general'!I103 -> 129.60317 | J22: ='Balance general'!J102/'Balance general'!J103 -> 156.22222
B23: Productividad | C23: 2015 | D23: 2016 | E23: 2017 | F23: 2018 | G23: 2019 | H23: 2020 | I23: 2021 | J23: 2022
B24: Rotación de activos fijos netos | C24: ='Estado de resultados'!C32/'Balance general'!C78 -> 2.0188413 | D24: ='Estado de resultados'!D32/'Balance general'!D78 -> 2.1757477 | E24: ='Estado de resultados'!E32/'Balance general'!E78 -> 2.3026902 | F24: ='Estado de resultados'!F32/'Balance general'!F78 -> 1.6787135 | G24: ='Estado de resultados'!G32/'Balance general'!G78 -> 1.8816578 | H24: ='Estado de resultados'!H32/'Balance general'!H78 -> 2.1148603 | I24: ='Estado de resultados'!I32/'Balance general'!I78 -> 1.7323695 | J24: ='Estado de resultados'!J32/'Balance general'!J78 -> 2.4523945 | K24: La empresa emplea su planta y equipo de forma eficiente.
B25: Ingresos | C25: ='Estado de resultados'!C32 -> 117861.89 | D25: ='Estado de resultados'!D32 -> 128579.52 | E25: ='Estado de resultados'!E32 -> 129124.71 | F25: ='Estado de resultados'!F32 -> 151524.88 | G25: ='Estado de resultados'!G32 -> 164664.44 | H25: ='Estado de resultados'!H32 -> 180766.85 | I25: ='Estado de resultados'!I32 -> 203226.68 | J25: ='Estado de resultados'!J32 -> 259326
B26: Activos fijos | C26: ='Balance general'!C78 -> 58380.96 | D26: ='Balance general'!D78 -> 59096.704 | E26: ='Balance general'!E78 -> 56075.59 | F26: ='Balance general'!F78 -> 90262.502 | G26: ='Balance general'!G78 -> 87510.303 | H26: ='Balance general'!H78 -> 85474.605 | I26: ='Balance general'!I78 -> 117311.39 | J26: ='Balance general'!J78 -> 105744
B27: Rotación de activos totales | C27: =C28/C29 -> 1.5509979 | D27: =D28/D29 -> 1.6615803 | E27: =E28/E29 -> 1.7194721 | F27: =F28/F29 -> 1.3266144 | G27: =G28/G29 -> 1.4811937 | H27: =H28/H29 -> 1.6173424 | I27: =I28/I29 -> 1.3364081 | J27: =J28/J29 -> 1.8079183 | K27: Se tiene una buena rotacion de activos, los activos tienen buena capacidad para generar ventas.
B28: Ingresos | C28: ='Estado de resultados'!C32 -> 117861.89 | D28: ='Estado de resultados'!D32 -> 128579.52 | E28: ='Estado de resultados'!E32 -> 129124.71 | F28: ='Estado de resultados'!F32 -> 151524.88 | G28: ='Estado de resultados'!G32 -> 164664.44 | H28: ='Estado de resultados'!H32 -> 180766.85 | I28: ='Estado de resultados'!I32 -> 203226.68 | J28: ='Estado de resultados'!J32 -> 259326
B29: Activo total | C29: ='Balance general'!C79 -> 75991.009 | D29: ='Balance general'!D79 -> 77383.872 | E29: ='Balance general'!E79 -> 75095.556 | F29: ='Balance general'!F79 -> 114219.24 | G29: ='Balance general'!G79 -> 111170.09 | H29: ='Balance general'!H79 -> 111767.83 | I29: ='Balance general'!I79 -> 152069.33 | J29: ='Balance general'!J79 -> 143439
B30: Rotación de capital contable | C30: =C31/C32 -> 3.1346353 | D30: =D31/D32 -> 3.2863984 | E30: =E31/E32 -> 3.326639 | F30: =F31/F32 -> 4.3253187 | G30: =G31/G32 -> 4.7224735 | H30: =H31/H32 -> 4.9957995 | I30: =I31/I32 -> 5.771188 | J30: =J31/J32 -> 6.5872282 | K30: Hay un uso eficiente del activo fijo.
B31: Ingresos | C31: ='Estado de resultados'!C32 -> 117861.89 | D31: ='Estado de resultados'!D32 -> 128579.52 | E31: ='Estado de resultados'!E32 -> 129124.71 | F31: ='Estado de resultados'!F32 -> 151524.88 | G31: ='Estado de resultados'!G32 -> 164664.44 | H31: ='Estado de resultados'!H32 -> 180766.85 | I31: ='Estado de resultados'!I32 -> 203226.68 | J31: ='Estado de resultados'!J32 -> 259326
B32: Capital contable | C32: ='Balance general'!C102 -> 37599.874 | D32: ='Balance general'!D102 -> 39124.751 | E32: ='Balance general'!E102 -> 38815.366 | F32: ='Balance general'!F102 -> 35032.073 | G32: ='Balance general'!G102 -> 34868.261 | H32: ='Balance general'!H102 -> 36183.767 | I32: ='Balance general'!I102 -> 35214.012 | J32: ='Balance general'!J102 -> 39368
B33: Rentabiidad | C33: 2015 | D33: 2016 | E33: 2017 | F33: 2018 | G33: 2019 | H33: 2020 | I33: 2021 | J33: 2022
B34: Margen de utilidad sobre ventas | C34: ='Estado de resultados'!C48/'Estado de resultados'!C32 -> 0.022759638 | D34: ='Estado de resultados'!D48/'Estado de resultados'!D32 -> 0.022704425 | E34: ='Estado de resultados'!E48/'Estado de resultados'!E32 -> 0.022382458 | F34: ='Estado de resultados'!F48/'Estado de resultados'!F32 -> 0.013668761 | G34: ='Estado de resultados'!G48/'Estado de resultados'!G32 -> 0.011873952 | H34: ='Estado de resultados'!H48/'Estado de resultados'!H32 -> 0.018279136 | I34: ='Estado de resultados'!I48/'Estado de resultados'!I32 -> 0.018462812 | J34: ='Estado de resultados'!J48/'Estado de resultados'!J32 -> 0.023815583 | K34: Se generan pocas utilidades con las ventas.
B35: Rendmiento sobre capital social | C35: =C36/C37 -> 0.071343165 | D35: =D36/D37 -> 0.074615784 | E35: =E36/E37 -> 0.074458357 | F35: =F36/F37 -> 0.059121748 | G35: =G36/G37 -> 0.056074425 | H35: =H36/H37 -> 0.091318899 | I35: =I36/I37 -> 0.10655236 | J35: =J36/J37 -> 0.15687868 | K35: Posible reducción/pérdida de mercado.
B36: Utilidad neta | C36: ='Estado de resultados'!C48 -> 2682.494 | D36: ='Estado de resultados'!D48 -> 2919.324 | E36: ='Estado de resultados'!E48 -> 2890.1284 | F36: ='Estado de resultados'!F48 -> 2071.1574 | G36: ='Estado de resultados'!G48 -> 1955.2177 | H36: ='Estado de resultados'!H48 -> 3304.2618 | I36: ='Estado de resultados'!I48 -> 3752.136 | J36: ='Estado de resultados'!J48 -> 6176
B37: Capital contable | C37: ='Balance general'!C102 -> 37599.874 | D37: ='Balance general'!D102 -> 39124.751 | E37: ='Balance general'!E102 -> 38815.366 | F37: ='Balance general'!F102 -> 35032.073 | G37: ='Balance general'!G102 -> 34868.261 | H37: ='Balance general'!H102 -> 36183.767 | I37: ='Balance general'!I102 -> 35214.012 | J37: ='Balance general'!J102 -> 39368
B38: Rendimiento sobre el patrimonio | C38: =C39/C40 -> 0.071343165 | D38: =D39/D40 -> -0.039424196 | E38: =E39/E40 -> 0.019978194 | F38: =F39/F40 -> -0.0036249534 | G38: =G39/G40 -> -0.013484604 | H38: =H39/H40 -> 0.15394307 | I38: =I39/I40 -> 0.12275618 | J38: =J39/J40 -> 0.064609404 | K38: La ROE ha mejorado en los últimos años, indicando que el dinero invertido está generando más ganancias.
B39: Utilidad neta | C39: ='Estado de resultados'!C48 -> 2682.494 | D39: ='Flujo de efectivo'!D58 -> -1542.4619 | E39: ='Flujo de efectivo'!E58 -> 775.4609 | F39: ='Flujo de efectivo'!F58 -> -126.98963 | G39: ='Flujo de efectivo'!G58 -> -470.1847 | H39: ='Flujo de efectivo'!H58 -> 5570.2403 | I39: ='Flujo de efectivo'!I58 -> 4322.7378 | J39: ='Flujo de efectivo'!J58 -> 2543.543
B40: Capital contable | C40: ='Balance general'!C102 -> 37599.874 | D40: ='Balance general'!D102 -> 39124.751 | E40: ='Balance general'!E102 -> 38815.366 | F40: ='Balance general'!F102 -> 35032.073 | G40: ='Balance general'!G102 -> 34868.261 | H40: ='Balance general'!H102 -> 36183.767 | I40: ='Balance general'!I102 -> 35214.012 | J40: ='Balance general'!J102 -> 39368
B41: Rendimiento sobre la inversión | C41: =C42/C43 -> 0.03530015 | D41: =D42/D43 -> 0.037725225 | E41: =E42/E43 -> 0.038486011 | F41: =F42/F43 -> 0.018133175 | G41: =G42/G43 -> 0.017587623 | H41: =H42/H43 -> 0.029563621 | I41: =I42/I43 -> 0.024673851 | J41: =J42/J43 -> 0.04305663 | K41: Se tiene una ROA bastante baja, lo que significa que la administración para conseguir utilidades es deficiente.
B42: Utilidad neta | C42: ='Estado de resultados'!C48 -> 2682.494 | D42: ='Estado de resultados'!D48 -> 2919.324 | E42: ='Estado de resultados'!E48 -> 2890.1284 | F42: ='Estado de resultados'!F48 -> 2071.1574 | G42: ='Estado de resultados'!G48 -> 1955.2177 | H42: ='Estado de resultados'!H48 -> 3304.2618 | I42: ='Estado de resultados'!I48 -> 3752.136 | J42: ='Estado de resultados'!J48 -> 6176
B43: Activo total | C43: ='Balance general'!C79 -> 75991.009 | D43: ='Balance general'!D79 -> 77383.872 | E43: ='Balance general'!E79 -> 75095.556 | F43: ='Balance general'!F79 -> 114219.24 | G43: ='Balance general'!G79 -> 111170.09 | H43: ='Balance general'!H79 -> 111767.83 | I43: ='Balance general'!I79 -> 152069.33 | J43: ='Balance general'!J79 -> 143439

Sheet Balance general
B1: Factor INPC | C1: =I1+42.04% -> 1.4986 | D1: =I1+37.42% -> 1.4524 | E1: =I1+28.7% -> 1.3652 | F1: =I1+22.77% -> 1.3059 | G1: =I1+19.39% -> 1.2721 | H1: =I1+15.75% -> 1.2357 | I1: =J1+7.82% -> 1.0782 | J1: 1
B3: Información del Balance General | C3: 31 de diciembre
B4: Millones de pesos | C4: 2015 | D4: 2016 | E4: 2017 | F4: 2018 | G4: 2019 | H4: 2020 | I4: 2021 | J4: 2022
B5: Efectivo | C5: 2048 | D5: 943 | E5: 1522 | F5: 1252 | G5: 984 | H5: 5445 | I5: 9101 | J5: 11566
B6: Cuentas y documentos por cobrar neto | C6: 795 | D6: 952 | E6: 1012 | F6: 1490 | G6: 1353 | H6: 1339 | I6: 2197 | J6: 1990
B7: Impuestos por recuperar | C7: 1405 | D7: 1710 | E7: 1439 | F7: 2329 | G7: 2253 | H7: 1991 | I7: 2003 | J7: 2092
B8: Cuentas por cobrar partes relacionadas | C8: 8 | D8: 22 | E8: 17 | F8: 25 | G8: 59 | H8: 34 | I8: 66 | J8: 60
B9: Instrumentos financieros derivados | D9: 22 | F9: 5 | G9: 0 | H9: 0 | I9: 0 | J9: 0
B10: Inventarios - neto | C10: 7495 | D10: 8942 | E10: 9654 | F10: 12871 | G10: 13471 | H10: 11986 | I10: 17908 | J10: 21039
B11: Pagos anticipados | E11: 288 | F11: 373 | G11: 479 | H11: 483 | I11: 867 | J11: 948
B12: Activos mantenidos para la venta | G12: 0 | H12: 0 | I12: 95 | J12: 0
B13: Total de Activo circulante | C13: =SUM(C5:C12) -> 11751 | D13: =SUM(D5:D12) -> 12591 | E13: =SUM(E5:E12) -> 13932 | F13: =SUM(F5:F12) -> 18345 | G13: =SUM(G5:G12) -> 18599 | H13: =SUM(H5:H12) -> 21278 | I13: =SUM(I5:I12) -> 32237 | J13: =SUM(J5:J12) -> 37695
B14: Inmuebles y equipo - neto | C14: 28142 | D14: 29898 | E14: 30829 | F14: 53830 | G14: 32965 | H14: 32812 | I14: 42178 | J14: 42792
B15: Activos por derechos de uso - Neto | G15: 19218 | H15: 19105 | I15: 41916 | J15: 38324
B16: Propiedades de inversión | C16: 5879 | D16: 6420 | E16: 6856 | F16: 8679 | G16: 9512 | H16: 9811 | I16: 10996 | J16: 11294
B17: Inversión en acciones asociadas | C17: 19 | D17: 17 | E17: 10 | F17: 8 | G17: 6 | H17: 139 | I17: 941 | J17: 976
B18: Cuentas por cobrar de largo plazo | C18: 94 | D18: 94 | E18: 95 | F18: 95 | G18: 471 | H18: 300 | I18: 100 | J18: 0
B19: Otros activos neto | C19: 2465 | D19: 2586 | E19: 2295 | F19: 5528 | G19: 5372 | H19: 5970 | I19: 12386 | J19: 11835
B20: Cuentas por cobrar de parte relacionada - largo plazo | C20: 37 | D20: 37 | E20: 37 | F20: 37 | G20: 37 | H20: 37 | I20: 37 | J20: 0
B21: Instrumentos financieros derivados | C21: 77 | D21: 39 | E21: 71 | F21: 90 | G21: 13 | H21: 0 | I21: 0 | J21: 268
B22: Impuestos a la utilidad diferidos | C22: 2244 | D22: 1598 | E22: 882 | F22: 852 | G22: 1198 | H22: 997 | I22: 249 | J22: 255
B23: Activos totales | C23: =SUM(C13:C22) -> 50708 | D23: =SUM(D13:D22) -> 53280 | E23: =SUM(E13:E22) -> 55007 | F23: =SUM(F13:F22) -> 87464 | G23: =SUM(G13:G22) -> 87391 | H23: =SUM(H13:H22) -> 90449 | I23: =SUM(I13:I22) -> 141040 | J23: =SUM(J13:J22) -> 143439
B24: Pasivo circulante
B25: Cuentas y documentos por pagar proveedores | C25: 12935 | D25: 14018 | E25: 14597 | F25: 18798 | G25: 17451 | H25: 18451 | I25: 26284 | J25: 29749
B26: Cuentas por pagar compañías afiliadas - Factoring corportaivo SA de CV | G26: 995 | H26: 1042 | I26: 1120 | J26: 903
B27: Prestamos de instituciones financieras | C27: 0 | D27: 205 | E27: 150 | F27: 73 | G27: 1207 | H27: 2000 | I27: 0 | J27: 0
B28: Porción circulante del pasivo a largo plazo | C28: 1960 | D28: 1107 | E28: 439 | F28: 338 | G28: 561 | H28: 1162 | I28: 177 | J28: 0
B29: Porción circulante de las obligaciones por arrendamiento | C29: 117 | D29: 64 | E29: 80 | F29: 575 | G29: 560 | H29: 602 | I29: 2177 | J29: 2329
B30: Porción circulante obligaciones relacionadas con derecho de cobro fideicomitidos | E30: 113 | F30: 122 | G30: 75 | H30: 0 | I30: 0 | J30: 0
B31: Instrumentos financieros derivados | C31: 0 | D31: 0 | E31: 0 | F31: 0 | G31: 0 | H31: 55 | I31: 0 | J31: 0
B32: Impuestos y gastos acumulados | C32: 2981 | D32: 3026 | E32: 3246 | F32: 3699 | G32: 3546 | H32: 3863 | I32: 7761 | J32: 8780
B33: Impuestos y contribuciones por pagar | F33: 432 | G33: 574 | H33: 573 | I33: 1025 | J33: 1380
B34: Total de Pasivo Circulante | C34: =SUM(C25:C32) -> 17993 | D34: =SUM(D25:D32) -> 18420 | E34: =SUM(E25:E32) -> 18625 | F34: =SUM(F25:F33) -> 24037 | G34: =SUM(G25:G33) -> 24969 | H34: =SUM(H25:H33) -> 27748 | I34: =SUM(I25:I33) -> 38544 | J34: 43141
B35: Préstamos de instituciones financieras | C35: 2893 | D35: 3927 | E35: 4476 | F35: 9716 | G35: 8733 | H35: 6186 | I35: 17391 | J35: 12682
B36: Beneficios a los empleados | C36: 478 | D36: 454 | E36: 538 | F36: 609 | G36: 892 | H36: 1073 | I36: 2869 | J36: 2292
B37: Instrumentos Financieros Derivados | C37: 100 | D37: 0 | F37: 0 | G37: 35 | H37: 253 | I37: 45 | J37: 0
B38: Obligaciones relacionadas con derecho de cobro
B39: Fideicomitidos | C39: 839 | D39: 742 | E39: 521 | F39: 405 | G39: 315 | H39: 0 | I39: 0 | J39: 0
B40: Obligaciones por arrendamiento | C40: 152 | D40: 137 | E40: 153 | F40: 22572 | G40: 21761 | H40: 22331 | I40: 44597 | J40: 41622
B41: Impuesto a la utilidad diferido | C41: 1476 | D41: 1724 | E41: 1801 | F41: 2858 | G41: 2856 | H41: 2608 | I41: 2625 | J41: 2069
B42: Impuestos sobre la renta | C42: 1327 | D42: 494 | E42: 0
B43: Otros pasivos de largo plazo | C43: 361 | D43: 445 | E43: 459 | F43: 439 | G43: 421 | H43: 970 | I43: 2308 | J43: 2265
B44: Total del Pasivo | C44: =SUM(C34:C43) -> 25619 | D44: =SUM(D34:D43) -> 26343 | E44: =SUM(E34:E43) -> 26573 | F44: =SUM(F34:F43) -> 60636 | G44: =SUM(G34:G43) -> 59982 | H44: =SUM(H34:H43) -> 61169 | I44: =SUM(I34:I43) -> 108379 | J44: =SUM(J34:J43) -> 104071
B45: Capital Contable | C45: =C52+C53 -> 25090 | D45: =D52+D53 -> 26938 | E45: =E52+E53 -> 28433 | F45: =F52+F53 -> 26827 | G45: =G52+G53 -> 27410 | H45: =H52+H53 -> 29282 | I45: =I52+I53 -> 32660 | J45: =J52+J53 -> 39367
B46: Capital social | C46: 252 | D46: 252 | E46: 252 | F46: 252 | G46: 252 | H46: 252 | I46: 252 | J46: 252
B47: Utilidades Retenidas | C47: 20315 | D47: 21940 | E47: 23668 | F47: 22369 | G47: 23377 | H47: 25577 | I47: 28498 | J47: 34032
B48: Remedición de obligaciones laborales | C48: -34 | D48: -27 | E48: -53 | F48: -57 | G48: -185 | H48: -242 | I48: -168 | J48: 390
B49: Efecto por el reconocimiento de la valuación de instrumentos derivados | C49: -71 | D49: 2 | E49: 57 | F49: 74 | G49: -11 | H49: -210 | I49: -30 | J49: 178
B50: Efectos de conversión de operaciones extranjeras | C50: 375 | D50: 692 | E50: 613 | F50: 561 | G50: 466 | H50: 438 | I50: 464 | J50: 424
B51: Prima en colocación de acciones | C51: 3953 | D51: 3751 | E51: 3612 | F51: 3545 | G51: 3499 | H51: 3474 | I51: 3527 | J51: 3799
B52: Participación Controladora | C52: 24790 | D52: 26610 | E52: 28150 | F52: 26745 | G52: 27398 | H52: 29289 | I52: 32543 | J52: 39074
B53: Participación no Controladora | C53: 300 | D53: 328 | E53: 283 | F53: 82 | G53: 12 | H53: -7 | I53: 117 | J53: 293
B54: Total del pasivo y capital contable | C54: =SUM(C44:C45) -> 50709 | D54: =SUM(D44:D45) -> 53281 | E54: =SUM(E44:E45) -> 55006 | F54: =SUM(F44:F45) -> 87463 | G54: =SUM(G44:G45) -> 87392 | H54: =SUM(H44:H45) -> 90451 | I54: =SUM(I44:I45) -> 141039 | J54: =SUM(J44:J45) -> 143438
C55: =ABS(C54-C23) -> 1 | D55: =ABS(D54-D23) -> 1 | E55: =ABS(E54-E23) -> 1 | F55: =ABS(F54-F23) -> 1 | G55: =ABS(G54-G23) -> 1 | H55: =ABS(H54-H23) -> 2 | I55: =ABS(I54-I23) -> 1 | J55: =ABS(J54-J23) -> 1
B58: Información del Balance General | C58: 31 de diciembre | L58: Análisis vertical
B59: Millones de pesos | C59: 2015 | D59: 2016 | E59: 2017 | F59: 2018 | G59: 2019 | H59: 2020 | I59: 2021 | J59: 2022 | L59: =C59 -> 2015 | M59: =D59 -> 2016 | N59: =E59 -> 2017 | O59: =F59 -> 2018 | P59: =G59 -> 2019 | Q59: =H59 -> 2020 | R59: =I59 -> 2021 | S59: =J59 -> 2022 | T59: Promedio
B60: Efectivo | C60: =IFERROR(C$1*C5,0) -> 3069.1328 | D60: =IFERROR(D$1*D5,0) -> 1369.6132 | E60: =IFERROR(E$1*E5,0) -> 2077.8344 | F60: =IFERROR(F$1*F5,0) -> 1634.9868 | G60: =IFERROR(G$1*G5,0) -> 1251.7464 | H60: =IFERROR(H$1*H5,0) -> 6728.3865 | I60: =IFERROR(I$1*I5,0) -> 9812.6982 | J60: =IFERROR(J$1*J5,0) -> 11566 | L60: =C60/C$79 -> 0.040388104 | M60: =D60/D$79 -> 0.017698949 | N60: =E60/E$79 -> 0.027669206 | O60: =F60/F$79 -> 0.014314461 | P60: =G60/G$79 -> 0.011259741 | Q60: =H60/H$79 -> 0.060199671 | R60: =I60/I$79 -> 0.064527794 | S60: =J60/J$79 -> 0.080633579
B61: Cuentas y documentos por cobrar neto | C61: =IFERROR(C$1*C6,0) -> 1191.387 | D61: =IFERROR(D$1*D6,0) -> 1382.6848 | E61: =IFERROR(E$1*E6,0) -> 1381.5824 | F61: =IFERROR(F$1*F6,0) -> 1945.791 | G61: =IFERROR(G$1*G6,0) -> 1721.1513 | H61: =IFERROR(H$1*H6,0) -> 1654.6023 | I61: =IFERROR(I$1*I6,0) -> 2368.8054 | J61: =IFERROR(J$1*J6,0) -> 1990 | L61: =C61/C$79 -> 0.015678 | M61: =D61/D$79 -> 0.017867868 | N61: =E61/E$79 -> 0.018397658 | O61: =F61/F$79 -> 0.01703558 | P61: =G61/G$79 -> 0.015482143 | Q61: =H61/H$79 -> 0.014803923 | R61: =I61/I$79 -> 0.015577141 | S61: =J61/J$79 -> 0.013873493
B62: Impuestos por recuperar | C62: =IFERROR(C$1*C7,0) -> 2105.533 | D62: =IFERROR(D$1*D7,0) -> 2483.604 | E62: =IFERROR(E$1*E7,0) -> 1964.5228 | F62: =IFERROR(F$1*F7,0) -> 3041.4411 | G62: =IFERROR(G$1*G7,0) -> 2866.0413 | H62: =IFERROR(H$1*H7,0) -> 2460.2787 | I62: =IFERROR(I$1*I7,0) -> 2159.6346 | J62: =IFERROR(J$1*J7,0) -> 2092 | L62: =C62/C$79 -> 0.02770766 | M62: =D62/D$79 -> 0.032094595 | N62: =E62/E$79 -> 0.026160307 | O62: =F62/F$79 -> 0.026628098 | P62: =G62/G$79 -> 0.025780687 | Q62: =H62/H$79 -> 0.022012405 | R62: =I62/I$79 -> 0.014201645 | S62: =J62/J$79 -> 0.014584597
B63: Cuentas por cobrar partes relacionadas | C63: =IFERROR(C$1*C8,0) -> 11.9888 | D63: =IFERROR(D$1*D8,0) -> 31.9528 | E63: =IFERROR(E$1*E8,0) -> 23.2084 | F63: =IFERROR(F$1*F8,0) -> 32.6475 | G63: =IFERROR(G$1*G8,0) -> 75.0539 | H63: =IFERROR(H$1*H8,0) -> 42.0138 | I63: =IFERROR(I$1*I8,0) -> 71.1612 | J63: =IFERROR(J$1*J8,0) -> 60 | L63: =C63/C$79 -> 0.00015776603 | M63: =D63/D$79 -> 0.00041291291 | N63: =E63/E$79 -> 0.00030905158 | O63: =F63/F$79 -> 0.00028583189 | P63: =G63/G$79 -> 0.00067512673 | Q63: =H63/H$79 -> 0.00037590244 | R63: =I63/I$79 -> 0.00046795235 | S63: =J63/J$79 -> 0.00041829628
B64: Instrumentos financieros derivados | C64: =IFERROR(C$1*C9,0) -> 0 | D64: =IFERROR(D$1*D9,0) -> 31.9528 | E64: =IFERROR(E$1*E9,0) -> 0 | F64: =IFERROR(F$1*F9,0) -> 6.5295 | G64: =IFERROR(G$1*G9,0) -> 0 | H64: =IFERROR(H$1*H9,0) -> 0 | I64: =IFERROR(I$1*I9,0) -> 0 | J64: =IFERROR(J$1*J9,0) -> 0 | L64: =C64/C$79 -> 0 | M64: =D64/D$79 -> 0.00041291291 | N64: =E64/E$79 -> 0 | O64: =F64/F$79 -> 5.7166377e-05 | P64: =G64/G$79 -> 0 | Q64: =H64/H$79 -> 0 | R64: =I64/I$79 -> 0 | S64: =J64/J$79 -> 0
B65: Inventarios - neto | C65: =IFERROR(C$1*C10,0) -> 11232.007 | D65: =IFERROR(D$1*D10,0) -> 12987.361 | E65: =IFERROR(E$1*E10,0) -> 13179.641 | F65: =IFERROR(F$1*F10,0) -> 16808.239 | G65: =IFERROR(G$1*G10,0) -> 17136.459 | H65: =IFERROR(H$1*H10,0) -> 14811.1 | I65: =IFERROR(I$1*I10,0) -> 19308.406 | J65: =IFERROR(J$1*J10,0) -> 21039 | L65: =C65/C$79 -> 0.14780705 | M65: =D65/D$79 -> 0.16783033 | N65: =E65/E$79 -> 0.17550494 | O65: =F65/F$79 -> 0.14715769 | P65: =G65/G$79 -> 0.15414631 | Q65: =H65/H$79 -> 0.13251667 | R65: =I65/I$79 -> 0.12697107 | S65: =J65/J$79 -> 0.14667559 | T65: =AVERAGE(L65:S65) -> 0.14982621
B66: Pagos anticipados | C66: =IFERROR(C$1*C11,0) -> 0 | D66: =IFERROR(D$1*D11,0) -> 0 | E66: =IFERROR(E$1*E11,0) -> 393.1776 | F66: =IFERROR(F$1*F11,0) -> 487.1007 | G66: =IFERROR(G$1*G11,0) -> 609.3359 | H66: =IFERROR(H$1*H11,0) -> 596.8431 | I66: =IFERROR(I$1*I11,0) -> 934.7994 | J66: =IFERROR(J$1*J11,0) -> 948 | L66: =C66/C$79 -> 0 | M66: =D66/D$79 -> 0 | N66: =E66/E$79 -> 0.0052356973 | O66: =F66/F$79 -> 0.0042646117 | P66: =G66/G$79 -> 0.0054811136 | Q66: =H66/H$79 -> 0.0053400259 | R66: =I66/I$79 -> 0.0061471923 | S66: =J66/J$79 -> 0.0066090812
B67: Activos mantenidos para la venta | C67: =IFERROR(C$1*C12,0) -> 0 | D67: =IFERROR(D$1*D12,0) -> 0 | E67: =IFERROR(E$1*E12,0) -> 0 | F67: =IFERROR(F$1*F12,0) -> 0 | G67: =IFERROR(G$1*G12,0) -> 0 | H67: =IFERROR(H$1*H12,0) -> 0 | I67: =IFERROR(I$1*I12,0) -> 102.429 | J67: =IFERROR(J$1*J12,0) -> 0 | L67: =C67/C$79 -> 0 | M67: =D67/D$79 -> 0 | N67: =E67/E$79 -> 0 | O67: =F67/F$79 -> 0 | P67: =G67/G$79 -> 0 | Q67: =H67/H$79 -> 0 | R67: =I67/I$79 -> 0.00067356778 | S67: =J67/J$79 -> 0
B68: Total de Activo circulante | C68: =SUM(C60:C67) -> 17610.049 | D68: =SUM(D60:D67) -> 18287.168 | E68: =SUM(E60:E67) -> 19019.966 | F68: =SUM(F60:F67) -> 23956.735 | G68: =SUM(G60:G67) -> 23659.788 | H68: =SUM(H60:H67) -> 26293.225 | I68: =SUM(I60:I67) -> 34757.933 | J68: =SUM(J60:J67) -> 37695 | L68: =C68/C$79 -> 0.23173858 | M68: =D68/D$79 -> 0.23631757 | N68: =E68/E$79 -> 0.25327686 | O68: =F68/F$79 -> 0.20974344 | P68: =G68/G$79 -> 0.21282512 | Q68: =H68/H$79 -> 0.23524859 | R68: =I68/I$79 -> 0.22856636 | S68: =J68/J$79 -> 0.26279464 | T68: =AVERAGE(L68:S68) -> 0.23381389
B69: Inmuebles y equipo - neto | C69: =IFERROR(C$1*C14,0) -> 42173.601 | D69: =IFERROR(D$1*D14,0) -> 43423.855 | E69: =IFERROR(E$1*E14,0) -> 42087.751 | F69: =IFERROR(F$1*F14,0) -> 70296.597 | G69: =IFERROR(G$1*G14,0) -> 41934.776 | H69: =IFERROR(H$1*H14,0) -> 40545.788 | I69: =IFERROR(I$1*I14,0) -> 45476.32 | J69: =IFERROR(J$1*J14,0) -> 42792 | L69: =C69/C$79 -> 0.55498146 | M69: =D69/D$79 -> 0.56114865 | N69: =E69/E$79 -> 0.56045594 | O69: =F69/F$79 -> 0.61545322 | P69: =G69/G$79 -> 0.37721276 | Q69: =H69/H$79 -> 0.36276797 | R69: =I69/I$79 -> 0.29904991 | S69: =J69/J$79 -> 0.29832891 | T69: =AVERAGE(L69:S69) -> 0.45367485
B70: Activos por derechos de uso - Neto | C70: =IFERROR(C$1*C15,0) -> 0 | D70: =IFERROR(D$1*D15,0) -> 0 | E70: =IFERROR(E$1*E15,0) -> 0 | F70: =IFERROR(F$1*F15,0) -> 0 | G70: =IFERROR(G$1*G15,0) -> 24447.218 | H70: =IFERROR(H$1*H15,0) -> 23608.049 | I70: =IFERROR(I$1*I15,0) -> 45193.831 | J70: =IFERROR(J$1*J15,0) -> 38324 | L70: =C70/C$79 -> 0 | M70: =D70/D$79 -> 0 | N70: =E70/E$79 -> 0 | O70: =F70/F$79 -> 0 | P70: =G70/G$79 -> 0.21990823 | Q70: =H70/H$79 -> 0.211224 | R70: =I70/I$79 -> 0.29719229 | S70: =J70/J$79 -> 0.26717978 | T70: =AVERAGE(L70:S70) -> 0.12443804
B71: Propiedades de inversión | C71: =IFERROR(C$1*C16,0) -> 8810.2694 | D71: =IFERROR(D$1*D16,0) -> 9324.408 | E71: =IFERROR(E$1*E16,0) -> 9359.8112 | F71: =IFERROR(F$1*F16,0) -> 11333.906 | G71: =IFERROR(G$1*G16,0) -> 12100.215 | H71: =IFERROR(H$1*H16,0) -> 12123.453 | I71: =IFERROR(I$1*I16,0) -> 11855.887 | J71: =IFERROR(J$1*J16,0) -> 11294 | L71: =C71/C$79 -> 0.11593831 | M71: =D71/D$79 -> 0.1204955 | N71: =E71/E$79 -> 0.12463868 | O71: =F71/F$79 -> 0.099229397 | P71: =G71/G$79 -> 0.10884416 | Q71: =H71/H$79 -> 0.10846997 | R71: =I71/I$79 -> 0.077963698 | S71: =J71/J$79 -> 0.078737303 | T71: =AVERAGE(L71:S71) -> 0.10428963
B72: Inversión en acciones asociadas | C72: =IFERROR(C$1*C17,0) -> 28.4734 | D72: =IFERROR(D$1*D17,0) -> 24.6908 | E72: =IFERROR(E$1*E17,0) -> 13.652 | F72: =IFERROR(F$1*F17,0) -> 10.4472 | G72: =IFERROR(G$1*G17,0) -> 7.6326 | H72: =IFERROR(H$1*H17,0) -> 171.7623 | I72: =IFERROR(I$1*I17,0) -> 1014.5862 | J72: =IFERROR(J$1*J17,0) -> 976 | L72: =C72/C$79 -> 0.00037469433 | M72: =D72/D$79 -> 0.00031906907 | N72: =E72/E$79 -> 0.00018179504 | O72: =F72/F$79 -> 9.1466203e-05 | P72: =G72/G$79 -> 6.8656956e-05 | Q72: =H72/H$79 -> 0.0015367776 | R72: =I72/I$79 -> 0.0066718661 | S72: =J72/J$79 -> 0.0068042861
B73: Cuentas por cobrar de largo plazo | C73: =IFERROR(C$1*C18,0) -> 140.8684 | D73: =IFERROR(D$1*D18,0) -> 136.5256 | E73: =IFERROR(E$1*E18,0) -> 129.694 | F73: =IFERROR(F$1*F18,0) -> 124.0605 | G73: =IFERROR(G$1*G18,0) -> 599.1591 | H73: =IFERROR(H$1*H18,0) -> 370.71 | I73: =IFERROR(I$1*I18,0) -> 107.82 | J73: =IFERROR(J$1*J18,0) -> 0 | L73: =C73/C$79 -> 0.0018537509 | M73: =D73/D$79 -> 0.0017642643 | N73: =E73/E$79 -> 0.0017270529 | O73: =F73/F$79 -> 0.0010861612 | P73: =G73/G$79 -> 0.005389571 | Q73: =H73/H$79 -> 0.0033167863 | R73: =I73/I$79 -> 0.00070901872 | S73: =J73/J$79 -> 0
B74: Otros activos neto | C74: =IFERROR(C$1*C19,0) -> 3694.049 | D74: =IFERROR(D$1*D19,0) -> 3755.9064 | E74: =IFERROR(E$1*E19,0) -> 3133.134 | F74: =IFERROR(F$1*F19,0) -> 7219.0152 | G74: =IFERROR(G$1*G19,0) -> 6833.7212 | H74: =IFERROR(H$1*H19,0) -> 7377.129 | I74: =IFERROR(I$1*I19,0) -> 13354.585 | J74: =IFERROR(J$1*J19,0) -> 11835 | L74: =C74/C$79 -> 0.048611659 | M74: =D74/D$79 -> 0.048536036 | N74: =E74/E$79 -> 0.041721963 | O74: =F74/F$79 -> 0.063203146 | P74: =G74/G$79 -> 0.061470861 | Q74: =H74/H$79 -> 0.066004046 | R74: =I74/I$79 -> 0.087819058 | S74: =J74/J$79 -> 0.082508941 | T74: =AVERAGE(L74:S74) -> 0.062484464
B75: Cuentas por cobrar de parte relacionada - largo plazo | C75: =IFERROR(C$1*C20,0) -> 55.4482 | D75: =IFERROR(D$1*D20,0) -> 53.7388 | E75: =IFERROR(E$1*E20,0) -> 50.5124 | F75: =IFERROR(F$1*F20,0) -> 48.3183 | G75: =IFERROR(G$1*G20,0) -> 47.0677 | H75: =IFERROR(H$1*H20,0) -> 45.7209 | I75: =IFERROR(I$1*I20,0) -> 39.8934 | J75: =IFERROR(J$1*J20,0) -> 0 | L75: =C75/C$79 -> 0.0007296679 | M75: =D75/D$79 -> 0.00069444444 | N75: =E75/E$79 -> 0.00067264166 | O75: =F75/F$79 -> 0.00042303119 | P75: =G75/G$79 -> 0.00042338456 | Q75: =H75/H$79 -> 0.0004090703 | R75: =I75/I$79 -> 0.00026233693 | S75: =J75/J$79 -> 0
B76: Instrumentos financieros derivados | C76: =IFERROR(C$1*C21,0) -> 115.3922 | D76: =IFERROR(D$1*D21,0) -> 56.6436 | E76: =IFERROR(E$1*E21,0) -> 96.9292 | F76: =IFERROR(F$1*F21,0) -> 117.531 | G76: =IFERROR(G$1*G21,0) -> 16.5373 | H76: =IFERROR(H$1*H21,0) -> 0 | I76: =IFERROR(I$1*I21,0) -> 0 | J76: =IFERROR(J$1*J21,0) -> 268 | L76: =C76/C$79 -> 0.0015184981 | M76: =D76/D$79 -> 0.00073198198 | N76: =E76/E$79 -> 0.0012907448 | O76: =F76/F$79 -> 0.0010289948 | P76: =G76/G$79 -> 0.00014875674 | Q76: =H76/H$79 -> 0 | R76: =I76/I$79 -> 0 | S76: =J76/J$79 -> 0.00186839
B77: Impuestos a la utilidad diferidos | C77: =IFERROR(C$1*C22,0) -> 3362.8584 | D77: =IFERROR(D$1*D22,0) -> 2320.9352 | E77: =IFERROR(E$1*E22,0) -> 1204.1064 | F77: =IFERROR(F$1*F22,0) -> 1112.6268 | G77: =IFERROR(G$1*G22,0) -> 1523.9758 | H77: =IFERROR(H$1*H22,0) -> 1231.9929 | I77: =IFERROR(I$1*I22,0) -> 268.4718 | J77: =IFERROR(J$1*J22,0) -> 255 | L77: =C77/C$79 -> 0.044253372 | M77: =D77/D$79 -> 0.029992492 | N77: =E77/E$79 -> 0.016034323 | O77: =F77/F$79 -> 0.0097411506 | P77: =G77/G$79 -> 0.013708505 | Q77: =H77/H$79 -> 0.011022786 | R77: =I77/I$79 -> 0.0017654566 | S77: =J77/J$79 -> 0.0017777592
B78: Total de Activo fijo (no circulante) | C78: =SUM(C69:C77) -> 58380.96 | D78: =SUM(D69:D77) -> 59096.704 | E78: =SUM(E69:E77) -> 56075.59 | F78: =SUM(F69:F77) -> 90262.502 | G78: =SUM(G69:G77) -> 87510.303 | H78: =SUM(H69:H77) -> 85474.605 | I78: =SUM(I69:I77) -> 117311.39 | J78: =SUM(J69:J77) -> 105744 | L78: =C78/C$79 -> 0.76826142 | M78: =D78/D$79 -> 0.76368243 | N78: =E78/E$79 -> 0.74672314 | O78: =F78/F$79 -> 0.79025656 | P78: =G78/G$79 -> 0.78717488 | Q78: =H78/H$79 -> 0.76475141 | R78: =I78/I$79 -> 0.77143364 | S78: =J78/J$79 -> 0.73720536 | T78: =AVERAGE(L78:S78) -> 0.76618611
B79: Activos totales | C79: =C68+C78 -> 75991.009 | D79: =D68+D78 -> 77383.872 | E79: =E68+E78 -> 75095.556 | F79: =F68+F78 -> 114219.24 | G79: =G68+G78 -> 111170.09 | H79: =H68+H78 -> 111767.83 | I79: =I68+I78 -> 152069.33 | J79: =J68+J78 -> 143439 | L79: =C79/C$79 -> 1 | M79: =D79/D$79 -> 1 | N79: =E79/E$79 -> 1 | O79: =F79/F$79 -> 1 | P79: =G79/G$79 -> 1 | Q79: =H79/H$79 -> 1 | R79: =I79/I$79 -> 1 | S79: =J79/J$79 -> 1
B80: Pasivo circulante
B81: Cuentas y documentos por pagar proveedores | C81: =IFERROR(C$1*C25,0) -> 19384.391 | D81: =IFERROR(D$1*D25,0) -> 20359.743 | E81: =IFERROR(E$1*E25,0) -> 19927.824 | F81: =IFERROR(F$1*F25,0) -> 24548.308 | G81: =IFERROR(G$1*G25,0) -> 22199.417 | H81: =IFERROR(H$1*H25,0) -> 22799.901 | I81: =IFERROR(I$1*I25,0) -> 28339.409 | J81: =IFERROR(J$1*J25,0) -> 29749 | L81: =C81/C$101 -> 0.50489871 | M81: =D81/D$101 -> 0.53213377 | N81: =E81/E$101 -> 0.54931698 | O81: =F81/F$101 -> 0.31001385 | P81: =G81/G$101 -> 0.29093728 | Q81: =H81/H$101 -> 0.30163972 | R81: =I81/I$101 -> 0.24251931 | S81: =J81/J$101 -> 0.28585293 | T81: =AVERAGE(L81:S81) -> 0.37716407
B82: Cuentas por pagar compañías afiliadas - Factoring corportaivo SA de CV | C82: =IFERROR(C$1*C26,0) -> 0 | D82: =IFERROR(D$1*D26,0) -> 0 | E82: =IFERROR(E$1*E26,0) -> 0 | F82: =IFERROR(F$1*F26,0) -> 0 | G82: =IFERROR(G$1*G26,0) -> 1265.7395 | H82: =IFERROR(H$1*H26,0) -> 1287.5994 | I82: =IFERROR(I$1*I26,0) -> 1207.584 | J82: =IFERROR(J$1*J26,0) -> 903 | L82: =C82/C$101 -> 0 | M82: =D82/D$101 -> 0 | N82: =E82/E$101 -> 0 | O82: =F82/F$101 -> 0 | P82: =G82/G$101 -> 0.01658831 | Q82: =H82/H$101 -> 0.017034773 | R82: =I82/I$101 -> 0.010334105 | S82: =J82/J$101 -> 0.0086767687
B83: Prestamos de instituciones financieras | C83: =IFERROR(C$1*C27,0) -> 0 | D83: =IFERROR(D$1*D27,0) -> 297.742 | E83: =IFERROR(E$1*E27,0) -> 204.78 | F83: =IFERROR(F$1*F27,0) -> 95.3307 | G83: =IFERROR(G$1*G27,0) -> 1535.4247 | H83: =IFERROR(H$1*H27,0) -> 2471.4 | I83: =IFERROR(I$1*I27,0) -> 0 | J83: =IFERROR(J$1*J27,0) -> 0 | L83: =C83/C$101 -> 0 | M83: =D83/D$101 -> 0.0077819535 | N83: =E83/E$101 -> 0.0056448275 | O83: =F83/F$101 -> 0.0012039053 | P83: =G83/G$101 -> 0.020122703 | Q83: =H83/H$101 -> 0.0326963 | R83: =I83/I$101 -> 0 | S83: =J83/J$101 -> 0
B84: Porción circulante del pasivo a largo plazo | C84: =IFERROR(C$1*C28,0) -> 2937.256 | D84: =IFERROR(D$1*D28,0) -> 1607.8068 | E84: =IFERROR(E$1*E28,0) -> 599.3228 | F84: =IFERROR(F$1*F28,0) -> 441.3942 | G84: =IFERROR(G$1*G28,0) -> 713.6481 | H84: =IFERROR(H$1*H28,0) -> 1435.8834 | I84: =IFERROR(I$1*I28,0) -> 190.8414 | J84: =IFERROR(J$1*J28,0) -> 0 | L84: =C84/C$101 -> 0.076505718 | M84: =D84/D$101 -> 0.042022549 | N84: =E84/E$101 -> 0.016520528 | O84: =F84/F$101 -> 0.0055742463 | P84: =G84/G$101 -> 0.0093528058 | Q84: =H84/H$101 -> 0.018996551 | R84: =I84/I$101 -> 0.0016331577 | S84: =J84/J$101 -> 0
B85: Porción circulante de las obligaciones por arrendamiento | C85: =IFERROR(C$1*C29,0) -> 175.3362 | D85: =IFERROR(D$1*D29,0) -> 92.9536 | E85: =IFERROR(E$1*E29,0) -> 109.216 | F85: =IFERROR(F$1*F29,0) -> 750.8925 | G85: =IFERROR(G$1*G29,0) -> 712.376 | H85: =IFERROR(H$1*H29,0) -> 743.8914 | I85: =IFERROR(I$1*I29,0) -> 2347.2414 | J85: =IFERROR(J$1*J29,0) -> 2329 | L85: =C85/C$101 -> 0.004566923 | M85: =D85/D$101 -> 0.0024294879 | N85: =E85/E$101 -> 0.0030105746 | O85: =F85/F$101 -> 0.0094828155 | P85: =G85/G$101 -> 0.0093361342 | Q85: =H85/H$101 -> 0.0098415864 | R85: =I85/I$101 -> 0.020086917 | S85: =J85/J$101 -> 0.022378953
B86: Porción circulante obligaciones relacionadas con derecho de cobro fideicomitidos | C86: =IFERROR(C$1*C30,0) -> 0 | D86: =IFERROR(D$1*D30,0) -> 0 | E86: =IFERROR(E$1*E30,0) -> 154.2676 | F86: =IFERROR(F$1*F30,0) -> 159.3198 | G86: =IFERROR(G$1*G30,0) -> 95.4075 | H86: =IFERROR(H$1*H30,0) -> 0 | I86: =IFERROR(I$1*I30,0) -> 0 | J86: =IFERROR(J$1*J30,0) -> 0 | L86: =C86/C$101 -> 0 | M86: =D86/D$101 -> 0 | N86: =E86/E$101 -> 0.0042524367 | O86: =F86/F$101 -> 0.0020120061 | P86: =G86/G$101 -> 0.0012503751 | Q86: =H86/H$101 -> 0 | R86: =I86/I$101 -> 0 | S86: =J86/J$101 -> 0
B87: Instrumentos financieros derivados | C87: =IFERROR(C$1*C31,0) -> 0 | D87: =IFERROR(D$1*D31,0) -> 0 | E87: =IFERROR(E$1*E31,0) -> 0 | F87: =IFERROR(F$1*F31,0) -> 0 | G87: =IFERROR(G$1*G31,0) -> 0 | H87: =IFERROR(H$1*H31,0) -> 67.9635 | I87: =IFERROR(I$1*I31,0) -> 0 | J87: =IFERROR(J$1*J31,0) -> 0 | L87: =C87/C$101 -> 0 | M87: =D87/D$101 -> 0 | N87: =E87/E$101 -> 0 | O87: =F87/F$101 -> 0 | P87: =G87/G$101 -> 0 | Q87: =H87/H$101 -> 0.00089914826 | R87: =I87/I$101 -> 0 | S87: =J87/J$101 -> 0
B88: Impuestos y gastos acumulados | C88: =IFERROR(C$1*C32,0) -> 4467.3266 | D88: =IFERROR(D$1*D32,0) -> 4394.9624 | E88: =IFERROR(E$1*E32,0) -> 4431.4392 | F88: =IFERROR(F$1*F32,0) -> 4830.5241 | G88: =IFERROR(G$1*G32,0) -> 4510.8666 | H88: =IFERROR(H$1*H32,0) -> 4773.5091 | I88: =IFERROR(I$1*I32,0) -> 8367.9102 | J88: =IFERROR(J$1*J32,0) -> 8780 | L88: =C88/C$101 -> 0.11635895 | M88: =D88/D$101 -> 0.11486923 | N88: =E88/E$101 -> 0.12215407 | O88: =F88/F$101 -> 0.061003364 | P88: =G88/G$101 -> 0.059117735 | Q88: =H88/H$101 -> 0.063152904 | R88: =I88/I$101 -> 0.071609814 | S88: =J88/J$101 -> 0.084365481 | T88: =AVERAGE(L88:S88) -> 0.086578943
B89: Impuestos y contribuciones por pagar | C89: =IFERROR(C$1*C33,0) -> 0 | D89: =IFERROR(D$1*D33,0) -> 0 | E89: =IFERROR(E$1*E33,0) -> 0 | F89: =IFERROR(F$1*F33,0) -> 564.1488 | G89: =IFERROR(G$1*G33,0) -> 730.1854 | H89: =IFERROR(H$1*H33,0) -> 708.0561 | I89: =IFERROR(I$1*I33,0) -> 1105.155 | J89: =IFERROR(J$1*J33,0) -> 1380 | L89: =C89/C$101 -> 0 | M89: =D89/D$101 -> 0 | N89: =E89/E$101 -> 0 | O89: =F89/F$101 -> 0.0071244805 | P89: =G89/G$101 -> 0.0095695375 | Q89: =H89/H$101 -> 0.0093674901 | R89: =I89/I$101 -> 0.0094575517 | S89: =J89/J$101 -> 0.013260178
B90: Total de Pasivo circulante | C90: =SUM(C81:C89) -> 26964.31 | D90: =SUM(D81:D89) -> 26753.208 | E90: =SUM(E81:E89) -> 25426.85 | F90: =SUM(F81:F89) -> 31389.918 | G90: =SUM(G81:G89) -> 31763.065 | H90: =SUM(H81:H89) -> 34288.204 | I90: =SUM(I81:I89) -> 41558.141 | J90: =SUM(J81:J89) -> 43141 | L90: =C90/C$101 -> 0.7023303 | M90: =D90/D$101 -> 0.69923699 | N90: =E90/E$101 -> 0.70089941 | O90: =F90/F$101 -> 0.39641467 | P90: =G90/G$101 -> 0.41627488 | Q90: =H90/H$101 -> 0.45362847 | R90: =I90/I$101 -> 0.35564085 | S90: =J90/J$101 -> 0.41453431 | T90: =AVERAGE(L90:S90) -> 0.51736999
B91: Préstamos de instituciones financieras | C91: =IFERROR(C$1*C35,0) -> 4335.4498 | D91: =IFERROR(D$1*D35,0) -> 5703.5748 | E91: =IFERROR(E$1*E35,0) -> 6110.6352 | F91: =IFERROR(F$1*F35,0) -> 12688.124 | G91: =IFERROR(G$1*G35,0) -> 11109.249 | H91: =IFERROR(H$1*H35,0) -> 7644.0402 | I91: =IFERROR(I$1*I35,0) -> 18750.976 | J91: =IFERROR(J$1*J35,0) -> 12682 | L91: =C91/C$101 -> 0.112924 | M91: =D91/D$101 -> 0.14907186 | N91: =E91/E$101 -> 0.16844165 | O91: =F91/F$101 -> 0.16023484 | P91: =G91/G$101 -> 0.14559368 | Q91: =H91/H$101 -> 0.10112966 | R91: =I91/I$101 -> 0.16046467 | S91: =J91/J$101 -> 0.12185912 | T91: =AVERAGE(L91:S91) -> 0.13996493
B92: Beneficios a los empleados | C92: =IFERROR(C$1*C36,0) -> 716.3308 | D92: =IFERROR(D$1*D36,0) -> 659.3896 | E92: =IFERROR(E$1*E36,0) -> 734.4776 | F92: =IFERROR(F$1*F36,0) -> 795.2931 | G92: =IFERROR(G$1*G36,0) -> 1134.7132 | H92: =IFERROR(H$1*H36,0) -> 1325.9061 | I92: =IFERROR(I$1*I36,0) -> 3093.3558 | J92: =IFERROR(J$1*J36,0) -> 2292 | L92: =C92/C$101 -> 0.018658027 | M92: =D92/D$101 -> 0.01723418 | N92: =E92/E$101 -> 0.020246114 | O92: =F92/F$101 -> 0.010043538 | P92: =G92/G$101 -> 0.014871128 | Q92: =H92/H$101 -> 0.017541565 | R92: =I92/I$101 -> 0.026471918 | S92: =J92/J$101 -> 0.022023426
B93: Instrumentos Financieros Derivados | C93: =IFERROR(C$1*C37,0) -> 149.86 | D93: =IFERROR(D$1*D37,0) -> 0 | E93: =IFERROR(E$1*E37,0) -> 0 | F93: =IFERROR(F$1*F37,0) -> 0 | G93: =IFERROR(G$1*G37,0) -> 44.5235 | H93: =IFERROR(H$1*H37,0) -> 312.6321 | I93: =IFERROR(I$1*I37,0) -> 48.519 | J93: =IFERROR(J$1*J37,0) -> 0 | L93: =C93/C$101 -> 0.003903353 | M93: =D93/D$101 -> 0 | N93: =E93/E$101 -> 0 | O93: =F93/F$101 -> 0 | P93: =G93/G$101 -> 0.00058350839 | Q93: =H93/H$101 -> 0.004136082 | R93: =I93/I$101 -> 0.00041520959 | S93: =J93/J$101 -> 0
B94: Obligaciones relacionadas con derecho de cobro | C94: =IFERROR(C$1*C38,0) -> 0 | D94: =IFERROR(D$1*D38,0) -> 0 | E94: =IFERROR(E$1*E38,0) -> 0 | F94: =IFERROR(F$1*F38,0) -> 0 | G94: =IFERROR(G$1*G38,0) -> 0 | H94: =IFERROR(H$1*H38,0) -> 0 | I94: =IFERROR(I$1*I38,0) -> 0 | J94: =IFERROR(J$1*J38,0) -> 0 | L94: =C94/C$101 -> 0 | M94: =D94/D$101 -> 0 | N94: =E94/E$101 -> 0 | O94: =F94/F$101 -> 0 | P94: =G94/G$101 -> 0 | Q94: =H94/H$101 -> 0 | R94: =I94/I$101 -> 0 | S94: =J94/J$101 -> 0
B95: Fideicomitidos | C95: =IFERROR(C$1*C39,0) -> 1257.3254 | D95: =IFERROR(D$1*D39,0) -> 1077.6808 | E95: =IFERROR(E$1*E39,0) -> 711.2692 | F95: =IFERROR(F$1*F39,0) -> 528.8895 | G95: =IFERROR(G$1*G39,0) -> 400.7115 | H95: =IFERROR(H$1*H39,0) -> 0 | I95: =IFERROR(I$1*I39,0) -> 0 | J95: =IFERROR(J$1*J39,0) -> 0 | L95: =C95/C$101 -> 0.032749132 | M95: =D95/D$101 -> 0.028166875 | N95: =E95/E$101 -> 0.019606367 | O95: =F95/F$101 -> 0.0066792005 | P95: =G95/G$101 -> 0.0052515755 | Q95: =H95/H$101 -> 0 | R95: =I95/I$101 -> 0 | S95: =J95/J$101 -> 0
B96: Obligaciones por arrendamiento | C96: =IFERROR(C$1*C40,0) -> 227.7872 | D96: =IFERROR(D$1*D40,0) -> 198.9788 | E96: =IFERROR(E$1*E40,0) -> 208.8756 | F96: =IFERROR(F$1*F40,0) -> 29476.775 | G96: =IFERROR(G$1*G40,0) -> 27682.168 | H96: =IFERROR(H$1*H40,0) -> 27594.417 | I96: =IFERROR(I$1*I40,0) -> 48084.485 | J96: =IFERROR(J$1*J40,0) -> 41622 | L96: =C96/C$101 -> 0.0059330965 | M96: =D96/D$101 -> 0.0052006226 | N96: =E96/E$101 -> 0.005757724 | O96: =F96/F$101 -> 0.37225411 | P96: =G96/G$101 -> 0.36279217 | Q96: =H96/H$101 -> 0.36507054 | R96: =I96/I$101 -> 0.41149116 | S96: =J96/J$101 -> 0.3999385 | T96: =AVERAGE(L96:S96) -> 0.24105474
B97: Impuesto a la utilidad diferido | C97: =IFERROR(C$1*C41,0) -> 2211.9336 | D97: =IFERROR(D$1*D41,0) -> 2503.9376 | E97: =IFERROR(E$1*E41,0) -> 2458.7252 | F97: =IFERROR(F$1*F41,0) -> 3732.2622 | G97: =IFERROR(G$1*G41,0) -> 3633.1176 | H97: =IFERROR(H$1*H41,0) -> 3222.7056 | I97: =IFERROR(I$1*I41,0) -> 2830.275 | J97: =IFERROR(J$1*J41,0) -> 2069 | L97: =C97/C$101 -> 0.05761349 | M97: =D97/D$101 -> 0.065444331 | N97: =E97/E$101 -> 0.067775562 | O97: =F97/F$101 -> 0.047133716 | P97: =G97/G$101 -> 0.047614284 | Q97: =H97/H$101 -> 0.042635976 | R97: =I97/I$101 -> 0.024220559 | S97: =J97/J$101 -> 0.019880658
B98: Impuestos sobre la renta | C98: =IFERROR(C$1*C42,0) -> 1988.6422 | D98: =IFERROR(D$1*D42,0) -> 717.4856 | E98: =IFERROR(E$1*E42,0) -> 0 | F98: =IFERROR(F$1*F42,0) -> 0 | G98: =IFERROR(G$1*G42,0) -> 0 | H98: =IFERROR(H$1*H42,0) -> 0 | I98: =IFERROR(I$1*I42,0) -> 0 | J98: =IFERROR(J$1*J42,0) -> 0 | L98: =C98/C$101 -> 0.051797494 | M98: =D98/D$101 -> 0.01875261 | N98: =E98/E$101 -> 0 | O98: =F98/F$101 -> 0 | P98: =G98/G$101 -> 0 | Q98: =H98/H$101 -> 0 | R98: =I98/I$101 -> 0 | S98: =J98/J$101 -> 0
B99: Otros pasivos de largo plazo | C99: =IFERROR(C$1*C43,0) -> 540.9946 | D99: =IFERROR(D$1*D43,0) -> 646.318 | E99: =IFERROR(E$1*E43,0) -> 626.6268 | F99: =IFERROR(F$1*F43,0) -> 573.2901 | G99: =IFERROR(G$1*G43,0) -> 535.5541 | H99: =IFERROR(H$1*H43,0) -> 1198.629 | I99: =IFERROR(I$1*I43,0) -> 2488.4856 | J99: =IFERROR(J$1*J43,0) -> 2265 | L99: =C99/C$101 -> 0.014091104 | M99: =D99/D$101 -> 0.016892533 | N99: =E99/E$101 -> 0.017273172 | O99: =F99/F$101 -> 0.0072399235 | P99: =G99/G$101 -> 0.0070187723 | Q99: =H99/H$101 -> 0.015857706 | R99: =I99/I$101 -> 0.021295638 | S99: =J99/J$101 -> 0.021763988
B100: Total de Pasivo no circulante | C100: =SUM(C91:C99) -> 11428.324 | D100: =SUM(D91:D99) -> 11507.365 | E100: =SUM(E91:E99) -> 10850.61 | F100: =SUM(F91:F99) -> 47794.634 | G100: =SUM(G91:G99) -> 44540.037 | H100: =SUM(H91:H99) -> 41298.33 | I100: =SUM(I91:I99) -> 75296.097 | J100: =SUM(J91:J99) -> 60930 | L100: =C100/C$101 -> 0.2976697 | M100: =D100/D$101 -> 0.30076301 | N100: =E100/E$101 -> 0.29910059 | O100: =F100/F$101 -> 0.60358533 | P100: =G100/G$101 -> 0.58372512 | Q100: =H100/H$101 -> 0.54637153 | R100: =I100/I$101 -> 0.64435915 | S100: =J100/J$101 -> 0.58546569 | T100: =AVERAGE(L100:S100) -> 0.48263001
B101: Total del Pasivo | C101: =C90+C100 -> 38392.633 | D101: =D90+D100 -> 38260.573 | E101: =E90+E100 -> 36277.46 | F101: =F90+F100 -> 79184.552 | G101: =G90+G100 -> 76303.102 | H101: =H90+H100 -> 75586.533 | I101: =I90+I100 -> 116854.24 | J101: =J90+J100 -> 104071 | L101: =C101/C$101 -> 1 | M101: =D101/D$101 -> 1 | N101: =E101/E$101 -> 1 | O101: =F101/F$101 -> 1 | P101: =G101/G$101 -> 1 | Q101: =H101/H$101 -> 1 | R101: =I101/I$101 -> 1 | S101: =J101/J$101 -> 1
B102: Capital Contable | C102: =C109+C110 -> 37599.874 | D102: =D109+D110 -> 39124.751 | E102: =E109+E110 -> 38815.366 | F102: =F109+F110 -> 35032.073 | G102: =G109+G110 -> 34868.261 | H102: =H109+H110 -> 36183.767 | I102: =I109+I110 -> 35214.012 | J102: =J109+J110 -> 39368
B103: Capital social | C103: =IFERROR(C$1*C46,0) -> 377.6472 | D103: =IFERROR(D$1*D46,0) -> 366.0048 | E103: =IFERROR(E$1*E46,0) -> 344.0304 | F103: =IFERROR(F$1*F46,0) -> 329.0868 | G103: =IFERROR(G$1*G46,0) -> 320.5692 | H103: =IFERROR(H$1*H46,0) -> 311.3964 | I103: =IFERROR(I$1*I46,0) -> 271.7064 | J103: =IFERROR(J$1*J46,0) -> 252 | L103: =C103/C$102 -> 0.010043842 | M103: =D103/D$102 -> 0.0093548148 | N103: =E103/E$102 -> 0.0088632527 | O103: =F103/F$102 -> 0.0093938716 | P103: =G103/G$102 -> 0.0091937249 | Q103: =H103/H$102 -> 0.0086059695 | R103: =I103/I$102 -> 0.0077158604 | S103: =J103/J$102 -> 0.006401138
...

Sheet Estado de resultados
B1: Factor INPC | C1: =I1+42.04% -> 1.4986 | D1: =I1+37.42% -> 1.4524 | E1: =I1+28.7% -> 1.3652 | F1: =I1+22.77% -> 1.3059 | G1: =I1+19.39% -> 1.2721 | H1: =I1+15.75% -> 1.2357 | I1: =J1+7.82% -> 1.0782 | J1: 1
B3: Información de Estado de Resultados | C3: 31 de diciembre
B4: Millones de pesos, excepto importes por acción y número de acciones | C4: 2015 | D4: 2016 | E4: 2017 | F4: 2018 | G4: 2019 | H4: 2020 | I4: 2021 | J4: 2022
B5: Ventas netas | C5: 78648 | D5: 88529 | E5: 94583 | F5: 116031 | G5: 129443 | H5: 146287 | I5: 188487 | J5: 259326
B6: Costo de ventas | C6: 63068 | D6: 70313 | E6: 74916 | F6: 91311 | G6: 101491 | H6: 113908 | I6: 146535 | J6: 200026
B7: Utilidad bruta | C7: 15580 | D7: 18216 | E7: 19666 | F7: 24720 | G7: 27952 | H7: 32380 | I7: 41952 | J7: 59300
B8: Gastos de operación | C8: 11901 | D8: 13961 | E8: 15248 | F8: 19558 | G8: 22376 | H8: 25446 | I8: 33204 | J8: 45554
B9: Utilidad de operación | C9: 3678 | D9: 4254 | E9: 4418 | F9: 5161 | G9: 5576 | H9: 6933 | I9: 8748 | J9: 13746
B10: Gastos por intereses | C10: 543 | D10: 647 | E10: 672 | F10: 2018 | G10: 2344 | H10: 2306 | I10: 2658 | J10: 3382
B11: Ingresos por intereses | C11: -35 | D11: -68 | E11: -72 | F11: -88 | G11: -63 | H11: -136 | I11: -135 | J11: -269
B12: Perdida (ganancia) cambiaria | C12: 5 | D12: 9 | E12: -36 | F12: 8 | G12: -56 | H12: 10 | I12: -25 | J12: -50
B13: Otros gastos financieros | C13: 526 | D13: 593 | E13: 617 | F13: 789 | G13: 885 | H13: 1006 | I13: 1356 | J13: 2049
C14: =C10+C11+C12+C13 -> 1039 | D14: =D10+D11+D12+D13 -> 1181 | E14: =E10+E11+E12+E13 -> 1181 | F14: =F10+F11+F12+F13 -> 2727 | G14: =G10+G11+G12+G13 -> 3110 | H14: =H10+H11+H12+H13 -> 3186 | I14: =I10+I11+I12+I13 -> 3854 | J14: 5112
B15: Participación en los resultados de compañías asociadas | I15: 54 | J15: 89
B16: Utilidad antes de impuesto a la utilidad | C16: 2639 | D16: 3073 | E16: 3238 | F16: 2435 | G16: 2465 | H16: 3748 | I16: 4950 | J16: 8722
B17: Impuestos a la utilidad | C17: 850 | D17: 1063 | E17: 1120 | F17: 848 | G17: 928 | H17: 1073 | I17: 1469 | J17: 2546
B18: Utilidad neta consolidada | C18: 1790 | D18: 2010 | E18: 2117 | F18: 1586 | G18: 1537 | H18: 2674 | I18: 3480 | J18: 6176
B19: Participación controladora | C19: 1740 | D19: 1953 | E19: 2079 | F19: 1638 | G19: 1566 | H19: 2589 | I19: 3420 | J19: 5997
B20: Participación no controladora | C20: 50 | D20: 57 | E20: 38 | F20: -51 | G20: -29 | H20: 85 | I20: 60 | J20: 179
B21: Utilidad neta consolidada | C21: =C18 -> 1790 | D21: =D18 -> 2010 | E21: =E18 -> 2117 | F21: =F18 -> 1586 | G21: =G18 -> 1537 | H21: =H18 -> 2674 | I21: =I18 -> 3480 | J21: 6176
B22: Promedio ponderado de acciones en circulación | C22: 963917211 | D22: 963917211 | E22: 963917211 | F22: 963917211 | G22: 963917211 | H22: 963917211 | I22: 963917211 | J22: 963917211
B23: Utilidad básica por acción ordinaria | C23: 1.8 | D23: 2 | E23: 2.2 | F23: 1.7 | G23: 1.6 | H23: 2.7 | I23: 3.5 | J23: 6.2
B24: Recursos generado por (utilizados en)
B25: Actividades de operación | C25: 4420 | D25: 3439 | E25: 5104 | F25: 6783 | G25: 5554 | H25: 12318 | I25: 16103 | J25: 18540
B26: Actividades de inverción | C26: -2735 | D26: -3358 | E26: -3093 | F26: -8840 | G26: -2845 | H26: -2536 | I26: -15622 | J26: -6481
B27: Actividades de financiamiento | C27: -415 | D27: -1143 | E27: -1442 | F27: 1960 | G27: -3079 | H27: -5274 | I27: 3528 | J27: -9516
B30: Información de Estado de Resultados | C30: 31 de diciembre | L30: Análisis vertical
B31: Millones de pesos, excepto importes por acción y número de acciones | C31: 2015 | D31: 2016 | E31: 2017 | F31: 2018 | G31: 2019 | H31: 2020 | I31: 2021 | J31: 2022 | L31: =C31 -> 2015 | M31: =D31 -> 2016 | N31: =E31 -> 2017 | O31: =F31 -> 2018 | P31: =G31 -> 2019 | Q31: =H31 -> 2020 | R31: =I31 -> 2021 | S31: =J31 -> 2022 | T31: Promedio
B32: Ventas netas | C32: =IFERROR(C$1*C5,0) -> 117861.89 | D32: =IFERROR(D$1*D5,0) -> 128579.52 | E32: =IFERROR(E$1*E5,0) -> 129124.71 | F32: =IFERROR(F$1*F5,0) -> 151524.88 | G32: =IFERROR(G$1*G5,0) -> 164664.44 | H32: =IFERROR(H$1*H5,0) -> 180766.85 | I32: =IFERROR(I$1*I5,0) -> 203226.68 | J32: =IFERROR(J$1*J5,0) -> 259326 | L32: =C32/C$32 -> 1 | M32: =D32/D$32 -> 1 | N32: =E32/E$32 -> 1 | O32: =F32/F$32 -> 1 | P32: =G32/G$32 -> 1 | Q32: =H32/H$32 -> 1 | R32: =I32/I$32 -> 1 | S32: =J32/J$32 -> 1
B33: Costo de ventas | C33: =IFERROR(C6*C$1,0) -> 94513.705 | D33: =IFERROR(D6*D$1,0) -> 102122.6 | E33: =IFERROR(E6*E$1,0) -> 102275.32 | F33: =IFERROR(F6*F$1,0) -> 119243.03 | G33: =IFERROR(G6*G$1,0) -> 129106.7 | H33: =IFERROR(H6*H$1,0) -> 140756.12 | I33: =IFERROR(I6*I$1,0) -> 157994.04 | J33: =IFERROR(J6*J$1,0) -> 200026 | L33: =C33/C$32 -> 0.80190215 | M33: =D33/D$32 -> 0.79423692 | N33: =E33/E$32 -> 0.79206623 | O33: =F33/F$32 -> 0.78695349 | P33: =G33/G$32 -> 0.78405939 | Q33: =H33/H$32 -> 0.77866113 | R33: =I33/I$32 -> 0.77742762 | S33: =J33/J$32 -> 0.77133029 | T33: =AVERAGE(L33:S33) -> 0.78582965
B34: Utilidad bruta | C34: =IFERROR(C7*C$1,0) -> 23348.188 | D34: =IFERROR(D7*D$1,0) -> 26456.918 | E34: =IFERROR(E7*E$1,0) -> 26848.023 | F34: =IFERROR(F7*F$1,0) -> 32281.848 | G34: =IFERROR(G7*G$1,0) -> 35557.739 | H34: =IFERROR(H7*H$1,0) -> 40011.966 | I34: =IFERROR(I7*I$1,0) -> 45232.646 | J34: =IFERROR(J7*J$1,0) -> 59300 | L34: =C34/C$32 -> 0.19809785 | M34: =D34/D$32 -> 0.20576308 | N34: =E34/E$32 -> 0.2079232 | O34: =F34/F$32 -> 0.21304651 | P34: =G34/G$32 -> 0.21594061 | Q34: =H34/H$32 -> 0.22134571 | R34: =I34/I$32 -> 0.22257238 | S34: =J34/J$32 -> 0.22866971 | T34: =AVERAGE(L34:S34) -> 0.21416988
B35: Gastos de operación | C35: =IFERROR(C8*C$1,0) -> 17834.839 | D35: =IFERROR(D8*D$1,0) -> 20276.956 | E35: =IFERROR(E8*E$1,0) -> 20816.57 | F35: =IFERROR(F8*F$1,0) -> 25540.792 | G35: =IFERROR(G8*G$1,0) -> 28464.51 | H35: =IFERROR(H8*H$1,0) -> 31443.622 | I35: =IFERROR(I8*I$1,0) -> 35800.553 | J35: =IFERROR(J8*J$1,0) -> 45554 | L35: =C35/C$32 -> 0.1513198 | M35: =D35/D$32 -> 0.15769974 | N35: =E35/E$32 -> 0.1612129 | O35: =F35/F$32 -> 0.1685584 | P35: =G35/G$32 -> 0.17286373 | Q35: =H35/H$32 -> 0.17394574 | R35: =I35/I$32 -> 0.17616069 | S35: =J35/J$32 -> 0.17566307 | T35: =AVERAGE(L35:S35) -> 0.16717801
B36: Utilidad de operación | C36: =IFERROR(C9*C$1,0) -> 5511.8508 | D36: =IFERROR(D9*D$1,0) -> 6178.5096 | E36: =IFERROR(E9*E$1,0) -> 6031.4536 | F36: =IFERROR(F9*F$1,0) -> 6739.7499 | G36: =IFERROR(G9*G$1,0) -> 7093.2296 | H36: =IFERROR(H9*H$1,0) -> 8567.1081 | I36: =IFERROR(I9*I$1,0) -> 9432.0936 | J36: =IFERROR(J9*J$1,0) -> 13746 | L36: =C36/C$32 -> 0.046765334 | M36: =D36/D$32 -> 0.048052051 | N36: =E36/E$32 -> 0.046710297 | O36: =F36/F$32 -> 0.044479493 | P36: =G36/G$32 -> 0.043076876 | Q36: =H36/H$32 -> 0.047393138 | R36: =I36/I$32 -> 0.046411689 | S36: =J36/J$32 -> 0.05300664
B37: Gastos por intereses | C37: =IFERROR(C10*C$1,0) -> 813.7398 | D37: =IFERROR(D10*D$1,0) -> 939.7028 | E37: =IFERROR(E10*E$1,0) -> 917.4144 | F37: =IFERROR(F10*F$1,0) -> 2635.3062 | G37: =IFERROR(G10*G$1,0) -> 2981.8024 | H37: =IFERROR(H10*H$1,0) -> 2849.5242 | I37: =IFERROR(I10*I$1,0) -> 2865.8556 | J37: =IFERROR(J10*J$1,0) -> 3382 | L37: =C37/C$32 -> 0.0069041807 | M37: =D37/D$32 -> 0.0073083396 | N37: =E37/E$32 -> 0.0071048709 | O37: =F37/F$32 -> 0.017391904 | P37: =G37/G$32 -> 0.018108357 | Q37: =H37/H$32 -> 0.015763533 | R37: =I37/I$32 -> 0.014101768 | S37: =J37/J$32 -> 0.0130415
B38: Ingresos por intereses | C38: =IFERROR(C11*C$1,0) -> -52.451 | D38: =IFERROR(D11*D$1,0) -> -98.7632 | E38: =IFERROR(E11*E$1,0) -> -98.2944 | F38: =IFERROR(F11*F$1,0) -> -114.9192 | G38: =IFERROR(G11*G$1,0) -> -80.1423 | H38: =IFERROR(H11*H$1,0) -> -168.0552 | I38: =IFERROR(I11*I$1,0) -> -145.557 | J38: =IFERROR(J11*J$1,0) -> -269 | L38: =C38/C$32 -> -0.00044502085 | M38: =D38/D$32 -> -0.00076810988 | N38: =E38/E$32 -> -0.00076123616 | O38: =F38/F$32 -> -0.00075841801 | P38: =G38/G$32 -> -0.00048670071 | Q38: =H38/H$32 -> -0.00092967933 | R38: =I38/I$32 -> -0.00071622977 | S38: =J38/J$32 -> -0.0010373044
B39: Perdida (ganancia) cambiaria | C39: =IFERROR(C12*C$1,0) -> 7.493 | D39: =IFERROR(D12*D$1,0) -> 13.0716 | E39: =IFERROR(E12*E$1,0) -> -49.1472 | F39: =IFERROR(F12*F$1,0) -> 10.4472 | G39: =IFERROR(G12*G$1,0) -> -71.2376 | H39: =IFERROR(H12*H$1,0) -> 12.357 | I39: =IFERROR(I12*I$1,0) -> -26.955 | J39: =IFERROR(J12*J$1,0) -> -50 | L39: =C39/C$32 -> 6.3574407e-05 | M39: =D39/D$32 -> 0.0001016616 | N39: =E39/E$32 -> -0.00038061808 | O39: =F39/F$32 -> 6.8947092e-05 | P39: =G39/G$32 -> -0.00043262285 | Q39: =H39/H$32 -> 6.8358774e-05 | R39: =I39/I$32 -> -0.00013263514 | S39: =J39/J$32 -> -0.00019280751
B40: Otros gastos financieros | C40: =IFERROR(C13*C$1,0) -> 788.2636 | D40: =IFERROR(D13*D$1,0) -> 861.2732 | E40: =IFERROR(E13*E$1,0) -> 842.3284 | F40: =IFERROR(F13*F$1,0) -> 1030.3551 | G40: =IFERROR(G13*G$1,0) -> 1125.8085 | H40: =IFERROR(H13*H$1,0) -> 1243.1142 | I40: =IFERROR(I13*I$1,0) -> 1462.0392 | J40: =IFERROR(J13*J$1,0) -> 2049 | L40: =C40/C$32 -> 0.0066880277 | M40: =D40/D$32 -> 0.00669837 | N40: =E40/E$32 -> 0.006523371 | O40: =F40/F$32 -> 0.0067999069 | P40: =G40/G$32 -> 0.0068369862 | Q40: =H40/H$32 -> 0.0068768927 | R40: =I40/I$32 -> 0.0071941301 | S40: =J40/J$32 -> 0.0079012517
C41: =IFERROR(C14*C$1,0) -> 1557.0454 | D41: =IFERROR(D14*D$1,0) -> 1715.2844 | E41: =IFERROR(E14*E$1,0) -> 1612.3012 | F41: =IFERROR(F14*F$1,0) -> 3561.1893 | G41: =IFERROR(G14*G$1,0) -> 3956.231 | H41: =IFERROR(H14*H$1,0) -> 3936.9402 | I41: =IFERROR(I14*I$1,0) -> 4155.3828 | J41: =IFERROR(J14*J$1,0) -> 5112 | L41: =C41/C$32 -> 0.013210762 | M41: =D41/D$32 -> 0.013340261 | N41: =E41/E$32 -> 0.012486388 | O41: =F41/F$32 -> 0.02350234 | P41: =G41/G$32 -> 0.024026019 | Q41: =H41/H$32 -> 0.021779105 | R41: =I41/I$32 -> 0.020447033 | S41: =J41/J$32 -> 0.01971264
B42: Participación en los resultados de compañías asociadas | C42: =IFERROR(C15*C$1,0) -> 0 | D42: =IFERROR(D15*D$1,0) -> 0 | E42: =IFERROR(E15*E$1,0) -> 0 | F42: =IFERROR(F15*F$1,0) -> 0 | G42: =IFERROR(G15*G$1,0) -> 0 | H42: =IFERROR(H15*H$1,0) -> 0 | I42: =IFERROR(I15*I$1,0) -> 58.2228 | J42: =IFERROR(J15*J$1,0) -> 89 | L42: =C42/C$32 -> 0 | M42: =D42/D$32 -> 0 | N42: =E42/E$32 -> 0 | O42: =F42/F$32 -> 0 | P42: =G42/G$32 -> 0 | Q42: =H42/H$32 -> 0 | R42: =I42/I$32 -> 0.00028649191 | S42: =J42/J$32 -> 0.00034319737
B43: Utilidad antes de impuesto a la utilidad | C43: =IFERROR(C16*C$1,0) -> 3954.8054 | D43: =IFERROR(D16*D$1,0) -> 4463.2252 | E43: =IFERROR(E16*E$1,0) -> 4420.5176 | F43: =IFERROR(F16*F$1,0) -> 3179.8665 | G43: =IFERROR(G16*G$1,0) -> 3135.7265 | H43: =IFERROR(H16*H$1,0) -> 4631.4036 | I43: =IFERROR(I16*I$1,0) -> 5337.09 | J43: =IFERROR(J16*J$1,0) -> 8722 | L43: =C43/C$32 -> 0.033554572 | M43: =D43/D$32 -> 0.034711789 | N43: =E43/E$32 -> 0.034234482 | O43: =F43/F$32 -> 0.020985771 | P43: =G43/G$32 -> 0.019043131 | Q43: =H43/H$32 -> 0.025620869 | R43: =I43/I$32 -> 0.026261758 | S43: =J43/J$32 -> 0.033633342
B44: Impuestos a la utilidad | C44: =IFERROR(C17*C$1,0) -> 1273.81 | D44: =IFERROR(D17*D$1,0) -> 1543.9012 | E44: =IFERROR(E17*E$1,0) -> 1529.024 | F44: =IFERROR(F17*F$1,0) -> 1107.4032 | G44: =IFERROR(G17*G$1,0) -> 1180.5088 | H44: =IFERROR(H17*H$1,0) -> 1325.9061 | I44: =IFERROR(I17*I$1,0) -> 1583.8758 | J44: =IFERROR(J17*J$1,0) -> 2546 | L44: =C44/C$32 -> 0.010807649 | M44: =D44/D$32 -> 0.012007365 | N44: =E44/E$32 -> 0.011841451 | O44: =F44/F$32 -> 0.0073083917 | P44: =G44/G$32 -> 0.0071691787 | Q44: =H44/H$32 -> 0.0073348965 | R44: =I44/I$32 -> 0.0077936409 | S44: =J44/J$32 -> 0.0098177583
B45: Utilidad neta consolidada | C45: =IFERROR(C18*C$1,0) -> 2682.494 | D45: =IFERROR(D18*D$1,0) -> 2919.324 | E45: =IFERROR(E18*E$1,0) -> 2890.1284 | F45: =IFERROR(F18*F$1,0) -> 2071.1574 | G45: =IFERROR(G18*G$1,0) -> 1955.2177 | H45: =IFERROR(H18*H$1,0) -> 3304.2618 | I45: =IFERROR(I18*I$1,0) -> 3752.136 | J45: =IFERROR(J18*J$1,0) -> 6176 | L45: =C45/C$32 -> 0.022759638 | M45: =D45/D$32 -> 0.022704425 | N45: =E45/E$32 -> 0.022382458 | O45: =F45/F$32 -> 0.013668761 | P45: =G45/G$32 -> 0.011873952 | Q45: =H45/H$32 -> 0.018279136 | R45: =I45/I$32 -> 0.018462812 | S45: =J45/J$32 -> 0.023815583
B46: Participación controladora | C46: =IFERROR(C19*C$1,0) -> 2607.564 | D46: =IFERROR(D19*D$1,0) -> 2836.5372 | E46: =IFERROR(E19*E$1,0) -> 2838.2508 | F46: =IFERROR(F19*F$1,0) -> 2139.0642 | G46: =IFERROR(G19*G$1,0) -> 1992.1086 | H46: =IFERROR(H19*H$1,0) -> 3199.2273 | I46: =IFERROR(I19*I$1,0) -> 3687.444 | J46: =IFERROR(J19*J$1,0) -> 5997 | L46: =C46/C$32 -> 0.022123894 | M46: =D46/D$32 -> 0.022060568 | N46: =E46/E$32 -> 0.021980694 | O46: =F46/F$32 -> 0.014116917 | P46: =G46/G$32 -> 0.012097989 | Q46: =H46/H$32 -> 0.017698087 | R46: =I46/I$32 -> 0.018144487 | S46: =J46/J$32 -> 0.023125333
B47: Participación no controladora | C47: =IFERROR(C20*C$1,0) -> 74.93 | D47: =IFERROR(D20*D$1,0) -> 82.7868 | E47: =IFERROR(E20*E$1,0) -> 51.8776 | F47: =IFERROR(F20*F$1,0) -> -66.6009 | G47: =IFERROR(G20*G$1,0) -> -36.8909 | H47: =IFERROR(H20*H$1,0) -> 105.0345 | I47: =IFERROR(I20*I$1,0) -> 64.692 | J47: =IFERROR(J20*J$1,0) -> 179 | L47: =C47/C$32 -> 0.00063574407 | M47: =D47/D$32 -> 0.00064385682 | N47: =E47/E$32 -> 0.00040176353 | O47: =F47/F$32 -> -0.00043953771 | P47: =G47/G$32 -> -0.00022403683 | Q47: =H47/H$32 -> 0.00058104958 | R47: =I47/I$32 -> 0.00031832434 | S47: =J47/J$32 -> 0.00069025088
B48: Utilidad neta consolidada | C48: =IFERROR(C21*C$1,0) -> 2682.494 | D48: =IFERROR(D21*D$1,0) -> 2919.324 | E48: =IFERROR(E21*E$1,0) -> 2890.1284 | F48: =IFERROR(F21*F$1,0) -> 2071.1574 | G48: =IFERROR(G21*G$1,0) -> 1955.2177 | H48: =IFERROR(H21*H$1,0) -> 3304.2618 | I48: =IFERROR(I21*I$1,0) -> 3752.136 | J48: =IFERROR(J21*J$1,0) -> 6176 | L48: =C48/C$32 -> 0.022759638 | M48: =D48/D$32 -> 0.022704425 | N48: =E48/E$32 -> 0.022382458 | O48: =F48/F$32 -> 0.013668761 | P48: =G48/G$32 -> 0.011873952 | Q48: =H48/H$32 -> 0.018279136 | R48: =I48/I$32 -> 0.018462812 | S48: =J48/J$32 -> 0.023815583
B49: Promedio ponderado de acciones en circulación | C49: 963917211 | D49: 963917211 | E49: 963917211 | F49: 963917211 | G49: 963917211 | H49: 963917211 | I49: 963917211 | J49: =IFERROR(J22*J$1,0) -> 963917211
B50: Utilidad básica por acción ordinaria | C50: 1.8 | D50: 2 | E50: 2.2 | F50: 1.7 | G50: 1.6 | H50: 2.7 | I50: 3.5 | J50: =IFERROR(J23*J$1,0) -> 6.2
B51: Recursos generado por (utilizados en) | L51: =C51/C$32 -> 0 | M51: =D51/D$32 -> 0 | N51: =E51/E$32 -> 0 | O51: =F51/F$32 -> 0 | P51: =G51/G$32 -> 0 | Q51: =H51/H$32 -> 0 | R51: =I51/I$32 -> 0 | S51: =J51/J$32 -> 0
B52: Actividades de operación | C52: =IFERROR(C25*C$1,0) -> 6623.812 | D52: =IFERROR(D25*D$1,0) -> 4994.8036 | E52: =IFERROR(E25*E$1,0) -> 6967.9808 | F52: =IFERROR(F25*F$1,0) -> 8857.9197 | G52: =IFERROR(G25*G$1,0) -> 7065.2434 | H52: =IFERROR(H25*H$1,0) -> 15221.353 | I52: =IFERROR(I25*I$1,0) -> 17362.255 | J52: =IFERROR(J25*J$1,0) -> 18540 | L52: =C52/C$32 -> 0.056199776 | M52: =D52/D$32 -> 0.038846028 | N52: =E52/E$32 -> 0.053963186 | O52: =F52/F$32 -> 0.058458515 | P52: =G52/G$32 -> 0.042906917 | Q52: =H52/H$32 -> 0.084204338 | R52: =I52/I$32 -> 0.085432948 | S52: =J52/J$32 -> 0.071493024
B53: Actividades de inverción | C53: =IFERROR(C26*C$1,0) -> -4098.671 | D53: =IFERROR(D26*D$1,0) -> -4877.1592 | E53: =IFERROR(E26*E$1,0) -> -4222.5636 | F53: =IFERROR(F26*F$1,0) -> -11544.156 | G53: =IFERROR(G26*G$1,0) -> -3619.1245 | H53: =IFERROR(H26*H$1,0) -> -3133.7352 | I53: =IFERROR(I26*I$1,0) -> -16843.64 | J53: =IFERROR(J26*J$1,0) -> -6481 | L53: =C53/C$32 -> -0.034775201 | M53: =D53/D$32 -> -0.037931073 | N53: =E53/E$32 -> -0.032701437 | O53: =F53/F$32 -> -0.076186536 | P53: =G53/G$32 -> -0.021978786 | Q53: =H53/H$32 -> -0.017335785 | R53: =I53/I$32 -> -0.082881047 | S53: =J53/J$32 -> -0.024991709
B54: Actividades de financiamiento | C54: =IFERROR(C27*C$1,0) -> -621.919 | D54: =IFERROR(D27*D$1,0) -> -1660.0932 | E54: =IFERROR(E27*E$1,0) -> -1968.6184 | F54: =IFERROR(F27*F$1,0) -> 2559.564 | G54: =IFERROR(G27*G$1,0) -> -3916.7959 | H54: =IFERROR(H27*H$1,0) -> -6517.0818 | I54: =IFERROR(I27*I$1,0) -> 3803.8896 | J54: =IFERROR(J27*J$1,0) -> -9516 | L54: =C54/C$32 -> -0.0052766758 | M54: =D54/D$32 -> -0.012911024 | N54: =E54/E$32 -> -0.015245869 | O54: =F54/F$32 -> 0.016892037 | P54: =G54/G$32 -> -0.023786532 | Q54: =H54/H$32 -> -0.036052418 | R54: =I54/I$32 -> 0.018717471 | S54: =J54/J$32 -> -0.036695125
U55: Se puede apreciar que el costo de ventas se ha mantenido estable pero los gastos de operación han incrementado.
B57: Información de Estado de Resultados | C57: 31 de diciembre | L57: Análisis horizontal
B58: Millones de pesos, excepto importes por acción y número de acciones | C58: 2015 | D58: 2016 | E58: 2017 | F58: 2018 | G58: 2019 | H58: 2020 | I58: 2021 | J58: 2022 | L58: =D58 -> 2016 | M58: =E58 -> 2017 | N58: =F58 -> 2018 | O58: =G58 -> 2019 | P58: =H58 -> 2020 | Q58: =I58 -> 2021 | R58: =J58 -> 2022 | S58: Promedio
B59: Ventas netas | C59: =C32 -> 117861.89 | D59: =D32 -> 128579.52 | E59: =E32 -> 129124.71 | F59: =F32 -> 151524.88 | G59: =G32 -> 164664.44 | H59: =H32 -> 180766.85 | I59: =I32 -> 203226.68 | J59: =J32 -> 259326 | L59: =D59/C59-1 -> 0.090933775 | M59: =E59/D59-1 -> 0.0042401154 | N59: =F59/E59-1 -> 0.17347703 | O59: =G59/F59-1 -> 0.086715509 | P59: =H59/G59-1 -> 0.09778921 | Q59: =I59/H59-1 -> 0.12424755 | R59: =J59/I59-1 -> 0.27604307 | S59: =AVERAGE(L59:R59) -> 0.12192089
B60: Costo de ventas | C60: =C33 -> 94513.705 | D60: =D33 -> 102122.6 | E60: =E33 -> 102275.32 | F60: =F33 -> 119243.03 | G60: =G33 -> 129106.7 | H60: =H33 -> 140756.12 | I60: =I33 -> 157994.04 | J60: =J33 -> 200026 | L60: =D60/C60-1 -> 0.080505747 | M60: =E60/D60-1 -> 0.001495477 | N60: =F60/E60-1 -> 0.1659023 | O60: =G60/F60-1 -> 0.082719013 | P60: =H60/G60-1 -> 0.090230905 | Q60: =I60/H60-1 -> 0.12246659 | R60: =J60/I60-1 -> 0.26603512 | S60: =AVERAGE(L60:R60) -> 0.11562217
B61: Utilidad bruta | C61: =C34 -> 23348.188 | D61: =D34 -> 26456.918 | E61: =E34 -> 26848.023 | F61: =F34 -> 32281.848 | G61: =G34 -> 35557.739 | H61: =H34 -> 40011.966 | I61: =I34 -> 45232.646 | J61: =J34 -> 59300 | L61: =D61/C61-1 -> 0.13314654 | M61: =E61/D61-1 -> 0.014782704 | N61: =F61/E61-1 -> 0.20239199 | O61: =G61/F61-1 -> 0.10147781 | P61: =H61/G61-1 -> 0.12526744 | Q61: =I61/H61-1 -> 0.13047798 | R61: =J61/I61-1 -> 0.31100001 | S61: =AVERAGE(L61:R61) -> 0.14550635
B62: Gastos de operación | C62: =C35 -> 17834.839 | D62: =D35 -> 20276.956 | E62: =E35 -> 20816.57 | F62: =F35 -> 25540.792 | G62: =G35 -> 28464.51 | H62: =H35 -> 31443.622 | I62: =I35 -> 35800.553 | J62: =J35 -> 45554 | L62: =D62/C62-1 -> 0.13692963 | M62: =E62/D62-1 -> 0.02661214 | N62: =F62/E62-1 -> 0.2269453 | O62: =G62/F62-1 -> 0.11447246 | P62: =H62/G62-1 -> 0.1046606 | Q62: =I62/H62-1 -> 0.13856325 | R62: =J62/I62-1 -> 0.27243845 | S62: =AVERAGE(L62:R62) -> 0.14580312
B63: Utilidad de operación | C63: =C36 -> 5511.8508 | D63: =D36 -> 6178.5096 | E63: =E36 -> 6031.4536 | F63: =F36 -> 6739.7499 | G63: =G36 -> 7093.2296 | H63: =H36 -> 8567.1081 | I63: =I36 -> 9432.0936 | J63: =J36 -> 13746 | L63: =D63/C63-1 -> 0.12095008 | M63: =E63/D63-1 -> -0.023801209 | N63: =F63/E63-1 -> 0.11743376 | O63: =G63/F63-1 -> 0.052447005 | P63: =H63/G63-1 -> 0.20778666 | Q63: =I63/H63-1 -> 0.10096587 | R63: =J63/I63-1 -> 0.45736467 | S63: =AVERAGE(L63:R63) -> 0.14759241
B64: Gastos por intereses | C64: =C37 -> 813.7398 | D64: =D37 -> 939.7028 | E64: =E37 -> 917.4144 | F64: =F37 -> 2635.3062 | G64: =G37 -> 2981.8024 | H64: =H37 -> 2849.5242 | I64: =I37 -> 2865.8556 | J64: =J37 -> 3382 | L64: =D64/C64-1 -> 0.15479518 | M64: =E64/D64-1 -> -0.023718563 | N64: =F64/E64-1 -> 1.8725363 | O64: =G64/F64-1 -> 0.13148233 | P64: =H64/G64-1 -> -0.044361826 | Q64: =I64/H64-1 -> 0.0057312726 | R64: =J64/I64-1 -> 0.18010133 | S64: =AVERAGE(L64:R64) -> 0.32522372
B65: Ingresos por intereses | C65: =C38 -> -52.451 | D65: =D38 -> -98.7632 | E65: =E38 -> -98.2944 | F65: =F38 -> -114.9192 | G65: =G38 -> -80.1423 | H65: =H38 -> -168.0552 | I65: =I38 -> -145.557 | J65: =J38 -> -269 | L65: =D65/C65-1 -> 0.88296124 | M65: =E65/D65-1 -> -0.0047467073 | N65: =F65/E65-1 -> 0.16913273 | O65: =G65/F65-1 -> -0.30262045 | P65: =H65/G65-1 -> 1.09696 | Q65: =I65/H65-1 -> -0.13387387 | R65: =J65/I65-1 -> 0.84807326 | S65: =AVERAGE(L65:R65) -> 0.36512661
B66: Perdida (ganancia) cambiaria | C66: =C39 -> 7.493 | D66: =D39 -> 13.0716 | E66: =E39 -> -49.1472 | F66: =F39 -> 10.4472 | G66: =G39 -> -71.2376 | H66: =H39 -> 12.357 | I66: =I39 -> -26.955 | J66: =J39 -> -50 | L66: =D66/C66-1 -> 0.74450821 | M66: =E66/D66-1 -> -4.7598458 | N66: =F66/E66-1 -> -1.2125696 | O66: =G66/F66-1 -> -7.8188223 | P66: =H66/G66-1 -> -1.1734618 | Q66: =I66/H66-1 -> -3.1813547 | R66: =J66/I66-1 -> 0.85494342 | S66: =AVERAGE(L66:R66) -> -2.3638004
B67: Otros gastos financieros | C67: =C40 -> 788.2636 | D67: =D40 -> 861.2732 | E67: =E40 -> 842.3284 | F67: =F40 -> 1030.3551 | G67: =G40 -> 1125.8085 | H67: =H40 -> 1243.1142 | I67: =I40 -> 1462.0392 | J67: =J40 -> 2049 | L67: =D67/C67-1 -> 0.092620793 | M67: =E67/D67-1 -> -0.021996272 | N67: =F67/E67-1 -> 0.22322256 | O67: =G67/F67-1 -> 0.092641265 | P67: =H67/G67-1 -> 0.10419685 | Q67: =I67/H67-1 -> 0.17611013 | R67: =J67/I67-1 -> 0.40146721 | S67: =AVERAGE(L67:R67) -> 0.15260893
L69: Se puede observar el incremento en el costo de ventas y de los gastos de operación desde el 2019.
L70: Sin embargo, la utilidad también incrementó.
B75: Ingresos
B76: Periodo | C76: =C58 -> 2015 | D76: =D58 -> 2016 | E76: =E58 -> 2017 | F76: =F58 -> 2018 | G76: =G58 -> 2019 | H76: =H58 -> 2020 | I76: =I58 -> 2021 | J76: =J58 -> 2022
B77: Ingresos por segmento
B78: Operaciones en México | H78: 82536 | I78: 90258 | J78: 104740
B79: Operaciones en Estados Unidos | H79: 62899 | I79: 97299 | J79: 153439
B80: Segmento inmobiliario | H80: 852 | I80: 930 | J80: 1147
B81: Total de ingresos | H81: =SUM(H78:H80) -> 146287 | I81: =SUM(I78:I80) -> 188487 | J81: =SUM(J78:J80) -> 259326
H82: =H81/G81-1 -> #DIV/0! | I82: =I81/H81-1 -> 0.28847403 | J82: =J81/I81-1 -> 0.37582963
B84: =B75 -> Ingresos
B85: =B76 -> Periodo | C85: =C76 -> 2015 | D85: =D76 -> 2016 | E85: =E76 -> 2017 | F85: =F76 -> 2018 | G85: =G76 -> 2019 | H85: =H76 -> 2020 | I85: =I76 -> 2021 | J85: =J76 -> 2022
B86: =B77 -> Ingresos por segmento
B87: =B78 -> Operaciones en México | C87: =IFERROR(C78*C$1,0) -> 0 | D87: =IFERROR(D78*D$1,0) -> 0 | E87: =IFERROR(E78*E$1,0) -> 0 | F87: =IFERROR(F78*F$1,0) -> 0 | G87: =IFERROR(G78*G$1,0) -> 0 | H87: =IFERROR(H78*H$1,0) -> 101989.74 | I87: =IFERROR(I78*I$1,0) -> 97316.176 | J87: =IFERROR(J78*J$1,0) -> 104740
B88: =B79 -> Operaciones en Estados Unidos | C88: =IFERROR(C79*C$1,0) -> 0 | D88: =IFERROR(D79*D$1,0) -> 0 | E88: =IFERROR(E79*E$1,0) -> 0 | F88: =IFERROR(F79*F$1,0) -> 0 | G88: =IFERROR(G79*G$1,0) -> 0 | H88: =IFERROR(H79*H$1,0) -> 77724.294 | I88: =IFERROR(I79*I$1,0) -> 104907.78 | J88: =IFERROR(J79*J$1,0) -> 153439
B89: =B80 -> Segmento inmobiliario | C89: =IFERROR(C80*C$1,0) -> 0 | D89: =IFERROR(D80*D$1,0) -> 0 | E89: =IFERROR(E80*E$1,0) -> 0 | F89: =IFERROR(F80*F$1,0) -> 0 | G89: =IFERROR(G80*G$1,0) -> 0 | H89: =IFERROR(H80*H$1,0) -> 1052.8164 | I89: =IFERROR(I80*I$1,0) -> 1002.726 | J89: =IFERROR(J80*J$1,0) -> 1147
B90: =B81 -> Total de ingresos | C90: =SUM(C87:C89) -> 0 | D90: =SUM(D87:D89) -> 0 | E90: =SUM(E87:E89) -> 0 | F90: =SUM(F87:F89) -> 0 | G90: =SUM(G87:G89) -> 0 | H90: =SUM(H87:H89) -> 180766.85 | I90: =SUM(I87:I89) -> 203226.68 | J90: =SUM(J87:J89) -> 259326
H93: =H87/G87-1 -> #DIV/0! | I93: =I87/H87-1 -> -0.045823823 | J93: =J87/I87-1 -> 0.076285616
H94: =H88/G88-1 -> #DIV/0! | I94: =I88/H88-1 -> 0.34974248 | J94: =J88/I88-1 -> 0.46260837
H95: =H89/G89-1 -> #DIV/0! | I95: =I89/H89-1 -> -0.047577526 | J95: =J89/I89-1 -> 0.14388178
H96: =H90/G90-1 -> #DIV/0! | I96: =I90/H90-1 -> 0.12424755 | J96: =J90/I90-1 -> 0.27604307

Sheet Flujo de efectivo
B1: Factor INPC | C1: =I1+42.04% -> 1.4986 | D1: =I1+37.42% -> 1.4524 | E1: =I1+28.7% -> 1.3652 | F1: =I1+22.77% -> 1.3059 | G1: =I1+19.39% -> 1.2721 | H1: =I1+15.75% -> 1.2357 | I1: =J1+7.82% -> 1.0782 | J1: 1
B5: Flujo de efectivo | C5: 31 de diciembre | L5: Miles de pesos | T5: Análisis vertical
A6: =10^3 -> 1000 | B6: Millones de pesos | C6: 2015 | D6: 2016 | E6: 2017 | F6: 2018 | G6: 2019 | H6: 2020 | I6: 2021 | J6: 2022 | L6: 2015 | M6: 2016 | N6: 2017 | O6: 2018 | P6: 2019 | Q6: 2020 | R6: 2021 | S6: 2022 | T6: =C6 -> 2015 | U6: =D6 -> 2016 | V6: =E6 -> 2017 | W6: =F6 -> 2018 | X6: =G6 -> 2019 | Y6: =H6 -> 2020 | Z6: =I6 -> 2021 | AA6: =J6 -> 2022 | AB6: Promedio
B7: Flujos de efectivo de actividades de operación:
B8: Utilidad antes de impuestos a la utilidad | C8: =IFERROR(L8/$A$6*C$1,0) -> 3955.0931 | D8: =IFERROR(M8/$A$6*D$1,0) -> 4462.9202 | E8: =IFERROR(N8/$A$6*E$1,0) -> 4419.8978 | F8: =IFERROR(O8/$A$6*F$1,0) -> 3179.527 | G8: =IFERROR(P8/$A$6*G$1,0) -> 3135.8792 | H8: =IFERROR(Q8/$A$6*H$1,0) -> 4630.8475 | I8: =IFERROR(R8/$A$6*I$1,0) -> 5336.5779 | J8: =IFERROR(S8/$A$6*J$1,0) -> 8722.151 | L8: 2639192 | M8: 3072790 | N8: 3237546 | O8: 2434740 | P8: 2465120 | Q8: 3747550 | R8: 4949525 | S8: 8722151 | T8: =C8/C$58 -> 2.0780843 | U8: =D8/D$58 -> -2.8933747 | V8: =E8/E$58 -> 5.6997042 | W8: =F8/F$58 -> -25.037689 | X8: =G8/G$58 -> -6.6694624 | Y8: =H8/H$58 -> 0.83135508 | Z8: =I8/I$58 -> 1.2345366 | AA8: =J8/J$58 -> 3.4291345
B9: Ajustes por: | T9: =C9/C$58 -> 0 | U9: =D9/D$58 -> 0 | V9: =E9/E$58 -> 0 | W9: =F9/F$58 -> 0 | X9: =G9/G$58 -> 0 | Y9: =H9/H$58 -> 0 | Z9: =I9/I$58 -> 0 | AA9: =J9/J$58 -> 0
B10: Depreciación y amortización | C10: =IFERROR(L10/$A$6*C$1,0) -> 1982.3915 | D10: =IFERROR(M10/$A$6*D$1,0) -> 2218.6165 | E10: =IFERROR(N10/$A$6*E$1,0) -> 2234.3218 | F10: =IFERROR(O10/$A$6*F$1,0) -> 3986.5314 | G10: =IFERROR(P10/$A$6*G$1,0) -> 4516.0326 | H10: =IFERROR(Q10/$A$6*H$1,0) -> 4694.2439 | I10: =IFERROR(R10/$A$6*I$1,0) -> 5822.5366 | J10: =IFERROR(S10/$A$6*J$1,0) -> 7680.74 | L10: 1322829 | M10: 1527552 | N10: 1636626 | O10: 3052708 | P10: 3550061 | Q10: 3798854 | R10: 5400238 | S10: 7680740 | T10: =C10/C$58 -> 1.0415878 | U10: =D10/D$58 -> -1.4383607 | V10: =E10/E$58 -> 2.8812823 | W10: =F10/F$58 -> -31.392573 | X10: =G10/G$58 -> -9.6048056 | Y10: =H10/H$58 -> 0.84273634 | Z10: =I10/I$58 -> 1.3469558 | AA10: =J10/J$58 -> 3.0197013 | AB10: =AVERAGE(T10:AA10) -> -4.1629345
B11: Otros movimientos - principalmente fluctuación cambiaria | C11: =IFERROR(L11/$A$6*C$1,0) -> 0 | D11: =IFERROR(M11/$A$6*D$1,0) -> 0 | E11: =IFERROR(N11/$A$6*E$1,0) -> 0 | F11: =IFERROR(O11/$A$6*F$1,0) -> -96.777637 | G11: =IFERROR(P11/$A$6*G$1,0) -> -7.4964853 | H11: =IFERROR(Q11/$A$6*H$1,0) -> 30.392041 | I11: =IFERROR(R11/$A$6*I$1,0) -> 48.009011 | J11: =IFERROR(S11/$A$6*J$1,0) -> -230.894 | O11: -74108 | P11: -5893 | Q11: 24595 | R11: 44527 | S11: -230894 | T11: =C11/C$58 -> 0 | U11: =D11/D$58 -> 0 | V11: =E11/E$58 -> 0 | W11: =F11/F$58 -> 0.76209084 | X11: =G11/G$58 -> 0.015943703 | Y11: =H11/H$58 -> 0.0054561455 | Z11: =I11/I$58 -> 0.011106159 | AA11: =J11/J$58 -> -0.090776527
B12: Perdida en venta de inmuebles y equipo | C12: =IFERROR(L12/$A$6*C$1,0) -> 0 | D12: =IFERROR(M12/$A$6*D$1,0) -> 0 | E12: =IFERROR(N12/$A$6*E$1,0) -> 0 | F12: =IFERROR(O12/$A$6*F$1,0) -> 0 | G12: =IFERROR(P12/$A$6*G$1,0) -> 0 | H12: =IFERROR(Q12/$A$6*H$1,0) -> 25.529562 | I12: =IFERROR(R12/$A$6*I$1,0) -> 171.90282 | J12: =IFERROR(S12/$A$6*J$1,0) -> 48.47 | Q12: 20660 | R12: 159435 | S12: 48470 | T12: =C12/C$58 -> 0 | U12: =D12/D$58 -> 0 | V12: =E12/E$58 -> 0 | W12: =F12/F$58 -> 0 | X12: =G12/G$58 -> 0 | Y12: =H12/H$58 -> 0.0045832066 | Z12: =I12/I$58 -> 0.039767117 | AA12: =J12/J$58 -> 0.019056096
B13: Otros movimientos de capital | C13: =IFERROR(L13/$A$6*C$1,0) -> 0 | D13: =IFERROR(M13/$A$6*D$1,0) -> 0 | E13: =IFERROR(N13/$A$6*E$1,0) -> 0 | F13: =IFERROR(O13/$A$6*F$1,0) -> 0 | G13: =IFERROR(P13/$A$6*G$1,0) -> 0 | H13: =IFERROR(Q13/$A$6*H$1,0) -> 0 | I13: =IFERROR(R13/$A$6*I$1,0) -> 110.43895 | J13: =IFERROR(S13/$A$6*J$1,0) -> 4.592 | Q13: 0 | R13: 102429 | S13: 4592 | T13: =C13/C$58 -> 0 | U13: =D13/D$58 -> 0 | V13: =E13/E$58 -> 0 | W13: =F13/F$58 -> 0 | X13: =G13/G$58 -> 0 | Y13: =H13/H$58 -> 0 | Z13: =I13/I$58 -> 0.02554838 | AA13: =J13/J$58 -> 0.0018053558
B14: Disposición de participación en otras sociedades | C14: =IFERROR(L14/$A$6*C$1,0) -> 0 | D14: =IFERROR(M14/$A$6*D$1,0) -> 0 | E14: =IFERROR(N14/$A$6*E$1,0) -> 0 | F14: =IFERROR(O14/$A$6*F$1,0) -> 0 | G14: =IFERROR(P14/$A$6*G$1,0) -> 0 | H14: =IFERROR(Q14/$A$6*H$1,0) -> 0 | I14: =IFERROR(R14/$A$6*I$1,0) -> 145.557 | J14: =IFERROR(S14/$A$6*J$1,0) -> 0 | R14: 135000 | S14: 0 | T14: =C14/C$58 -> 0 | U14: =D14/D$58 -> 0 | V14: =E14/E$58 -> 0 | W14: =F14/F$58 -> 0 | X14: =G14/G$58 -> 0 | Y14: =H14/H$58 -> 0 | Z14: =I14/I$58 -> 0.03367241 | AA14: =J14/J$58 -> 0
B15: Minusvalía (plusvalía) neta sobre revaluación de propiedades de inversión | C15: =IFERROR(L15/$A$6*C$1,0) -> -39.095477 | D15: =IFERROR(M15/$A$6*D$1,0) -> 76.807269 | E15: =IFERROR(N15/$A$6*E$1,0) -> -40.58057 | F15: =IFERROR(O15/$A$6*F$1,0) -> -395.96847 | G15: =IFERROR(P15/$A$6*G$1,0) -> -0.4439629 | H15: =IFERROR(Q15/$A$6*H$1,0) -> 0 | I15: =IFERROR(R15/$A$6*I$1,0) -> 0 | J15: =IFERROR(S15/$A$6*J$1,0) -> 32.815 | L15: -26088 | M15: 52883 | N15: -29725 | O15: -303215 | P15: -349 | Q15: 0 | R15: 0 | S15: 32815 | T15: =C15/C$58 -> -0.020541538 | U15: =D15/D$58 -> -0.049795247 | V15: =E15/E$58 -> -0.052330904 | W15: =F15/F$58 -> 3.1181165 | X15: =G15/G$58 -> 0.00094423086 | Y15: =H15/H$58 -> 0 | Z15: =I15/I$58 -> 0 | AA15: =J15/J$58 -> 0.012901296
B16: (Ganancia) pérdida en venta de inmuebles y equipo | C16: =IFERROR(L16/$A$6*C$1,0) -> 181.33959 | D16: =IFERROR(M16/$A$6*D$1,0) -> -22.002408 | E16: =IFERROR(N16/$A$6*E$1,0) -> 30.946354 | F16: =IFERROR(O16/$A$6*F$1,0) -> 6.1808247 | G16: =IFERROR(P16/$A$6*G$1,0) -> -83.883546 | H16: =IFERROR(Q16/$A$6*H$1,0) -> 0 | I16: =IFERROR(R16/$A$6*I$1,0) -> 0 | J16: =IFERROR(S16/$A$6*J$1,0) -> 0 | L16: 121006 | M16: -15149 | N16: 22668 | O16: 4733 | P16: -65941 | T16: =C16/C$58 -> 0.095279415 | U16: =D16/D$58 -> 0.014264474 | V16: =E16/E$58 -> 0.039907046 | W16: =F16/F$58 -> -0.048671884 | X16: =G16/G$58 -> 0.17840552 | Y16: =H16/H$58 -> 0 | Z16: =I16/I$58 -> 0 | AA16: =J16/J$58 -> 0
B17: Ingreso por intereses | C17: =IFERROR(L17/$A$6*C$1,0) -> -51.725678 | D17: =IFERROR(M17/$A$6*D$1,0) -> -98.542435 | E17: =IFERROR(N17/$A$6*E$1,0) -> -98.97427 | F17: =IFERROR(O17/$A$6*F$1,0) -> -115.38802 | G17: =IFERROR(P17/$A$6*G$1,0) -> -80.297496 | H17: =IFERROR(Q17/$A$6*H$1,0) -> -168.14046 | I17: =IFERROR(R17/$A$6*I$1,0) -> -145.29392 | J17: =IFERROR(S17/$A$6*J$1,0) -> -269.217 | L17: -34516 | M17: -67848 | N17: -72498 | O17: -88359 | P17: -63122 | Q17: -136069 | R17: -134756 | S17: -269217 | T17: =C17/C$58 -> -0.027177696 | U17: =D17/D$58 -> 0.063886464 | V17: =E17/E$58 -> -0.12763283 | W17: =F17/F$58 -> 0.90864124 | X17: =G17/G$58 -> 0.17077863 | Y17: =H17/H$58 -> -0.030185496 | Z17: =I17/I$58 -> -0.033611551 | AA17: =J17/J$58 -> -0.10584331
B18: Valuación de instrumentos financieros derivados | C18: =IFERROR(L18/$A$6*C$1,0) -> -46.98111 | D18: =IFERROR(M18/$A$6*D$1,0) -> 5.1836156 | E18: =IFERROR(N18/$A$6*E$1,0) -> 41.424264 | F18: =IFERROR(O18/$A$6*F$1,0) -> -7.6564917 | G18: =IFERROR(P18/$A$6*G$1,0) -> 39.010219 | H18: =IFERROR(Q18/$A$6*H$1,0) -> 107.79135 | I18: =IFERROR(R18/$A$6*I$1,0) -> -97.054173 | J18: =IFERROR(S18/$A$6*J$1,0) -> -102.743 | L18: -31350 | M18: 3569 | N18: 30343 | O18: -5863 | P18: 30666 | Q18: 87231 | R18: -90015 | S18: -102743 | T18: =C18/C$58 -> -0.024684806 | U18: =D18/D$58 -> -0.0033606118 | V18: =E18/E$58 -> 0.053418894 | W18: =F18/F$58 -> 0.060292258 | X18: =G18/G$58 -> -0.082967861 | Y18: =H18/H$58 -> 0.019351292 | Z18: =I18/I$58 -> -0.022452015 | AA18: =J18/J$58 -> -0.040393656
B19: Gastos por intereses | C19: =IFERROR(L19/$A$6*C$1,0) -> 813.01747 | D19: =IFERROR(M19/$A$6*D$1,0) -> 940.08478 | E19: =IFERROR(N19/$A$6*E$1,0) -> 917.80348 | F19: =IFERROR(O19/$A$6*F$1,0) -> 2635.237 | G19: =IFERROR(P19/$A$6*G$1,0) -> 2982.3151 | H19: =IFERROR(Q19/$A$6*H$1,0) -> 2849.7664 | I19: =IFERROR(R19/$A$6*I$1,0) -> 2865.3704 | J19: =IFERROR(S19/$A$6*J$1,0) -> 3382.48 | L19: 542518 | M19: 647263 | N19: 672285 | O19: 2017947 | P19: 2344403 | Q19: 2306196 | R19: 2657550 | S19: 3382480 | T19: =C19/C$58 -> 0.42717549 | U19: =D19/D$58 -> -0.60947035 | V19: =E19/E$58 -> 1.1835587 | W19: =F19/F$58 -> -20.751591 | X19: =G19/G$58 -> -6.3428586 | Y19: =H19/H$58 -> 0.51160565 | Z19: =I19/I$58 -> 0.6628601 | AA19: =J19/J$58 -> 1.3298301 | AB19: =AVERAGE(T19:AA19) -> -2.9486113
C20: =SUM(C8:C19) -> 6794.0395 | D20: =SUM(D8:D19) -> 7583.0675 | E20: =SUM(E8:E19) -> 7504.8389 | F20: =SUM(F8:F19) -> 9191.6855 | G20: =SUM(G8:G19) -> 10501.116 | H20: =SUM(H8:H19) -> 12170.43 | I20: =SUM(I8:I19) -> 14258.045 | J20: =SUM(J8:J19) -> 19268.394 | L20: =SUM(L8:L19) -> 4533591 | M20: =SUM(M8:M19) -> 5221060 | N20: =SUM(N8:N19) -> 5497245 | O20: =SUM(O8:O19) -> 7038583 | P20: =SUM(P8:P19) -> 8254945 | Q20: =SUM(Q7:Q19) -> 9849017 | R20: =SUM(R7:R19) -> 13223933 | S20: =SUM(S7:S19) -> 19268394 | T20: =C20/C$58 -> 3.569723 | U20: =D20/D$58 -> -4.9162107 | V20: =E20/E$58 -> 9.6779075 | W20: =F20/F$58 -> -72.381385 | X20: =G20/G$58 -> -22.334022 | Y20: =H20/H$58 -> 2.1849022 | Z20: =I20/I$58 -> 3.298383 | AA20: =J20/J$58 -> 7.5754151
B21: Cambios en el capital del trabajo
B22: Cuentas y documentos por cobrar - Neto | C22: =IFERROR(L22/$A$6*C$1,0) -> -159.50049 | D22: =IFERROR(M22/$A$6*D$1,0) -> -175.44266 | E22: =IFERROR(N22/$A$6*E$1,0) -> -100.3149 | F22: =IFERROR(O22/$A$6*F$1,0) -> -142.68786 | G22: =IFERROR(P22/$A$6*G$1,0) -> -333.37289 | H22: =IFERROR(Q22/$A$6*H$1,0) -> 92.452603 | I22: =IFERROR(R22/$A$6*I$1,0) -> 744.03024 | J22: =IFERROR(S22/$A$6*J$1,0) -> 159.677 | L22: -106433 | M22: -120795 | N22: -73480 | O22: -109264 | P22: -262065 | Q22: 74818 | R22: 690067 | S22: 159677 | T22: =C22/C$58 -> -0.08380472 | U22: =D22/D$58 -> 0.11374197 | V22: =E22/E$58 -> -0.12936164 | W22: =F22/F$58 -> 1.1236182 | X22: =G22/G$58 -> 0.70902539 | Y22: =H22/H$58 -> 0.016597597 | Z22: =I22/I$58 -> 0.17212014 | AA22: =J22/J$58 -> 0.062777394
B23: Inventarios - Neto | C23: =IFERROR(L23/$A$6*C$1,0) -> -536.03274 | D23: =IFERROR(M23/$A$6*D$1,0) -> -1874.2205 | E23: =IFERROR(N23/$A$6*E$1,0) -> -1043.3923 | F23: =IFERROR(O23/$A$6*F$1,0) -> -3179.6288 | G23: =IFERROR(P23/$A$6*G$1,0) -> -889.12666 | H23: =IFERROR(Q23/$A$6*H$1,0) -> 2001.3101 | I23: =IFERROR(R23/$A$6*I$1,0) -> -635.47275 | J23: =IFERROR(S23/$A$6*J$1,0) -> -3100.045 | L23: -357689 | M23: -1290430 | N23: -764278 | O23: -2434818 | P23: -698944 | Q23: 1619576 | R23: -589383 | S23: -3100045 | T23: =C23/C$58 -> -0.28164222 | U23: =D23/D$58 -> 1.2150839 | V23: =E23/E$58 -> -1.3455125 | W23: =F23/F$58 -> 25.038491 | X23: =G23/G$58 -> 1.8910157 | Y23: =H23/H$58 -> 0.35928613 | Z23: =I23/I$58 -> -0.14700701 | AA23: =J23/J$58 -> -1.2187901
B24: Participación en la (Utilidad) Perdida de asociadas y negocios conjuntos | C24: =IFERROR(L24/$A$6*C$1,0) -> 0 | D24: =IFERROR(M24/$A$6*D$1,0) -> 0 | E24: =IFERROR(N24/$A$6*E$1,0) -> 0 | F24: =IFERROR(O24/$A$6*F$1,0) -> 0 | G24: =IFERROR(P24/$A$6*G$1,0) -> 0 | H24: =IFERROR(Q24/$A$6*H$1,0) -> 0 | I24: =IFERROR(R24/$A$6*I$1,0) -> -58.730632 | J24: =IFERROR(S24/$A$6*J$1,0) -> -88.766 | R24: -54471 | S24: -88766 | T24: =C24/C$58 -> 0 | U24: =D24/D$58 -> 0 | V24: =E24/E$58 -> 0 | W24: =F24/F$58 -> 0 | X24: =G24/G$58 -> 0 | Y24: =H24/H$58 -> 0 | Z24: =I24/I$58 -> -0.013586443 | AA24: =J24/J$58 -> -0.034898565
B25: Otros activos - Neto | C25: =IFERROR(L25/$A$6*C$1,0) -> 126.80554 | D25: =IFERROR(M25/$A$6*D$1,0) -> -205.42019 | E25: =IFERROR(N25/$A$6*E$1,0) -> 329.97021 | F25: =IFERROR(O25/$A$6*F$1,0) -> -1196.6837 | G25: =IFERROR(P25/$A$6*G$1,0) -> -151.39262 | H25: =IFERROR(Q25/$A$6*H$1,0) -> 48.07738 | I25: =IFERROR(R25/$A$6*I$1,0) -> -306.45894 | J25: =IFERROR(S25/$A$6*J$1,0) -> 803.352 | L25: 84616 | M25: -141435 | N25: 241701 | O25: -916367 | P25: -119010 | Q25: 38907 | R25: -284232 | S25: 803352 | T25: =C25/C$58 -> 0.066626142 | U25: =D25/D$58 -> 0.13317684 | V25: =E25/E$58 -> 0.42551495 | W25: =F25/F$58 -> 9.4234752 | X25: =G25/G$58 -> 0.32198543 | Y25: =H25/H$58 -> 0.0086311142 | Z25: =I25/I$58 -> -0.070894641 | AA25: =J25/J$58 -> 0.31583976
B26: Aumento (disminución) en: | C26: =IFERROR(L26/$A$6*C$1,0) -> 0 | D26: =IFERROR(M26/$A$6*D$1,0) -> 0 | E26: =IFERROR(N26/$A$6*E$1,0) -> 0 | F26: =IFERROR(O26/$A$6*F$1,0) -> 0 | G26: =IFERROR(P26/$A$6*G$1,0) -> 0 | H26: =IFERROR(Q26/$A$6*H$1,0) -> 0 | I26: =IFERROR(R26/$A$6*I$1,0) -> 0 | J26: =IFERROR(S26/$A$6*J$1,0) -> 0 | T26: =C26/C$58 -> 0 | U26: =D26/D$58 -> 0 | V26: =E26/E$58 -> 0 | W26: =F26/F$58 -> 0 | X26: =G26/G$58 -> 0 | Y26: =H26/H$58 -> 0 | Z26: =I26/I$58 -> 0 | AA26: =J26/J$58 -> 0
B27: Cuentas y documentos por pagar a proveedores | C27: =IFERROR(L27/$A$6*C$1,0) -> 1572.5844 | D27: =IFERROR(M27/$A$6*D$1,0) -> 1226.9759 | E27: =IFERROR(N27/$A$6*E$1,0) -> 890.8517 | F27: =IFERROR(O27/$A$6*F$1,0) -> 4864.4919 | G27: =IFERROR(P27/$A$6*G$1,0) -> -320.64934 | H27: =IFERROR(Q27/$A$6*H$1,0) -> 1141.3605 | I27: =IFERROR(R27/$A$6*I$1,0) -> 4781.7458 | J27: =IFERROR(S27/$A$6*J$1,0) -> 2944.299 | L27: 1049369 | M27: 844792 | N27: 652543 | O27: 3725011 | P27: -252063 | Q27: 923655 | R27: 4434934 | S27: 2944299 | T27: =C27/C$58 -> 0.826267 | U27: =D27/D$58 -> -0.79546595 | V27: =E27/E$58 -> 1.1488029 | W27: =F27/F$58 -> -38.306212 | X27: =G27/G$58 -> 0.68196465 | Y27: =H27/H$58 -> 0.20490328 | Z27: =I27/I$58 -> 1.1061846 | AA27: =J27/J$58 -> 1.1575582 | AB27: =AVERAGE(T27:AA27) -> -4.2469997
B28: Otras cuentas por pagar e impuestos | C28: =IFERROR(L28/$A$6*C$1,0) -> -1295.3823 | D28: =IFERROR(M28/$A$6*D$1,0) -> -1595.8477 | E28: =IFERROR(N28/$A$6*E$1,0) -> -615.95503 | F28: =IFERROR(O28/$A$6*F$1,0) -> -767.55317 | G28: =IFERROR(P28/$A$6*G$1,0) -> -1939.8584 | H28: =IFERROR(Q28/$A$6*H$1,0) -> -362.21951 | I28: =IFERROR(R28/$A$6*I$1,0) -> -1604.0327 | J28: =IFERROR(S28/$A$6*J$1,0) -> -1446.429 | L28: -864395 | M28: -1098766 | N28: -451183 | O28: -587758 | P28: -1524926 | Q28: -293129 | R28: -1487695 | S28: -1446429 | T28: =C28/C$58 -> -0.68061955 | U28: =D28/D$58 -> 1.0346108 | V28: =E28/E$58 -> -0.7943083 | W28: =F28/F$58 -> 6.0442191 | X28: =G28/G$58 -> 4.1257369 | Y28: =H28/H$58 -> -0.065027627 | Z28: =I28/I$58 -> -0.37106871 | AA28: =J28/J$58 -> -0.56866701
B29: Variaciones por obligaciones laborales | C29: =IFERROR(L29/$A$6*C$1,0) -> 121.13184 | D29: =IFERROR(M29/$A$6*D$1,0) -> 35.666587 | E29: =IFERROR(N29/$A$6*E$1,0) -> 1.7501864 | F29: =IFERROR(O29/$A$6*F$1,0) -> 87.871399 | G29: =IFERROR(P29/$A$6*G$1,0) -> 198.72365 | H29: =IFERROR(Q29/$A$6*H$1,0) -> 129.38644 | I29: =IFERROR(R29/$A$6*I$1,0) -> 183.00396 | J29: =IFERROR(S29/$A$6*J$1,0) -> -0.344 | L29: 80830 | M29: 24557 | N29: 1282 | O29: 67288 | P29: 156217 | Q29: 104707 | R29: 169731 | S29: -344 | T29: =C29/C$58 -> 0.063645068 | U29: =D29/D$58 -> -0.023123156 | V29: =E29/E$58 -> 0.0022569628 | W29: =F29/F$58 -> -0.69195726 | X29: =G29/G$58 -> -0.42265018 | Y29: =H29/H$58 -> 0.023228161 | Z29: =I29/I$58 -> 0.042335199 | AA29: =J29/J$58 -> -0.00013524442
B30: Flujos netos de efectivo de actividades de operación | C30: =SUM(C20:C29) -> 6623.6457 | D30: =SUM(D20:D29) -> 4994.7789 | E30: =SUM(E20:E29) -> 6967.7487 | F30: =SUM(F20:F29) -> 8857.4953 | G30: =SUM(G20:G29) -> 7065.4393 | H30: =SUM(H20:H29) -> 15220.798 | I30: =SUM(I20:I29) -> 17362.13 | J30: =SUM(J20:J29) -> 18540.138 | L30: =SUM(L20:L29) -> 4419889 | M30: =SUM(M20:M29) -> 3438983 | N30: =SUM(N20:N29) -> 5103830 | O30: =SUM(O20:O29) -> 6782675 | P30: =SUM(P20:P29) -> 5554154 | Q30: =SUM(Q20:Q29) -> 12317551 | R30: =SUM(R20:R29) -> 16102884 | S30: =SUM(S20:S29) -> 18540138 | T30: =C30/C$58 -> 3.4801947 | U30: =D30/D$58 -> -3.2381863 | V30: =E30/E$58 -> 8.9852998 | W30: =F30/F$58 -> -69.749751 | X30: =G30/G$58 -> -15.026944 | Y30: =H30/H$58 -> 2.7325209 | Z30: =I30/I$58 -> 4.0164661 | AA30: =J30/J$58 -> 7.2890995
B32: Actividades de inversión:
B33: Adquisición de negocio | C33: =IFERROR(L33/$A$6*C$1,0) -> 0 | D33: =IFERROR(M33/$A$6*D$1,0) -> 0 | E33: =IFERROR(N33/$A$6*E$1,0) -> 0 | F33: =IFERROR(O33/$A$6*F$1,0) -> -5805.6814 | G33: =IFERROR(P33/$A$6*G$1,0) -> 0 | H33: =IFERROR(Q33/$A$6*H$1,0) -> -27.80325 | I33: =IFERROR(R33/$A$6*I$1,0) -> -12379.374 | J33: =IFERROR(S33/$A$6*J$1,0) -> -1106.722 | O33: -4445732 | P33: 0 | Q33: -22500 | R33: -11481519 | S33: -1106722 | T33: =C33/C$58 -> 0 | U33: =D33/D$58 -> 0 | V33: =E33/E$58 -> 0 | W33: =F33/F$58 -> 45.717759 | X33: =G33/G$58 -> 0 | Y33: =H33/H$58 -> -0.0049913915 | Z33: =I33/I$58 -> -2.8637809 | AA33: =J33/J$58 -> -0.4351104
B34: Adquisición de inmuebles y equipo | C34: =IFERROR(L34/$A$6*C$1,0) -> -4287.0885 | D34: =IFERROR(M34/$A$6*D$1,0) -> -4764.6926 | E34: =IFERROR(N34/$A$6*E$1,0) -> -4088.4982 | F34: =IFERROR(O34/$A$6*F$1,0) -> -5578.1375 | G34: =IFERROR(P34/$A$6*G$1,0) -> -4821.0084 | H34: =IFERROR(Q34/$A$6*H$1,0) -> -2901.9512 | I34: =IFERROR(R34/$A$6*I$1,0) -> -4460.0131 | J34: =IFERROR(S34/$A$6*J$1,0) -> -5401.455 | L34: -2860729 | M34: -3280565 | N34: -2994798 | O34: -4271489 | P34: -3789803 | Q34: -2348427 | R34: -4136536 | S34: -5401455 | T34: =C34/C$58 -> -2.2525212 | U34: =D34/D$58 -> 3.0890181 | V34: =E34/E$58 -> -5.272346 | W34: =F34/F$58 -> 43.925928 | X34: =G34/G$58 -> 10.253435 | Y34: =H34/H$58 -> -0.52097416 | Z34: =I34/I$58 -> -1.0317566 | AA34: =J34/J$58 -> -2.1235949 | AB34: =AVERAGE(T34:AA34) -> 5.7583985
B35: Ingreso por venta de inmuebles y equipo | C35: =IFERROR(L35/$A$6*C$1,0) -> 331.65966 | D35: =IFERROR(M35/$A$6*D$1,0) -> 2.4371272 | E35: =IFERROR(N35/$A$6*E$1,0) -> 7.1850476 | F35: =IFERROR(O35/$A$6*F$1,0) -> 21.62701 | G35: =IFERROR(P35/$A$6*G$1,0) -> 1322.2983 | H35: =IFERROR(Q35/$A$6*H$1,0) -> 13.298603 | I35: =IFERROR(R35/$A$6*I$1,0) -> 77.311253 | J35: =IFERROR(S35/$A$6*J$1,0) -> 38.604 | L35: 221313 | M35: 1678 | N35: 5263 | O35: 16561 | P35: 1039461 | Q35: 10762 | R35: 71704 | S35: 38604 | T35: =C35/C$58 -> 0.17426056 | U35: =D35/D$58 -> -0.0015800243 | V35: =E35/E$58 -> 0.0092655188 | W35: =F35/F$58 -> -0.17030532 | X35: =G35/G$58 -> -2.8122956 | Y35: =H35/H$58 -> 0.002387438 | Z35: =I35/I$58 -> 0.017884789 | AA35: =J35/J$58 -> 0.015177255
B36: Adquisición de otros activos | C36: =IFERROR(L36/$A$6*C$1,0) -> -194.63068 | D36: =IFERROR(M36/$A$6*D$1,0) -> -213.43889 | E36: =IFERROR(N36/$A$6*E$1,0) -> -250.2316 | F36: =IFERROR(O36/$A$6*F$1,0) -> -299.90646 | G36: =IFERROR(P36/$A$6*G$1,0) -> -202.59592 | H36: =IFERROR(Q36/$A$6*H$1,0) -> -221.21007 | I36: =IFERROR(R36/$A$6*I$1,0) -> -226.47483 | J36: =IFERROR(S36/$A$6*J$1,0) -> -280.488 | L36: -129875 | M36: -146956 | N36: -183293 | O36: -229655 | P36: -159261 | Q36: -179016 | R36: -210049 | S36: -280488 | T36: =C36/C$58 -> -0.10226281 | U36: =D36/D$58 -> 0.13837548 | V36: =E36/E$58 -> -0.32268758 | W36: =F36/F$58 -> 2.361661 | X36: =G36/G$58 -> 0.43088582 | Y36: =H36/H$58 -> -0.039712842 | Z36: =I36/I$58 -> -0.052391527 | AA36: =J36/J$58 -> -0.11027453
B37: Dividendos recibidos | C37: =IFERROR(L37/$A$6*C$1,0) -> 0 | D37: =IFERROR(M37/$A$6*D$1,0) -> 0 | E37: =IFERROR(N37/$A$6*E$1,0) -> 9.3529852 | F37: =IFERROR(O37/$A$6*F$1,0) -> 2.4067737 | G37: =IFERROR(P37/$A$6*G$1,0) -> 2.1078697 | H37: =IFERROR(Q37/$A$6*H$1,0) -> 2.5677846 | I37: =IFERROR(R37/$A$6*I$1,0) -> 0 | J37: =IFERROR(S37/$A$6*J$1,0) -> 0 | N37: 6851 | O37: 1843 | P37: 1657 | Q37: 2078 | T37: =C37/C$58 -> 0 | U37: =D37/D$58 -> 0 | V37: =E37/E$58 -> 0.012061195 | W37: =F37/F$58 -> -0.018952521 | X37: =G37/G$58 -> -0.0044830674 | Y37: =H37/H$58 -> 0.00046098274 | Z37: =I37/I$58 -> 0 | AA37: =J37/J$58 -> 0
B38: Adquisición de participación en asociadas | C38: =IFERROR(L38/$A$6*C$1,0) -> 0 | D38: =IFERROR(M38/$A$6*D$1,0) -> 0 | E38: =IFERROR(N38/$A$6*E$1,0) -> 0 | F38: =IFERROR(O38/$A$6*F$1,0) -> 0 | G38: =IFERROR(P38/$A$6*G$1,0) -> 0 | H38: =IFERROR(Q38/$A$6*H$1,0) -> -166.8195 | I38: =IFERROR(R38/$A$6*I$1,0) -> 0 | J38: =IFERROR(S38/$A$6*J$1,0) -> 0 | Q38: -135000 | T38: =C38/C$58 -> 0 | U38: =D38/D$58 -> 0 | V38: =E38/E$58 -> 0 | W38: =F38/F$58 -> 0 | X38: =G38/G$58 -> 0 | Y38: =H38/H$58 -> -0.029948349 | Z38: =I38/I$58 -> 0 | AA38: =J38/J$58 -> 0
B39: Intereses cobrados | C39: =IFERROR(L39/$A$6*C$1,0) -> 51.725678 | D39: =IFERROR(M39/$A$6*D$1,0) -> 98.542435 | E39: =IFERROR(N39/$A$6*E$1,0) -> 98.97427 | F39: =IFERROR(O39/$A$6*F$1,0) -> 115.38802 | G39: =IFERROR(P39/$A$6*G$1,0) -> 80.297496 | H39: =IFERROR(Q39/$A$6*H$1,0) -> 168.14046 | I39: =IFERROR(R39/$A$6*I$1,0) -> 145.29392 | J39: =IFERROR(S39/$A$6*J$1,0) -> 269.217 | L39: 34516 | M39: 67848 | N39: 72498 | O39: 88359 | P39: 63122 | Q39: 136069 | R39: 134756 | S39: 269217 | T39: =C39/C$58 -> 0.027177696 | U39: =D39/D$58 -> -0.063886464 | V39: =E39/E$58 -> 0.12763283 | W39: =F39/F$58 -> -0.90864124 | X39: =G39/G$58 -> -0.17077863 | Y39: =H39/H$58 -> 0.030185496 | Z39: =I39/I$58 -> 0.033611551 | AA39: =J39/J$58 -> 0.10584331
B40: Flujos netos de efectivo de actividades de inversión | C40: =SUM(C33:C39) -> -4098.3338 | D40: =SUM(D33:D39) -> -4877.1519 | E40: =SUM(E33:E39) -> -4223.2175 | F40: =SUM(F33:F39) -> -11544.304 | G40: =SUM(G33:G39) -> -3618.9006 | H40: =SUM(H33:H39) -> -3133.7772 | I40: =SUM(I33:I39) -> -16843.257 | J40: =SUM(J33:J39) -> -6480.844 | L40: =SUM(L33:L39) -> -2734775 | M40: =SUM(M33:M39) -> -3357995 | N40: =SUM(N33:N39) -> -3093479 | O40: =SUM(O33:O39) -> -8840113 | P40: =SUM(P33:P39) -> -2844824 | Q40: =SUM(Q33:Q39) -> -2536034 | R40: =SUM(R33:R39) -> -15621644 | S40: =SUM(S33:S39) -> -6480844 | T40: =C40/C$58 -> -2.1533458 | U40: =D40/D$58 -> 3.1619271 | V40: =E40/E$58 -> -5.4460741 | W40: =F40/F$58 -> 90.907448 | X40: =G40/G$58 -> 7.6967639 | Y40: =H40/H$58 -> -0.56259283 | Z40: =I40/I$58 -> -3.8964326 | AA40: =J40/J$58 -> -2.5479593
B42: Actividades de financiamiento:
B43: Pago de préstamos | C43: =IFERROR(L43/$A$6*C$1,0) -> -5029.4335 | D43: =IFERROR(M43/$A$6*D$1,0) -> -2500.5317 | E43: =IFERROR(N43/$A$6*E$1,0) -> -2299.8828 | F43: =IFERROR(O43/$A$6*F$1,0) -> -1248.985 | G43: =IFERROR(P43/$A$6*G$1,0) -> -737.83835 | H43: =IFERROR(Q43/$A$6*H$1,0) -> -4317.2677 | I43: =IFERROR(R43/$A$6*I$1,0) -> -8879.3608 | J43: =IFERROR(S43/$A$6*J$1,0) -> -3883.715 | L43: -3356088 | M43: -1721655 | N43: -1684649 | O43: -956417 | P43: -580016 | Q43: -3493783 | R43: -8235356 | S43: -3883715 | T43: =C43/C$58 -> -2.642564 | U43: =D43/D$58 -> 1.6211303 | V43: =E43/E$58 -> -2.9658269 | W43: =F43/F$58 -> 9.83533 | X43: =G43/G$58 -> 1.5692522 | Y43: =H43/H$58 -> -0.7750595 | Z43: =I43/I$58 -> -2.0541058 | AA43: =J43/J$58 -> -1.5268918 | AB43: =AVERAGE(T43:AA43) -> 0.38265806
B44: Adquisición de préstamos | C44: =IFERROR(L44/$A$6*C$1,0) -> 5896.3586 | D44: =IFERROR(M44/$A$6*D$1,0) -> 2819.6734 | E44: =IFERROR(N44/$A$6*E$1,0) -> 2133.8281 | F44: =IFERROR(O44/$A$6*F$1,0) -> 7857.4057 | G44: =IFERROR(P44/$A$6*G$1,0) -> 1535.2402 | H44: =IFERROR(Q44/$A$6*H$1,0) -> 2471.4 | I44: =IFERROR(R44/$A$6*I$1,0) -> 17571.177 | J44: =IFERROR(S44/$A$6*J$1,0) -> 0 | L44: 3934578 | M44: 1941389 | N44: 1563015 | O44: 6016851 | P44: 1206855 | Q44: 2000000 | R44: 16296770 | S44: 0 | T44: =C44/C$58 -> 3.0980636 | U44: =D44/D$58 -> -1.8280344 | V44: =E44/E$58 -> 2.7516901 | W44: =F44/F$58 -> -61.874387 | X44: =G44/G$58 -> -3.2651855 | Y44: =H44/H$58 -> 0.44367925 | Z44: =I44/I$58 -> 4.0648261 | AA44: =J44/J$58 -> 0 | AB44: =AVERAGE(T44:AA44) -> -7.0761685
B45: Intereses pagados | C45: =IFERROR(L45/$A$6*C$1,0) -> -813.01747 | D45: =IFERROR(M45/$A$6*D$1,0) -> -940.08478 | E45: =IFERROR(N45/$A$6*E$1,0) -> -917.80348 | F45: =IFERROR(O45/$A$6*F$1,0) -> -2635.2383 | G45: =IFERROR(P45/$A$6*G$1,0) -> -2982.3151 | H45: =IFERROR(Q45/$A$6*H$1,0) -> -2849.7652 | I45: =IFERROR(R45/$A$6*I$1,0) -> -2865.3704 | J45: =IFERROR(S45/$A$6*J$1,0) -> -3382.48 | L45: -542518 | M45: -647263 | N45: -672285 | O45: -2017948 | P45: -2344403 | Q45: -2306195 | R45: -2657550 | S45: -3382480 | T45: =C45/C$58 -> -0.42717549 | U45: =D45/D$58 -> 0.60947035 | V45: =E45/E$58 -> -1.1835587 | W45: =F45/F$58 -> 20.751602 | X45: =G45/G$58 -> 6.3428586 | Y45: =H45/H$58 -> -0.51160543 | Z45: =I45/I$58 -> -0.6628601 | AA45: =J45/J$58 -> -1.3298301
B46: Pago de dividendos | C46: =IFERROR(L46/$A$6*C$1,0) -> -361.13113 | D46: =IFERROR(M46/$A$6*D$1,0) -> -357.41821 | E46: =IFERROR(N46/$A$6*E$1,0) -> -434.26056 | F46: =IFERROR(O46/$A$6*F$1,0) -> -491.84503 | G46: =IFERROR(P46/$A$6*G$1,0) -> -498.94052 | H46: =IFERROR(Q46/$A$6*H$1,0) -> -528.73379 | I46: =IFERROR(R46/$A$6*I$1,0) -> -493.6625 | J46: =IFERROR(S46/$A$6*J$1,0) -> -503.643 | L46: -240979 | M46: -246088 | N46: -318093 | O46: -376633 | P46: -392218 | Q46: -427882 | R46: -457858 | S46: -503643 | T46: =C46/C$58 -> -0.18974545 | U46: =D46/D$58 -> 0.23171932 | V46: =E46/E$58 -> -0.56000317 | W46: =F46/F$58 -> 3.8731117 | X46: =G46/G$58 -> 1.0611586 | Y46: =H46/H$58 -> -0.094921181 | Z46: =I46/I$58 -> -0.11420135 | AA46: =J46/J$58 -> -0.19800845
B47: Obligaciones por arrendamiento | C47: =IFERROR(L47/$A$6*C$1,0) -> -70.441693 | D47: =IFERROR(M47/$A$6*D$1,0) -> -98.802415 | E47: =IFERROR(N47/$A$6*E$1,0) -> -85.106568 | F47: =IFERROR(O47/$A$6*F$1,0) -> -605.8266 | G47: =IFERROR(P47/$A$6*G$1,0) -> -838.45638 | H47: =IFERROR(Q47/$A$6*H$1,0) -> -697.62061 | I47: =IFERROR(R47/$A$6*I$1,0) -> -1499.5519 | J47: =IFERROR(S47/$A$6*J$1,0) -> -2051.334 | L47: -47005 | M47: -68027 | N47: -62340 | O47: -463915 | P47: -659112 | Q47: -564555 | R47: -1390792 | S47: -2051334 | T47: =C47/C$58 -> -0.037011461 | U47: =D47/D$58 -> 0.064055013 | V47: =E47/E$58 -> -0.10974966 | W47: =F47/F$58 -> 4.7706776 | X47: =G47/G$58 -> 1.783249 | Y47: =H47/H$58 -> -0.12524067 | Z47: =I47/I$58 -> -0.34689866 | AA47: =J47/J$58 -> -0.80648686
B48: Adquisiciones de arrendamiento financiero | C48: =IFERROR(L48/$A$6*C$1,0) -> 0 | D48: =IFERROR(M48/$A$6*D$1,0) -> 0 | E48: =IFERROR(N48/$A$6*E$1,0) -> 129.29946 | F48: =IFERROR(O48/$A$6*F$1,0) -> 0 | G48: =IFERROR(P48/$A$6*G$1,0) -> 0 | H48: =IFERROR(Q48/$A$6*H$1,0) -> 0 | I48: =IFERROR(R48/$A$6*I$1,0) -> 0 | J48: =IFERROR(S48/$A$6*J$1,0) -> 0 | N48: 94711 | T48: =C48/C$58 -> 0 | U48: =D48/D$58 -> 0 | V48: =E48/E$58 -> 0.16673885 | W48: =F48/F$58 -> 0 | X48: =G48/G$58 -> 0 | Y48: =H48/H$58 -> 0 | Z48: =I48/I$58 -> 0 | AA48: =J48/J$58 -> 0
B49: Otros movimientos de capital | C49: =IFERROR(L49/$A$6*C$1,0) -> 0 | D49: =IFERROR(M49/$A$6*D$1,0) -> 0 | E49: =IFERROR(N49/$A$6*E$1,0) -> 0 | F49: =IFERROR(O49/$A$6*F$1,0) -> -133.4238 | G49: =IFERROR(P49/$A$6*G$1,0) -> -84.659527 | H49: =IFERROR(Q49/$A$6*H$1,0) -> -173.39837 | I49: =IFERROR(R49/$A$6*I$1,0) -> 0 | J49: =IFERROR(S49/$A$6*J$1,0) -> 0 | O49: -102170 | P49: -66551 | Q49: -140324 | T49: =C49/C$58 -> 0 | U49: =D49/D$58 -> 0 | V49: =E49/E$58 -> 0 | W49: =F49/F$58 -> 1.0506669 | X49: =G49/G$58 -> 0.1800559 | Y49: =H49/H$58 -> -0.031129423 | Z49: =I49/I$58 -> 0 | AA49: =J49/J$58 -> 0
B50: Compra de acciones de participación no controladora | C50: =IFERROR(L50/$A$6*C$1,0) -> -160.97512 | D50: =IFERROR(M50/$A$6*D$1,0) -> -363.36434 | E50: =IFERROR(N50/$A$6*E$1,0) -> -323.66844 | F50: =IFERROR(O50/$A$6*F$1,0) -> 0 | G50: =IFERROR(P50/$A$6*G$1,0) -> 0 | H50: =IFERROR(Q50/$A$6*H$1,0) -> 0 | I50: =IFERROR(R50/$A$6*I$1,0) -> 0 | J50: =IFERROR(S50/$A$6*J$1,0) -> 0 | L50: -107417 | M50: -250182 | N50: -237085 | T50: =C50/C$58 -> -0.084579516 | U50: =D50/D$58 -> 0.23557427 | V50: =E50/E$58 -> -0.41738847 | W50: =F50/F$58 -> 0 | X50: =G50/G$58 -> 0 | Y50: =H50/H$58 -> 0 | Z50: =I50/I$58 -> 0 | AA50: =J50/J$58 -> 0
B51: Pago de obligaciones relacionadas con derecho de cobro fideicomitidos | C51: =IFERROR(L51/$A$6*C$1,0) -> -77.447648 | D51: =IFERROR(M51/$A$6*D$1,0) -> -141.61336 | E51: =IFERROR(N51/$A$6*E$1,0) -> -147.63819 | F51: =IFERROR(O51/$A$6*F$1,0) -> -138.91903 | G51: =IFERROR(P51/$A$6*G$1,0) -> -127.09678 | H51: =IFERROR(Q51/$A$6*H$1,0) -> -482.00826 | I51: =IFERROR(R51/$A$6*I$1,0) -> 0 | J51: =IFERROR(S51/$A$6*J$1,0) -> 0 | L51: -51680 | M51: -97503 | N51: -108144 | O51: -106378 | P51: -99911 | Q51: -390069 | T51: =C51/C$58 -> -0.040692529 | U51: =D51/D$58 -> 0.091809956 | V51: =E51/E$58 -> -0.19038766 | W51: =F51/F$58 -> 1.0939399 | X51: =G51/G$58 -> 0.27031246 | Y51: =H51/H$58 -> -0.08653276 | Z51: =I51/I$58 -> 0 | AA51: =J51/J$58 -> 0
B52: Prima en venta de acciones | C52: =IFERROR(L52/$A$6*C$1,0) -> 0 | D52: =IFERROR(M52/$A$6*D$1,0) -> 0 | E52: =IFERROR(N52/$A$6*E$1,0) -> 0 | F52: =IFERROR(O52/$A$6*F$1,0) -> 108.20296 | G52: =IFERROR(P52/$A$6*G$1,0) -> 309.58207 | H52: =IFERROR(Q52/$A$6*H$1,0) -> 0 | I52: =IFERROR(R52/$A$6*I$1,0) -> 61.454165 | J52: =IFERROR(S52/$A$6*J$1,0) -> 276.402 | O52: 82857 | P52: 243363 | R52: 56997 | S52: 276402 | T52: =C52/C$58 -> 0 | U52: =D52/D$58 -> 0 | V52: =E52/E$58 -> 0 | W52: =F52/F$58 -> -0.85206133 | X52: =G52/G$58 -> -0.65842652 | Y52: =H52/H$58 -> 0 | Z52: =I52/I$58 -> 0.014216492 | AA52: =J52/J$58 -> 0.10866811
B53: Recompra de acciones | C53: =IFERROR(L53/$A$6*C$1,0) -> 0 | D53: =IFERROR(M53/$A$6*D$1,0) -> -91.357412 | E53: =IFERROR(N53/$A$6*E$1,0) -> -23.837757 | F53: =IFERROR(O53/$A$6*F$1,0) -> -151.55231 | G53: =IFERROR(P53/$A$6*G$1,0) -> -492.23909 | H53: =IFERROR(Q53/$A$6*H$1,0) -> 332.40577 | I53: =IFERROR(R53/$A$6*I$1,0) -> 233.48098 | J53: =IFERROR(S53/$A$6*J$1,0) -> 596.725 | L53: 0 | M53: -62901 | N53: -17461 | O53: -116052 | P53: -386950 | Q53: 269002 | R53: 216547 | S53: 596725 | T53: =C53/C$58 -> 0 | U53: =D53/D$58 -> 0.059228312 | V53: =E53/E$58 -> -0.030740115 | W53: =F53/F$58 -> 1.1934227 | X53: =G53/G$58 -> 1.0469058 | Y53: =H53/H$58 -> 0.059675302 | Z53: =I53/I$58 -> 0.054012292 | AA53: =J53/J$58 -> 0.23460386
B54: Recompra de acciones propias | C54: =IFERROR(L54/$A$6*C$1,0) -> 0 | D54: =IFERROR(M54/$A$6*D$1,0) -> 0 | E54: =IFERROR(N54/$A$6*E$1,0) -> 0 | F54: =IFERROR(O54/$A$6*F$1,0) -> 0 | G54: =IFERROR(P54/$A$6*G$1,0) -> 0 | H54: =IFERROR(Q54/$A$6*H$1,0) -> -271.79221 | I54: =IFERROR(R54/$A$6*I$1,0) -> -324.30207 | J54: =IFERROR(S54/$A$6*J$1,0) -> -567.706 | Q54: -219950 | R54: -300781 | S54: -567706 | T54: =C54/C$58 -> 0 | U54: =D54/D$58 -> 0 | V54: =E54/E$58 -> 0 | W54: =F54/F$58 -> 0 | X54: =G54/G$58 -> 0 | Y54: =H54/H$58 -> -0.048793625 | Z54: =I54/I$58 -> -0.07502238 | AA54: =J54/J$58 -> -0.22319497
B55: Otras partidas | C55: =IFERROR(L55/$A$6*C$1,0) -> -5.9839098 | D55: =IFERROR(M55/$A$6*D$1,0) -> 13.410009 | E55: =IFERROR(N55/$A$6*E$1,0) -> 0 | F55: =IFERROR(O55/$A$6*F$1,0) -> 0 | G55: =IFERROR(P55/$A$6*G$1,0) -> 0 | H55: =IFERROR(Q55/$A$6*H$1,0) -> 0 | I55: =IFERROR(R55/$A$6*I$1,0) -> 0 | J55: =IFERROR(S55/$A$6*J$1,0) -> 0 | L55: -3993 | M55: 9233 | T55: =C55/C$58 -> -0.0031440648 | U55: =D55/D$58 -> -0.0086939 | V55: =E55/E$58 -> 0 | W55: =F55/F$58 -> 0 | X55: =G55/G$58 -> 0 | Y55: =H55/H$58 -> 0 | Z55: =I55/I$58 -> 0 | AA55: =J55/J$58 -> 0
B56: Flujos netos de efectivo de actividades de financiamiento | C56: =SUM(C43:C55) -> -622.07186 | D56: =IFERROR(M56/$A$6*D$1,0) -> -1660.0888 | E56: =IFERROR(N56/$A$6*E$1,0) -> -1969.0703 | F56: =IFERROR(O56/$A$6*F$1,0) -> 2559.8187 | G56: =IFERROR(P56/$A$6*G$1,0) -> -3916.7234 | H56: =IFERROR(Q56/$A$6*H$1,0) -> -6516.7803 | I56: =IFERROR(R56/$A$6*I$1,0) -> 3803.8648 | J56: =IFERROR(S56/$A$6*J$1,0) -> -9515.751 | L56: =SUM(L43:L55) -> -415102 | M56: =SUM(M43:M55) -> -1142997 | N56: =SUM(N43:N55) -> -1442331 | O56: =SUM(O43:O55) -> 1960195 | P56: =SUM(P43:P55) -> -3078943 | Q56: =SUM(Q43:Q55) -> -5273756 | R56: =SUM(R43:R55) -> 3527977 | S56: =SUM(S43:S55) -> -9515751 | T56: =C56/C$58 -> -0.32684888 | U56: =D56/D$58 -> 1.0762592 | V56: =E56/E$58 -> -2.5392257 | W56: =F56/F$58 -> -20.157698 | X56: =G56/G$58 -> 8.3301805 | Y56: =H56/H$58 -> -1.169928 | Z56: =I56/I$58 -> 0.87996659 | AA56: =J56/J$58 -> -3.7411402
B58: (Disminución) aumento neto de efectivo | C58: =IFERROR(L58/$A$6*C$1,0) -> 1903.24 | D58: =IFERROR(M58/$A$6*D$1,0) -> -1542.4619 | E58: =IFERROR(N58/$A$6*E$1,0) -> 775.4609 | F58: =IFERROR(O58/$A$6*F$1,0) -> -126.98963 | G58: =IFERROR(P58/$A$6*G$1,0) -> -470.1847 | H58: =IFERROR(Q58/$A$6*H$1,0) -> 5570.2403 | I58: =IFERROR(R58/$A$6*I$1,0) -> 4322.7378 | J58: =IFERROR(S58/$A$6*J$1,0) -> 2543.543 | L58: 1270012 | M58: -1062009 | N58: 568020 | O58: -97243 | P58: -369613 | Q58: 4507761 | R58: 4009217 | S58: 2543543 | T58: =C58/C$58 -> 1 | U58: =D58/D$58 -> 1 | V58: =E58/E$58 -> 1 | W58: =F58/F$58 -> 1 | X58: =G58/G$58 -> 1 | Y58: =H58/H$58 -> 1 | Z58: =I58/I$58 -> 1 | AA58: =J58/J$58 -> 1
B59: Efectos de las variaciones del tipo de cambio en el balance de efectivo en moneda extranjera | C59: =IFERROR(L59/$A$6*C$1,0) -> -22.831171 | D59: =IFERROR(M59/$A$6*D$1,0) -> -62.518558 | E59: =IFERROR(N59/$A$6*E$1,0) -> 14.800133 | F59: =IFERROR(O59/$A$6*F$1,0) -> -225.8332 | G59: =IFERROR(P59/$A$6*G$1,0) -> 129.86487 | H59: =IFERROR(Q59/$A$6*H$1,0) -> -58.253369 | I59: =IFERROR(R59/$A$6*I$1,0) -> -380.2585 | J59: =IFERROR(S59/$A$6*J$1,0) -> -79.243 | L59: -15235 | M59: -43045 | N59: 10841 | O59: -172933 | P59: 102087 | Q59: -47142 | R59: -352679 | S59: -79243
B60: Efectivo al principio del período | C60: =IFERROR(L60/$A$6*C$1,0) -> 1188.6326 | D60: =IFERROR(M60/$A$6*D$1,0) -> 2974.4266 | E60: =IFERROR(N60/$A$6*E$1,0) -> 1287.2266 | F60: =IFERROR(O60/$A$6*F$1,0) -> 1987.2481 | G60: =IFERROR(P60/$A$6*G$1,0) -> 1592.1222 | H60: =IFERROR(Q60/$A$6*H$1,0) -> 1215.9832 | I60: =IFERROR(R60/$A$6*I$1,0) -> 5870.4356 | J60: =IFERROR(S60/$A$6*J$1,0) -> 9101.201 | L60: 793162 | M60: 2047939 | N60: 942885 | O60: 1521746 | P60: 1251570 | Q60: 984044 | R60: 5444663 | S60: 9101201
B61: Efectivo al final del período | C61: =SUM(C58:C60) -> 3069.0414 | D61: =SUM(D58:D60) -> 1369.4462 | E61: =SUM(E58:E60) -> 2077.4876 | F61: =SUM(F58:F60) -> 1634.4253 | G61: =SUM(G58:G60) -> 1251.8024 | H61: =SUM(H58:H60) -> 6727.9701 | I61: =SUM(I58:I60) -> 9812.9149 | J61: =SUM(J58:J60) -> 11565.501 | L61: =SUM(L58:L60) -> 2047939 | M61: =SUM(M58:M60) -> 942885 | N61: =SUM(N58:N60) -> 1521746 | O61: =SUM(O58:O60) -> 1251570 | P61: =SUM(P58:P60) -> 984044 | Q61: =SUM(Q58:Q60) -> 5444663 | R61: =SUM(R58:R60) -> 9101201 | S61: =SUM(S58:S60) -> 11565501
B64: Flujo de efectivo | C64: 31 de diciembre | T64: Análisis horizontal
B65: Millones de pesos | C65: 2015 | D65: 2016 | E65: 2017 | F65: 2018 | G65: 2019 | H65: 2020 | I65: 2021 | J65: 2022 | T65: =D65 -> 2016 | U65: =E65 -> 2017 | V65: =F65 -> 2018 | W65: =G65 -> 2019 | X65: =H65 -> 2020 | Y65: =I65 -> 2021 | Z65: =J65 -> 2022 | AA65: Promedio
B66: Depreciación y amortización | C66: =C10 -> 1982.3915 | D66: =D10 -> 2218.6165 | E66: =E10 -> 2234.3218 | F66: =F10 -> 3986.5314 | G66: =G10 -> 4516.0326 | H66: =H10 -> 4694.2439 | I66: =I10 -> 5822.5366 | J66: =J10 -> 7680.74 | T66: =D66/C66-1 -> 0.11916162 | U66: =E66/D66-1 -> 0.0070788666 | V66: =F66/E66-1 -> 0.78422434 | W66: =G66/F66-1 -> 0.13282254 | X66: =H66/G66-1 -> 0.039461914 | Y66: =I66/H66-1 -> 0.24035665 | Z66: =J66/I66-1 -> 0.31913984 | AA66: =AVERAGE(T66:Z66) -> 0.23460654 | AC66: =AVERAGE(C66:J66) -> 4141.9268
B67: Gastos por intereses | C67: =C19 -> 813.01747 | D67: =D19 -> 940.08478 | E67: =E19 -> 917.80348 | F67: =F19 -> 2635.237 | G67: =G19 -> 2982.3151 | H67: =H19 -> 2849.7664 | I67: =I19 -> 2865.3704 | J67: =J19 -> 3382.48 | T67: =D67/C67-1 -> 0.15629099 | U67: =E67/D67-1 -> -0.023701372 | V67: =F67/E67-1 -> 1.8712432 | W67: =G67/F67-1 -> 0.13170659 | X67: =H67/G67-1 -> -0.044444888 | Y67: =I67/H67-1 -> 0.005475541 | Z67: =J67/I67-1 -> 0.18046867 | AA67: =AVERAGE(T67:Z67) -> 0.32529124
B68: Cuentas y documentos por pagar a proveedores | C68: =C27 -> 1572.5844 | D68: =D27 -> 1226.9759 | E68: =E27 -> 890.8517 | F68: =F27 -> 4864.4919 | G68: =G27 -> -320.64934 | H68: =H27 -> 1141.3605 | I68: =I27 -> 4781.7458 | J68: =J27 -> 2944.299 | T68: =D68/C68-1 -> -0.21977103 | U68: =E68/D68-1 -> -0.27394523 | V68: =F68/E68-1 -> 4.4604957 | W68: =G68/F68-1 -> -1.0659163 | X68: =H68/G68-1 -> -4.5595285 | Y68: =I68/H68-1 -> 3.1895141 | Z68: =J68/I68-1 -> -0.38426276 | AA68: =AVERAGE(T68:Z68) -> 0.16379799
B69: Adquisición de inmuebles y equipo | C69: =C34 -> -4287.0885 | D69: =D34 -> -4764.6926 | E69: =E34 -> -4088.4982 | F69: =F34 -> -5578.1375 | G69: =G34 -> -4821.0084 | H69: =H34 -> -2901.9512 | I69: =I34 -> -4460.0131 | J69: =J34 -> -5401.455 | T69: =D69/C69-1 -> 0.11140524 | U69: =E69/D69-1 -> -0.14191773 | V69: =F69/E69-1 -> 0.36434876 | W69: =G69/F69-1 -> -0.13573152 | X69: =H69/G69-1 -> -0.39806136 | Y69: =I69/H69-1 -> 0.53690146 | Z69: =J69/I69-1 -> 0.211085 | AA69: =AVERAGE(T69:Z69) -> 0.078289979
B70: Pago de préstamos | C70: =C43 -> -5029.4335 | D70: =D43 -> -2500.5317 | E70: =E43 -> -2299.8828 | F70: =F43 -> -1248.985 | G70: =G43 -> -737.83835 | H70: =H43 -> -4317.2677 | I70: =I43 -> -8879.3608 | J70: =J43 -> -3883.715 | T70: =D70/C70-1 -> -0.5028204 | U70: =E70/D70-1 -> -0.080242496 | V70: =F70/E70-1 -> -0.45693539 | W70: =G70/F70-1 -> -0.40924961 | X70: =H70/G70-1 -> 4.8512378 | Y70: =I70/H70-1 -> 1.0567084 | Z70: =J70/I70-1 -> -0.56261323 | AA70: =AVERAGE(T70:Z70) -> 0.55658359
B71: Adquisición de préstamos | C71: =C44 -> 5896.3586 | D71: =D44 -> 2819.6734 | E71: =E44 -> 2133.8281 | F71: =F44 -> 7857.4057 | G71: =G44 -> 1535.2402 | H71: =H44 -> 2471.4 | I71: =I44 -> 17571.177 | J71: =J44 -> 0 | T71: =D71/C71-1 -> -0.52179411 | U71: =E71/D71-1 -> -0.24323573 | V71: =F71/E71-1 -> 2.682305 | W71: =G71/F71-1 -> -0.80461232 | X71: =H71/G71-1 -> 0.60978062 | Y71: =I71/H71-1 -> 6.1098072 | Z71: =J71/I71-1 -> -1 | AA71: =AVERAGE(T71:Z71) -> 0.9760358
B72: (Disminución) aumento neto de efectivo | C72: =C58 -> 1903.24 | D72: =D58 -> -1542.4619 | E72: =E58 -> 775.4609 | F72: =F58 -> -126.98963 | G72: =G58 -> -470.1847 | H72: =H58 -> 5570.2403 | I72: =I58 -> 4322.7378 | J72: =J58 -> 2543.543 | T72: =D72/C72-1 -> -1.81044 | U72: =E72/D72-1 -> -1.5027423 | V72: =F72/E72-1 -> -1.1637602 | W72: =G72/F72-1 -> 2.7025439 | X72: =H72/G72-1 -> -12.84692 | Y72: =I72/H72-1 -> -0.22395847 | Z72: =J72/I72-1 -> -0.4115898 | AA72: =AVERAGE(T72:Z72) -> -2.1795523
